Workbook

Sheet legacy
A1: asset class | B1: region | C1: subregion | D1: description | E1: factor_name | G1: Active Vol
A2: Equities | B2: USD | C2: Equities | D2: S&P 500 | E2: SPX | F2: SPX
A3: Equities | B3: USD | C3: Equities | D3: Russell 2000 | E3: RTY | F3: RTY
A4: Equities | B4: USD | C4: Equities | D4: Dow Jones 30 | E4: DOW | F4: INDU
A5: Equities | B5: USD | C5: Equities | D5: Nasdaq 100 | E5: NDX | F5: NDX
A6: Equities | B6: USD | C6: Equities | D6: Technology | E6: XLK | F6: XLK
A7: Equities | B7: USD | C7: Sectors | D7: Industrials | E7: XLI | F7: XLI
A8: Equities | B8: USD | C8: Sectors | D8: Financials | E8: XLF | F8: XLF
A9: Equities | B9: USD | C9: Sectors | D9: Regional Banks | E9: KRE | F9: KRE | G9: 0
A10: Equities | B10: USD | C10: Sectors | D10: Communications | E10: XLC | F10: XLC
A11: Equities | B11: USD | C11: Sectors | D11: Energy | E11: XLE | F11: XLE
A12: Equities | B12: USD | C12: Sectors | D12: Discretionary | E12: XLY | F12: XLY
A13: Equities | B13: USD | C13: Sectors | D13: Materials | E13: XLB | F13: XLB
A14: Equities | B14: USD | C14: Sectors | D14: Health Care | E14: XLV | F14: XLV
A15: Equities | B15: USD | C15: Sectors | D15: Utilities | E15: XLU | F15: XLU
A16: Equities | B16: USD | D16: Staples | E16: XLP | F16: XLP
A17: Equities | B17: USD | D17: Real Estate | E17: REIT | F17: IYR
A18: Equities | B18: USD | D18: TSX 60 (Canada) | E18: TSX | F18: SPTSX60
A19: Equities | B19: EUR | D19: Eurostoxx 50 | E19: SX5E | F19: SX5E
A20: Equities | B20: EUR | D20: Eurostoxx Banks | E20: SX7E | F20: SX7E
A21: Equities | B21: EUR | D21: DAX (Germany) | E21: DAX | F21: DAX
A22: Equities | B22: EUR | D22: CAC 40 (France) | E22: CAC | F22: CAC
A23: Equities | B23: EUR | D23: FTSE 100 (UK) | E23: FTSE | F23: UKX
A24: Equities | B24: JPY | D24: Nikkei 225 (Japan) | E24: NKY | F24: NKY
A25: Equities | B25: JPY | D25: Topix (Japan domenstic) | E25: TPX | F25: TPX
A26: Equities | B26: EM | D26: Hang Seng (Hong Kong) | E26: HSI | F26: HSI
A27: Equities | B27: EM | D27: KOSPI 200 (Korea) | E27: KOSPI | F27: KOSPI2
A28: Equities | B28: EM | D28: NIFTY 50 (India) | E28: NIFTY | F28: NIFTY5
A29: Equities | B29: EM | D29: MSCI Brazil Index | E29: EWZ | F29: EWZ | G29: 0
A30: Equities | B30: EM | D30: CSI 300 (China) | E30: ASHR | F30: ASHR
A31: Equities | B31: EM | D31: FTSE China 50 | E31: FXI | F31: FXI
A32: Equities | B32: EM | D32: MSCI EM | E32: EEM | F32: EEM
A33: Credit | B33: USD | D33: US IG CDX | E33: IG | F33: IBOXUMAE
A34: Credit | B34: USD | D34: US HY CDX | E34: HY | F34: IBOXHYSE
A35: Credit | B35: USD | D35: US IG Bond ETF | E35: LQD | F35: LQD
A36: Credit | B36: USD | D36: US HY Bond ETF | E36: HYG | F36: HYG
A37: Credit | B37: USD | D37: Leveraged Loans | E37: LOAN | F37: BKLN | G37: 0
A38: Credit | B38: EUR | D38: Eur MAIN CDX (IG) | E38: MAIN | F38: ITRXEBE
A39: Credit | B39: EUR | D39: Eur XOVER CDX (HY) | E39: XOVER | F39: ITRXEXE
A40: Credit | B40: EUR | D40: Eur Sen Fin CDX | E40: SENFIN | F40: ITRXESE
A41: Rates | B41: USD | D41: US Agg Bond Index | E41: AGG | F41: AGG
A42: Rates | B42: USD | D42: 1-3 Year Treasury ETF | E42: SHY | F42: SHY | G42: 0
A43: Rates | B43: USD | D43: 7-10 Year Treasury ETF | E43: IEF | F43: IEF
A44: Rates | B44: USD | D44: 20+ Year Treasury ETF | E44: TLT | F44: TLT
A45: Rates | B45: USD | D45: TIPS ETF | E45: TIP | F45: TIP
A46: Rates | B46: USD | D46: Muni ETF | E46: MUB | F46: MUB
A47: Rates | B47: USD | D47: USD 2-year swap | E47: USD02
A48: Rates | B48: USD | D48: USD 5-year swap | E48: USD05
A49: Rates | B49: USD | D49: USD 10-year swap | E49: USD10
A50: Rates | B50: USD | D50: USD 20-year swap | E50: USD20
A51: Rates | B51: USD | D51: USD 30-year swap | E51: USD30
A52: Rates | B52: EUR | D52: EUR 2-year swap | E52: EUR02
A53: Rates | B53: EUR | D53: EUR 5-year swap | E53: EUR05
A54: Rates | B54: EUR | D54: EUR 10-year swap | E54: EUR10
A55: Rates | B55: EUR | D55: EUR 20-year swap | E55: EUR20
A56: Rates | B56: EUR | D56: EUR 30-year swap | E56: EUR30
A57: Rates | B57: GBP | D57: GBP 2-year swap | E57: GBP02
A58: Rates | B58: GBP | D58: GBP 5-year swap | E58: GBP05
... A61: Rates | B61: GBP | D61: GBP 30-year swap | E61: GBP30
A62: Currencies | B62: G7 | D62: Euro | E62: EUR | F62: EURUSD
A63: Currencies | B63: G7 | D63: Japanese Yen | E63: JPY | F63: USDJPY
A64: Currencies | B64: G7 | D64: British Pound | E64: GBP | F64: GBPUSD
A65: Currencies | B65: AUD | D65: Australian Dollar | E65: AUD | F65: AUDUSD
A66: Currencies | B66: AUD | D66: New Zealand Dollar | E66: NZD | F66: NZDUSD
A67: Currencies | B67: Commdty | D67: Canadian Dollar | E67: CAD | F67: USDCAD
A68: Currencies | B68: Commdty | D68: Swiss Franc | E68: CHF | F68: USDCHF
A69: Currencies | B69: Commdty | D69: Swedish Krona | E69: SEK | F69: USDSEK
A70: Currencies | B70: Commdty | D70: Norwegian Krone | E70: NOK | F70: USDNOK
A71: Currencies | B71: Asia | D71: Chinese Yuan | E71: CNH | F71: USDCNH
A72: Currencies | B72: Asia | D72: Indian Rupee | E72: INR | F72: USDINR | G72: 0
A73: Currencies | B73: Asia | D73: New Taiwan Dollar | E73: TWD | F73: USDTWD | G73: 0
A74: Currencies | B74: Asia | D74: South Korean Won | E74: KRW | F74: USDKRW | G74: 0
A75: Currencies | B75: EM | D75: Brazilian Real | E75: BRL | F75: USDBRL
A76: Currencies | B76: EM | D76: Mexican Peso | E76: MXN | F76: USDMXN
A77: Currencies | B77: EM | D77: Turkish Lira | E77: TRY | F77: USDTRY
A78: Currencies | B78: EM | D78: Russian Ruble | E78: RUB | F78: USDRUB
A79: Commodities | B79: Commodities | D79: Gold | E79: GOLD | F79: GLD
A80: Commodities | B80: Commodities | D80: Crude Oil | E80: CRUDE | F80: USO
A81: Commodities | B81: Commodities | D81: GSCI | E81: GSCI | F81: GSG

Sheet gpt
A1: Asset Class | B1: Region | C1: Ticker | D1: Description | E1: Underlying
A2: Equities | B2: USD | C2: SPY | D2: SPDR S&P 500 ETF Trust | E2: S&P 500 Index
A3: Equities | B3: USD | C3: IWM | D3: iShares Russell 2000 ETF | E3: Russell 2000 Index
A4: Equities | B4: USD | C4: QQQ | D4: Invesco QQQ Trust | E4: Nasdaq-100 Index
A5: Equities | B5: USD | C5: DIA | D5: SPDR Dow Jones Industrial Average ETF Trust | E5: Dow Jones Industrial Average
A6: Equities | B6: USD | C6: MDY | D6: SPDR S&P MidCap 400 ETF Trust | E6: S&P MidCap 400 Index
A7: Equities | B7: USD | C7: VNQ | D7: Vanguard Real Estate ETF | E7: MSCI US REIT Index
A8: Equities | B8: USD | C8: PFF | D8: iShares Preferred and Income Securities ETF | E8: U.S. preferred stocks
A9: Equities | B9: USD | C9: XLK | D9: Technology Select Sector SPDR Fund | E9: U.S. technology sector
A10: Equities | B10: USD | C10: XLI | D10: Industrial Select Sector SPDR Fund | E10: U.S. industrial sector
A11: Equities | B11: USD | C11: XLF | D11: Financial Select Sector SPDR Fund | E11: U.S. financial sector
A12: Equities | B12: USD | C12: KRE | D12: SPDR S&P Regional Banking ETF | E12: U.S. regional banking sector
... A61: Commodities | B61: USD | C61: DBC | D61: Invesco DB Commodity Index Tracking Fund | E61: Broad commodity index

Sheet data_new
A5: {=_xlfn.XMATCH(C5:C65,data[factor_name])} -> 1 | C5: SPY | D5: {=IF(G5:G65<>0,G5:G65,_xlfn.XLOOKUP(C5:C65,data[factor_name],data[description]))} -> S&P 500 | E5: {=IF(ISERROR(_xlfn.ANCHORARRAY(M5)),#N/A,IFERROR(_xlfn.ANCHORARRAY(N5),_xlfn.ANCHORARRAY(O5)))} -> SPDR S&P 500 ETF Trust | F5: {=_xlfn.XLOOKUP(C5:C65,legacy!E2:E81,legacy!D2:D81)} -> #N/A | M5: {=IFERROR(_xlfn.ANCHORARRAY(N5)<>_xlfn.ANCHORARRAY(O5),0)} -> FALSE | N5: {=_xlfn.LET(_xlpm.x,_xlfn.XLOOKUP(C5:C65,data[factor_name],data[Description_GPT]),IF(_xlpm.x=0,#N/A,_xlpm.x))} -> SPDR S&P 500 ETF Trust | O5: {=_xlfn.XLOOKUP(C5:C65,gpt!C2:C61,gpt!D2:D61)} -> SPDR S&P 500 ETF Trust
A6: 3 | C6: MDY | D6: S&P 400 | E6: SPDR S&P MidCap 400 ETF Trust | F6: #N/A | G6: S&P 400 | M6: FALSE | N6: SPDR S&P MidCap 400 ETF Trust | O6: SPDR S&P MidCap 400 ETF Trust
A7: 2 | C7: IWM | D7: Russell 2000 | E7: iShares Russell 2000 ETF | F7: #N/A | M7: FALSE | N7: iShares Russell 2000 ETF | O7: iShares Russell 2000 ETF
A8: 5 | C8: QQQ | D8: Nasdaq 100 | E8: Invesco QQQ Trust | F8: #N/A | M8: FALSE | N8: Invesco QQQ Trust | O8: Invesco QQQ Trust
A9: 6 | C9: DIA | D9: Dow Jones 30 | E9: SPDR Dow Jones Industrial Average ETF Trust | F9: #N/A | M9: FALSE | N9: SPDR Dow Jones Industrial Average ETF Trust | O9: SPDR Dow Jones Industrial Average ETF Trust
A10: 7 | C10: XLK | D10: Technology | E10: Technology Select Sector SPDR Fund | F10: Technology | G10: Technology | M10: FALSE | N10: Technology Select Sector SPDR Fund | O10: Technology Select Sector SPDR Fund
A11: 8 | C11: XLI | D11: Industrials | E11: Industrial Select Sector SPDR Fund | F11: Industrials | G11: Industrials | M11: FALSE | N11: Industrial Select Sector SPDR Fund | O11: Industrial Select Sector SPDR Fund
A12: 9 | C12: XLF | D12: Financials | E12: Financial Select Sector SPDR Fund | F12: Financials | G12: Financials | M12: FALSE | N12: Financial Select Sector SPDR Fund | O12: Financial Select Sector SPDR Fund
A13: 10 | C13: KRE | D13: Regional Banks | E13: SPDR S&P Regional Banking ETF | F13: Regional Banks | G13: Regional Banks | M13: FALSE | N13: SPDR S&P Regional Banking ETF | O13: SPDR S&P Regional Banking ETF
A14: 11 | C14: XLC | D14: Communications | E14: Communication Services Select Sector SPDR | F14: Communications | G14: Communications | M14: FALSE | N14: Communication Services Select Sector SPDR | O14: Communication Services Select Sector SPDR
A15: 12 | C15: XLE | D15: Energy | E15: Energy Select Sector SPDR Fund | F15: Energy | G15: Energy | M15: FALSE | N15: Energy Select Sector SPDR Fund | O15: Energy Select Sector SPDR Fund
A16: 13 | C16: XLY | D16: Discretionary | E16: Consumer Discretionary Select Sector SPDR | F16: Discretionary | G16: Discretionary | M16: FALSE | N16: Consumer Discretionary Select Sector SPDR | O16: Consumer Discretionary Select Sector SPDR
A17: 14 | C17: XLB | D17: Materials | E17: Materials Select Sector SPDR Fund | F17: Materials | G17: Materials | M17: FALSE | N17: Materials Select Sector SPDR Fund | O17: Materials Select Sector SPDR Fund
A18: 15 | C18: XLV | D18: Health Care | E18: Health Care Select Sector SPDR Fund | F18: Health Care | G18: Health Care | M18: FALSE | N18: Health Care Select Sector SPDR Fund | O18: Health Care Select Sector SPDR Fund
A19: 16 | C19: XLU | D19: Utilities | E19: Utilities Select Sector SPDR Fund | F19: Utilities | G19: Utilities | M19: FALSE | N19: Utilities Select Sector SPDR Fund | O19: Utilities Select Sector SPDR Fund
A20: 17 | C20: XLP | D20: Staples | E20: Consumer Staples Select Sector SPDR Fund | F20: Staples | G20: Staples | M20: FALSE | N20: Consumer Staples Select Sector SPDR Fund | O20: Consumer Staples Select Sector SPDR Fund
A21: 18 | C21: IYR | D21: Real Estate | E21: iShares U.S. Real Estate ETF | F21: #N/A | G21: Real Estate | M21: FALSE | N21: iShares U.S. Real Estate ETF | O21: iShares U.S. Real Estate ETF
A22: 19 | C22: VNQ | D22: Real Estate 2 | E22: Vanguard Real Estate ETF | F22: #N/A | G22: Real Estate 2 | M22: FALSE | N22: Vanguard Real Estate ETF | O22: Vanguard Real Estate ETF
A23: 22 | C23: AIQ | D23: AI | E23: Global X Artificial Intelligence & Technology ETF | F23: #N/A | G23: AI | M23: FALSE | N23: Global X Artificial Intelligence & Technology ETF | O23: Global X Artificial Intelligence & Technology ETF
A24: 27 | C24: PFF | D24: Preferred | E24: iShares Preferred and Income Securities ETF | F24: #N/A | G24: Preferred | M24: FALSE | N24: iShares Preferred and Income Securities ETF | O24: iShares Preferred and Income Securities ETF
A25: 31 | C25: FEZ | D25: Eurostoxx 50 | E25: SPDR EURO STOXX 50 ETF | F25: #N/A | M25: FALSE | N25: SPDR EURO STOXX 50 ETF | O25: SPDR EURO STOXX 50 ETF
A26: 32 | C26: SX7E | D26: Eurostoxx Banks | E26: iShares STOXX Europe 600 Banks | F26: Eurostoxx Banks | M26: 0 | N26: #N/A | O26: iShares STOXX Europe 600 Banks
A27: 33 | C27: EWU | D27: FTSE 100 | E27: iShares FTSE United Kingdom ETF | F27: #N/A | M27: FALSE | N27: iShares FTSE United Kingdom ETF | O27: iShares FTSE United Kingdom ETF
A28: 34 | C28: DAX | D28: DAX (Germany) | E28: Xtrackers DAX Equity ETF | F28: DAX (Germany) | M28: FALSE | N28: Xtrackers DAX Equity ETF | O28: Xtrackers DAX Equity ETF
A29: 35 | C29: EWC | D29: MSCI Canada | E29: iShares MSCI Canada ETF | F29: #N/A | M29: 0 | N29: iShares MSCI Canada ETF | O29: #N/A
A30: 36 | C30: FTSEMIB.MI | D30: FTSE MIB (Italy) | E30: iShares MSCI Italy ETF | F30: #N/A | M30: 0 | N30: #N/A | O30: iShares MSCI Italy ETF
A31: 37 | C31: CAC | D31: CAC 40 (France) | E31: Lyxor CAC 40 ETF | F31: CAC 40 (France) | M31: FALSE | N31: Lyxor CAC 40 ETF | O31: Lyxor CAC 40 ETF
A32: 38 | C32: EWI | D32: MSCI Italy | E32: iShares MSCI Italy ETF | F32: #N/A | M32: FALSE | N32: iShares MSCI Italy ETF | O32: iShares MSCI Italy ETF
A33: 39 | C33: ^IBEX | D33: IBEX 35 (Spain) | E33: IBEX 35 ETF | F33: #N/A | M33: 0 | N33: #N/A | O33: IBEX 35 ETF
A34: 40 | C34: EWP | D34: MSCI Spain | E34: iShares MSCI Spain ETF | F34: #N/A | M34: FALSE | N34: iShares MSCI Spain ETF | O34: iShares MSCI Spain ETF
A35: 41 | C35: ^N225 | D35: Nikkei 225 | E35: Nikkei 225 ETF | F35: #N/A | M35: FALSE | N35: Nikkei 225 ETF | O35: Nikkei 225 ETF
A36: 42 | C36: TPX | D36: TOPIX | E36: iShares TOPIX ETF | F36: Topix (Japan domenstic) | M36: FALSE | N36: iShares TOPIX ETF | O36: iShares TOPIX ETF
A37: 43 | C37: FXI | D37: China Large-Cap | E37: iShares China Large-Cap ETF | F37: FTSE China 50 | M37: FALSE | N37: iShares China Large-Cap ETF | O37: iShares China Large-Cap ETF
A38: 44 | C38: ASHR | D38: CSI 300 (China) | E38: Xtrackers Harvest CSI 300 China A-Shares ETF | F38: CSI 300 (China) | M38: FALSE | N38: Xtrackers Harvest CSI 300 China A-Shares ETF | O38: Xtrackers Harvest CSI 300 China A-Shares ETF
A39: 45 | C39: KWEB | D39: CSI China Internet | E39: KraneShares CSI China Internet ETF | F39: #N/A | M39: FALSE | N39: KraneShares CSI China Internet ETF | O39: KraneShares CSI China Internet ETF
A40: 47 | C40: LQD | D40: iShares iBoxx $ Investment Grade Corporate Bond ETF | E40: iShares iBoxx $ Investment Grade Corporate Bond ETF | F40: US IG Bond ETF | M40: FALSE | N40: iShares iBoxx $ Investment Grade Corporate Bond ETF | O40: iShares iBoxx $ Investment Grade Corporate Bond ETF
A41: 49 | C41: HYG | D41: iShares iBoxx $ High Yield Corporate Bond ETF | E41: iShares iBoxx $ High Yield Corporate Bond ETF | F41: US HY Bond ETF | M41: FALSE | N41: iShares iBoxx $ High Yield Corporate Bond ETF | O41: iShares iBoxx $ High Yield Corporate Bond ETF
A42: 50 | C42: LQDH | D42: Hedged LQD | E42: iShares Interest Rate Hedged Corporate Bond ETF | F42: #N/A | M42: 0 | N42: #N/A | O42: iShares Interest Rate Hedged Corporate Bond ETF
A43: 51 | C43: HYGH | D43: Hedged HYG | E43: iShares Interest Rate Hedged High Yield Bond ETF | F43: #N/A | M43: 0 | N43: #N/A | O43: iShares Interest Rate Hedged High Yield Bond ETF
A44: 55 | C44: SHY | D44: 1-3 Year Treasury | E44: iShares 1-3 Year Treasury Bond ETF | F44: 1-3 Year Treasury ETF | M44: FALSE | N44: iShares 1-3 Year Treasury Bond ETF | O44: iShares 1-3 Year Treasury Bond ETF
A45: 56 | C45: IEI | D45: 3-7 Year Treasury | E45: iShares 3-7 Year Treasury Bond ETF | F45: #N/A | M45: FALSE | N45: iShares 3-7 Year Treasury Bond ETF | O45: iShares 3-7 Year Treasury Bond ETF
A46: 57 | C46: IEF | D46: 7-10 Year Treasury | E46: iShares 7-10 Year Treasury Bond ETF | F46: 7-10 Year Treasury ETF | M46: FALSE | N46: iShares 7-10 Year Treasury Bond ETF | O46: iShares 7-10 Year Treasury Bond ETF
A47: 58 | C47: TLT | D47: 20+ Year Treasury | E47: iShares 20+ Year Treasury Bond ETF | F47: 20+ Year Treasury ETF | M47: FALSE | N47: iShares 20+ Year Treasury Bond ETF | O47: iShares 20+ Year Treasury Bond ETF
A48: 59 | C48: TIP | D48: iShares TIPS Bond ETF | E48: iShares TIPS Bond ETF | F48: TIPS ETF | M48: FALSE | N48: iShares TIPS Bond ETF | O48: iShares TIPS Bond ETF
A49: 60 | C49: VTIP | D49: Short-Term Inflation-Protected Securities ETF | E49: Vanguard Short-Term Inflation-Protected Securities ETF | F49: #N/A | M49: 0 | N49: #N/A | O49: Vanguard Short-Term Inflation-Protected Securities ETF
A50: 61 | C50: MBB | D50: iShares MBS ETF | E50: iShares MBS ETF | F50: #N/A | M50: FALSE | N50: iShares MBS ETF | O50: iShares MBS ETF
A51: 62 | C51: MBTA | D51: Simplify Mortgage Backed Securities ETF | E51: Simplify Mortgage Backed Securities ETF | F51: #N/A | M51: FALSE | N51: Simplify Mortgage Backed Securities ETF | O51: Simplify Mortgage Backed Securities ETF
A52: 63 | C52: AGNC | D52: AGNC Investment Corp. | E52: AGNC Investment Corp. | F52: #N/A | M52: FALSE | N52: AGNC Investment Corp. | O52: AGNC Investment Corp.
A53: 64 | C53: VMBS | D53: Mortgage-Backed Securities ETF | E53: Vanguard Mortgage-Backed Securities ETF | F53: #N/A | M53: 0 | N53: #N/A | O53: Vanguard Mortgage-Backed Securities ETF
A54: 65 | C54: CMBS | D54: CMBS | E54: iShares CMBS ETF | F54: #N/A | G54: CMBS | M54: 0 | N54: #N/A | O54: iShares CMBS ETF
A55: 66 | C55: EMB | D55: iShares J.P. Morgan USD Emerging Markets Bond ETF | E55: iShares J.P. Morgan USD Emerging Markets Bond ETF | F55: #N/A | M55: FALSE | N55: iShares J.P. Morgan USD Emerging Markets Bond ETF | O55: iShares J.P. Morgan USD Emerging Markets Bond ETF
A56: 67 | C56: EMHY | D56: iShares JP Morgan EM High Yield Bond ETF | E56: iShares Emerging Markets High Yield Bond ETF | F56: #N/A | M56: 0 | N56: #N/A | O56: iShares Emerging Markets High Yield Bond ETF
A57: 68 | C57: CEW | D57: WisdomTree Emerging Markets Local Debt Fund | E57: WisdomTree Emerging Markets Local Debt Fund | F57: #N/A | M57: FALSE | N57: WisdomTree Emerging Markets Local Debt Fund | O57: WisdomTree Emerging Markets Local Debt Fund
A58: 69 | C58: IGOV | D58: iShares International Government Bonds ETF | E58: iShares International Government Bonds ETF | F58: #N/A | M58: FALSE | N58: iShares International Government Bonds ETF | O58: iShares International Government Bonds ETF
A59: 70 | C59: GLD | D59: SPDR Gold Shares | E59: SPDR Gold Shares | F59: #N/A | M59: FALSE | N59: SPDR Gold Shares | O59: SPDR Gold Shares
A60: 71 | C60: SLV | D60: iShares Silver Trust | E60: iShares Silver Trust | F60: #N/A | M60: FALSE | N60: iShares Silver Trust | O60: iShares Silver Trust
A61: 72 | C61: USO | D61: United States Oil Fund | E61: United States Oil Fund | F61: #N/A | M61: FALSE | N61: United States Oil Fund | O61: United States Oil Fund
A62: 75 | C62: DBC | D62: Invesco DB Commodity Index Tracking Fund | E62: Invesco DB Commodity Index Tracking Fund | F62: #N/A | M62: FALSE | N62: Invesco DB Commodity Index Tracking Fund | O62: Invesco DB Commodity Index Tracking Fund
A63: 79 | C63: UUP | D63: Invesco DB US Dollar Index Bullish Fund | E63: Invesco DB US Dollar Index Bullish Fund | F63: #N/A | M63: FALSE | N63: Invesco DB US Dollar Index Bullish Fund | O63: Invesco DB US Dollar Index Bullish Fund
A64: 81 | C64: FXE | D64: Invesco CurrencyShares Euro Trust | E64: Invesco CurrencyShares Euro Trust | F64: #N/A | M64: FALSE | N64: Invesco CurrencyShares Euro Trust | O64: Invesco CurrencyShares Euro Trust
A65: 86 | C65: FXY | D65: Invesco CurrencyShares Japanese Yen Trust | E65: Invesco CurrencyShares Japanese Yen Trust | F65: #N/A | M65: FALSE | N65: Invesco CurrencyShares Japanese Yen Trust | O65: Invesco CurrencyShares Japanese Yen Trust

Sheet lior
A1: tip | B1: {=_xlfn.XMATCH(A1:A9,data[factor_name])} -> 59 | D1: {=_xlfn.XLOOKUP(_xlfn._TRO_ALL(A:A),data[factor_name],data[Active])} -> 1
A2: vtip | B2: 60 | D2: 1
A3: cmbs | B3: 65 | D3: 1
A4: vmbs | B4: 64 | D4: 1
A5: gld | B5: 70 | D5: 1
A6: lqd | B6: 47 | D6: 1
A7: lqdh | B7: 50 | D7: 1
A8: hyg | B8: 49 | D8: 1
A9: hygh | B9: 51 | D9: 1
D10: #N/A
D11: #N/A
A12: {=_xlfn.TEXTSPLIT(data!#REF!,," ")} -> #REF! | B12: {=_xlfn.XMATCH(_xlfn.ANCHORARRAY(A12),data[factor_name])} -> #REF! | D12: #REF!
D13: #N/A
D14: #N/A
D15: #N/A
D16: #N/A
D17: #N/A
D18: #N/A
D19: #N/A
D20: #N/A
A21: XLK | D21: 1
A22: XLI | D22: 1
A23: XLF | D23: 1
A24: KRE | D24: 1
A25: XLC | D25: 1
A26: XLE | D26: 1
A27: XLY | D27: 1
A28: XLB | D28: 1
A29: XLV | D29: 1
A30: XLU | D30: 1
A31: XLP | D31: 1
A32: IYR | D32: 1

Sheet read_composites
A1: {=composities[#Headers]} -> portfolio_name | B1: factor_name | C1: weight
A2: {=composities[]} -> FED | B2: SHY | C2: 1
A3: FED | B3: BSV | C3: 1
A4: AI | B4: AIQ | C4: 1
A5: AI | B5: QQQ | C5: 0.25
A6: AI | B6: IWM | C6: -0.25
A7: GEOPOLITICS | B7: GLD | C7: 0.65
A8: GEOPOLITICS | B8: USO | C8: 0.3
A9: GEOPOLITICS | B9: ^VIX3M | C9: -0.15
A10: GEOPOLITICS | B10: FEZ | C10: -0.05
A11: 2s10s | B11: SHY | C11: -3.863388
A12: 2s10s | B12: IEF | C12: 1
A13: XLPXLY | B13: XLP | C13: 1
A14: XLPXLY | B14: XLY | C14: -1
... A28: PRIVATES | B28: LQDH | C28: -0.5

Sheet risk_parity
A1: SPY | B1: {=_xlfn.XLOOKUP(_xlfn._TRO_ALL(A:A),data[factor_name],data[asset_class],"")} -> Equities | F1: ="['"&_xlfn.TEXTJOIN("', '",,_xlfn._TRO_ALL(A:A))&"']" -> ['SPY', 'FEZ', '^N225', 'LQDH', 'HYGH', 'EMB', 'IEI', 'IEF', 'TLT', 'FXE', 'FXY', 'FXF', 'TIP', 'VMBS', 'CMBS', 'GLD', 'USO']
A2: FEZ | B2: Equities
A3: ^N225 | B3: Equities
A5: LQDH | B5: Credit
A6: HYGH | B6: Credit
A7: EMB | B7: Rates
A9: IEI | B9: Rates
A10: IEF | B10: Rates
A11: TLT | B11: Rates
A13: FXE | B13: Currencies
A14: FXY | B14: Currencies
A15: FXF | B15: Currencies
A17: TIP | B17: Rates
... A22: USO | B22: Commodities

Sheet tradewar
B1: {=TRANSPOSE(_xlfn.DROP(_xlfn._xlws.FILTER(composities[],composities[portfolio_name]="TRADEWAR"),,1))} -> GLD | C1: FXY | D1: FXF | E1: ^VIX3M | F1: XLP | G1: XLY
A2: =TODAY()-1 -> 46186 | B2: 0.20547945 | C2: 0.2970297 | D2: 0.36585366 | E2: -0.0375 | F2: 0.15 | G2: -0.15

Sheet tracking
A1: date | B1: SPY | C1: FEZ | D1: ^N225 | E1: LQDH | F1: HYGH | G1: EMB | H1: IEI | I1: IEF | J1: TLT | K1: FXE | L1: FXY | M1: FXF | N1: TIP | O1: VMBS | P1: CMBS | Q1: GLD | R1: USO
A2: {=DATE(_xlfn.SEQUENCE(12,,2025,-1),1,1)} -> 45658 | B2: 1
A3: 45292 | E3: 1
A4: 44927 | J4: 1
A5: 44562 | K5: 1
A6: 44197 | O6: 1
A7: 43831 | R7: 1
A8: 43466 | B8: 1
A9: 43101 | E9: 1
A10: 42736 | J10: 1
A11: 42370 | K11: 1
A12: 42005 | O12: 1
A13: 41640 | R13: 1

Sheet yf_desc
A1: ticker | B1: shortName | C1: longName | D1: longBusinessSummary | E1: Column1
A2: SPY | B2: SPDR S&P 500 | C2: SPDR S&P 500 ETF | D2: The trust seeks to achieve its investment objective by holding a portfolio of the common stocks that are included in the index, with the weight of each stock in the portfolio substantially corresponding to the weight of such stock in the index.
A3: IWM | B3: iShares Russell 2000 ETF | C3: iShares Russell 2000 ETF | D3: The fund generally invests at least 80% of its assets in the component securities of its underlying index and in investments that have economic characteristics that are substantially identical to the component securities of its underlying index (i.e., depositary receipts representing securities of the underlying index) and may invest up to 20% of its assets in certain futures, options and swap contracts, cash and cash equivalents.
A4: MDY | B4: SPDR S&P MidCap 400 ETF Trust | C4: SPDR S&P MIDCAP 400 ETF Trust | D4: The Trust seeks to achieve its investment objective by holding a portfolio of the common stocks that are included in the index (the “Portfolio”), with the weight of each stock in the Portfolio substantially corresponding to the weight of such stock in the index.
A5: RSP | B5: Invesco S&P 500 Equal Weight ET | C5: Invesco S&P 500 Equal Weight ETF | D5: The fund generally will invest at least 90% of its total assets in securities that comprise the underlying index. Strictly in accordance with its guidelines and mandated procedures, the index provider compiles, maintains and calculates the underlying index, which consists of all of the of the S&P 500® Index.
A6: QQQ | B6: Invesco QQQ Trust, Series 1 | C6: Invesco QQQ Trust | D6: To maintain the correspondence between the composition and weights of the securities in the trust (the "securities") and the stocks in the NASDAQ-100 Index®, the adviser adjusts the securities from time to time to conform to periodic changes in the identity and/or relative weights of index securities. The composition and weighting of the securities portion of a portfolio deposit are also adjusted to conform to changes in the index.
A7: DIA | B7: SPDR Dow Jones Industrial Avera | C7: SPDR Dow Jones Industrial Average ETF Trust | D7: The Trust’s Portfolio consists of substantially all of the component common stocks that comprise the DJIA, which are weighted in accordance with the terms of the Trust Agreement.
A8: XLK | B8: SPDR Select Sector Fund - Techn | C8: The Technology Select Sector SPDR Fund | D8: In seeking to track the performance of the index, the fund employs a replication strategy, which means that the fund typically invests in substantially all of the securities represented in the index in approximately the same proportions as the index. It generally invests substantially all, but at least 95%, of its total assets in the securities comprising the index. The fund is non-diversified.
A9: XLI | B9: SPDR Select Sector Fund - Indus | C9: The Industrial Select Sector SPDR Fund | D9: Under normal market conditions, the fund generally invests substantially all, but at least 95%, of its total assets in the securities comprising the index. The index includes companies that have been identified as Industrial companies by the Global Industry Classification Standard, including securities of companies from the following industries: aerospace and defense; industrial conglomerates; marine transportation. It is non-diversified.
A10: XLF | B10: SPDR Select Sector Fund - Finan | C10: The Financial Select Sector SPDR Fund | D10: The fund generally invests substantially all, but at least 95%, of its total assets in the securities comprising the index. The index includes companies that have been identified as Financial companies by the Global Industry Classification Standard, including securities of companies from the following industries: financial services; insurance; banks; capital markets; mortgage real estate investment trusts; and consumer finance. The fund is non-diversified.
A11: KRE | B11: SPDR S&P Regional Banking ETF | C11: SPDR S&P Regional Banking ETF | D11: In seeking to track the performance of the S&P Regional Banks Select Industry Index (the "index"), the fund employs a sampling strategy. It generally invests substantially all, but at least 80%, of its total assets in the securities comprising the index. The index represents the regional banks segment of the S&P Total Market Index ("S&P TMI").
A12: XLC | B12: The Communication Services Sele | C12: The Communication Services Select Sector SPDR ETF Fund | D12: Normally, the fund generally invests substantially all, but at least 95%, of its total assets in the securities comprising the index. The index includes companies that have been identified as Communication Services companies by the GICS®, including securities of companies from the following industries: diversified telecommunication services; wireless telecommunication services; media; entertainment; and interactive media & services. The fund is non-diversified.
A13: XLE | B13: SPDR Select Sector Fund - Energ | C13: The Energy Select Sector SPDR Fund | D13: In seeking to track the performance of the index, the fund employs a replication strategy. It generally invests substantially all, but at least 95%, of its total assets in the securities comprising the index. The index includes companies that have been identified as Energy companies by the GICS®, including securities of companies from the following industries: oil, gas and consumable fuels; and energy equipment and services. It is non-diversified.
... A27: EWC | B27: iShares MSCI Canada Index Fund | C27: iShares MSCI Canada ETF | D27: The fund generally will invest at least 80% of its assets in the component securities of its underlying index and in investments that have economic characteristics that are substantially identical to the component securities of its underlying index. The underlying index is designed to measure broad-based equity performance in Canada. The underlying index includes large- and mid-capitalization companies and may change over time.
A28: FTSEMIB.MI | B28: FTSE MIB Index | C28: FTSE MIB Index
A29: CAC | B29: Camden National Corporation | C29: Camden National Corporation | D29: Camden National Corporation operates as the bank holding company for Camden National Bank that provides various commercial and consumer banking products and services for consumer, institutional, municipal, non-profit, and commercial customers in the United States. The company accepts checking, savings, time, and brokered deposits, as well as deposits with the certificate of deposit account registry system. Its loan products include non-owner-occupied commercial real estate loans; owner-occupied commercial real estate loans; commercial loans; residential real estate loans, including one- to four-family residences; and consumer and home equity loans. In addition, the company provides brokerage and insurance services through its financial offerings consisting of college, retirement, estate planning, mutual funds, strategic asset management accounts, and variable and fixed annuities. Further, it offers a range of fiduciary and asset management, wealth management, investment management and advisory, financial planning, and trustee services. Camden National Corporation was founded in 1875 and is headquartered in Camden, Maine.
A30: EWI | B30: iShares Inc iShares MSCI Italy | C30: iShares MSCI Italy ETF | D30: The fund generally will invest at least 80% of its assets in the component securities of its underlying index and in investments that have economic characteristics that are substantially identical to the component securities of its underlying index. The underlying index is a free float-adjusted market capitalization-weighted index that is designed to measure the performance of the large- and mid-capitalization segments of the equity market in Italy. The fund is non-diversified.
A31: ^IBEX | B31: IBEX 35... | C31: IBEX 35...
A32: EWP | B32: iShares Inc iShares MSCI Spain | C32: iShares MSCI Spain ETF | D32: The fund generally will invest at least 80% of its assets in the component securities of its underlying index and in investments that have economic characteristics that are substantially identical to the component securities of its underlying index. The index is a free float-adjusted market capitalization-weighted index that is designed to measure the performance of the large- and mid-capitalization segments of the equity market in Spain. The fund is non-diversified.
A33: ^N225 | B33: Nikkei 225 | C33: Nikkei 225
A34: FXI | B34: iShares China Large-Cap ETF | C34: iShares China Large-Cap ETF | D34: The fund generally will invest at least 80% of its assets in the component securities of its underlying index and in investments that have economic characteristics that are substantially identical to the component securities of its underlying index. The index designed to measure the performance of the largest companies in the Chinese equity market that trade on the Stock Exchange of Hong Kong and are available to international investors. The fund is non-diversified.
A35: ASHR | B35: Xtrackers Harvest CSI 300 China | C35: Xtrackers Harvest CSI 300 China A-Shares ETF | D35: The fund will normally invest at least 80% of its total assets in securities of issuers that comprise the underlying index. The underlying index is designed to reflect the price fluctuation and performance of the China A-Share market and is composed of the 300 largest and most liquid stocks in the China A-Share market. The underlying index includes small-cap, mid-cap, and large-cap stocks. It is non-diversified.
A36: KWEB | B36: KraneShares Trust KraneShares C | C36: KraneShares CSI China Internet ETF | D36: The fund will invest at least 80% of its net assets in instruments in its underlying index or in instruments that have economic characteristics similar to those in the underlying index. The index is designed to measure the equity market performance of investable publicly traded "China-based companies" whose primary business or businesses are in the Internet and Internet-related sectors, and are listed outside of Mainland China, as determined by the index provider. The fund is non-diversified.
A37: EEM | B37: iShares MSCI Emerging Index Fun | C37: iShares MSCI Emerging Markets ETF | D37: The fund generally will invest at least 80% of its assets in the component securities of its underlying index and in investments that have economic characteristics that are substantially identical to the component securities of its underlying index. The index is designed to measure equity market performance in the global emerging markets. The underlying index includes large- and mid-capitalization companies and may change over time.
A38: LQD | B38: iShares iBoxx $ Investment Grad | C38: iShares iBoxx $ Investment Grade Corporate Bond ETF | D38: The fund will invest at least 80% of its assets in the component securities of the underlying index, and it will invest at least 90% of its assets in fixed income securities of the types included in the underlying index that the advisor believes will help the fund track the underlying index. The underlying index is designed to provide a broad representation of the U.S. dollar-denominated liquid investment-grade corporate bond market.
A39: BSV | B39: Vanguard Short-Term Bond ETF | C39: Vanguard Short-Term Bond Index Fund ETF Shares | D39: This index includes all medium and larger issues of U.S. government, investment-grade corporate, and investment-grade international dollar-denominated bonds that have maturities between 1 and 5 years and are publicly issued. All of the fund's investments will be selected through the sampling process, and at least 80% of its assets will be invested in bonds held in the index.
A40: HYG | B40: iShares iBoxx $ High Yield Corp | C40: iShares iBoxx $ High Yield Corporate Bond ETF | D40: The underlying index is a rules-based index consisting of U.S. dollar-denominated, high yield corporate bonds for sale in the U.S. The fund will invest at least 80% of its assets in the component securities of the underlying index, and the fund will invest at least 90% of its assets in fixed income securities of the types included in the underlying index that the advisor believes will help the fund track the underlying index.
A41: LQDH | B41: iShares Interest Rate Hedged Co | C41: iShares Interest Rate Hedged Corporate Bond ETF | D41: The index is designed to minimize the interest-rate risk exposure of a portfolio composed of U.S. dollar-denominated, investment grade bonds, represented in the index by the underlying fund, by including a series of up to 10 interest rate swap contracts with different maturities. The fund invests, under normal circumstances, at least 80% of its net assets, plus the amount of any borrowings for investment purposes, in component securities and instruments in the index and/or bonds included in the underlying index of the underlying fund.
A42: HYGH | B42: iShares Interest Rate Hedged Hi | C42: iShares Interest Rate Hedged High Yield Bond ETF | D42: The fund seeks to track the investment results of the underlying index, which is designed to minimize the interest-rate risk of a portfolio composed of U.S. dollar-denominated, high yield corporate bonds, represented in the underlying index by the underlying fund. It invests at least 80% of its net assets in component securities and instruments in the fund’s underlying index.
A43: AGG | B43: iShares Core U.S. Aggregate Bon | C43: iShares Core U.S. Aggregate Bond ETF | D43: The index measures the performance of the total U.S. investment-grade bond market. The fund will invest at least 80% of its assets in the component securities of the underlying index and TBAs that have economic characteristics that are substantially identical to the economic characteristics of the component securities of the underlying index, and the fund will invest at least 90% of its assets in fixed income securities of the types included in the underlying index that the advisor believes will help the fund track the underlying index.
A44: ^TNX | B44: CBOE Interest Rate 10 Year T No | C44: CBOE Interest Rate 10 Year T No
A45: SHY | B45: iShares 1-3 Year Treasury Bond | C45: iShares 1-3 Year Treasury Bond ETF | D45: The fund will invest at least 80% of its assets in the component securities of the underlying index and it will invest at least 90% of its assets in U.S. Treasury securities that BFA believes will help the fund track the underlying index. The underlying index measures the performance of public obligations of the U.S. Treasury that have a remaining maturity of greater than or equal to one year and less than three years.
A46: IEI | B46: iShares 3-7 Year Treasury Bond | C46: iShares 3-7 Year Treasury Bond ETF | D46: The index measures the performance of public obligations of the U.S. Treasury that have a remaining maturity of greater than or equal to three years and less than seven years. The fund will invest at least 80% of its assets in the component securities of the index, and the fund will invest at least 90% of its assets in U.S. Treasury securities that BFA believes will help the fund track the index.
A47: IEF | B47: iShares 7-10 Year Treasury Bond | C47: iShares 7-10 Year Treasury Bond ETF | D47: The underlying index measures the performance of public obligations of the U.S. Treasury that have a remaining maturity of greater than or equal to seven years and less than ten years. The fund will invest at least 80% of its assets in the component securities of the underlying index, and the fund will invest at least 90% of its assets in U.S. Treasury securities that the advisor believes will help the fund track the underlying index.
A48: TLT | B48: iShares 20+ Year Treasury Bond | C48: iShares 20+ Year Treasury Bond ETF | D48: The fund will invest at least 80% of its assets in the component securities of the underlying index, and it will invest at least 90% of its assets in U.S. Treasury securities that the advisor believes will help the fund track the underlying index. The underlying index measures the performance of public obligations of the U.S. Treasury that have a remaining maturity greater than or equal to twenty years.
A49: TIP | B49: iShares TIPS Bond ETF | C49: iShares TIPS Bond ETF | D49: The index tracks the performance of inflation-protected public obligations of the U.S. Treasury, commonly known as “TIPS,” that have a remaining maturity of more than one year. The fund will invest at least 80% of its assets in the component securities of the index, and it will invest at least 90% of its assets in U.S. Treasury securities that BFA believes will help the fund track the index.
A50: VTIP | B50: Vanguard Short-Term Inflation-P | C50: Vanguard Short-Term Inflation-Protected Securities Index Fund ETF Shares | D50: The index is a market-capitalization-weighted index that includes all inflation-protected public obligations issued by the U.S. Treasury with remaining maturities of less than 5 years.
A51: MBB | B51: iShares MBS ETF | C51: iShares MBS ETF | D51: The fund will invest at least 80% of its assets in the component securities of the underlying index and TBAs that have economic characteristics that are substantially identical to the economic characteristics of the component securities of the index, and the fund will invest at least 90% of its assets in fixed income securities of the types included in the underlying index that BFA believes will help the fund track the index.
A52: AGNC | B52: AGNC Investment Corp. | C52: AGNC Investment Corp. | D52: AGNC Investment Corp. provides private capital to housing market in the United States. The company invests in residential mortgage pass-through securities and collateralized mortgage obligations for which the principal and interest payments are guaranteed by the United States government-sponsored enterprise or by the United States government agency. It qualifies as a real estate investment trust for federal income tax purposes. The company generally would not be subject to federal or state corporate income taxes if it distributes at least 90% of its taxable income to its stockholders. The company was formerly known as American Capital Agency Corp. and changed its name to AGNC Investment Corp. in September 2016. AGNC Investment Corp. was incorporated in 2008 and is headquartered in Bethesda, Maryland.
A53: VMBS | B53: Vanguard Mortgage-Backed Securi | C53: Vanguard Mortgage-Backed Securities Index Fund ETF Shares | D53: The fund employs an indexing investment approach designed to track the performance of the Bloomberg U.S. MBS Float Adjusted Index. This index covers U.S. agency mortgage-backed pass-through securities issued by the GNMA, the FNMA, and the FHLMC. To be included in the index, pool aggregates must have at least $1 billion currently outstanding and a weighted average maturity of at least 1 year. All of the fund's investments will be selected through the sampling process, and at least 80% of the fund's assets will be invested in bonds included in the index.
A54: CMBS | B54: iShares CMBS Bond ETF | C54: iShares CMBS ETF | D54: The index measures the performance of investment-grade commercial mortgage-backed securities ("CMBS"), which are classes of securities (known as "certificates") that represent interests in "pools" of commercial mortgages. The fund will invest at least 80% of its assets in the component securities of the underlying index, and it will invest at least 90% of its assets in fixed income securities of the types included in the underlying index that BFA believes will help the fund track the underlying index.
A55: EMB | B55: iShares J.P. Morgan USD Emergin | C55: iShares J.P. Morgan USD Emerging Markets Bond ETF | D55: The fund will invest at least 80% of its assets in the component securities of the underlying index and will invest at least 90% of its assets in fixed income securities of the types included in the underlying index. The index is a broad, diverse U.S. dollar-denominated emerging markets debt benchmark that tracks the total return of actively traded external debt instruments in emerging market countries.
A56: EMHY | B56: iShares J.P. Morgan EM High Yie | C56: iShares J.P. Morgan EM High Yield Bond ETF | D56: The fund will invest at least 80% of its assets in the component securities of the underlying index, and the fund will invest at least 90% of its assets in fixed income securities of the types included in the underlying index that BFA believes will help the fund track the underlying index. The index tracks the performance of below investment-grade U.S. dollar-denominated, emerging market fixed and floating-rate debt securities issued by corporate, sovereign, and quasi-sovereign entities.
... A63: UUP | B63: Invesco DB USD Index Bullish Fu | C63: Invesco DB US Dollar Index Bullish Fund | D63: The fund invests in futures contracts in an attempt to track its index. The index is calculated to reflect the changes in market value over time, whether positive or negative, of long positions in DX Contracts.
A64: DX-Y.NYB | B64: ICE US Dollar Index - Index - C | C64: US Dollar Index
A65: FXE | B65: Invesco CurrencyShares Euro Cur | C65: Invesco CurrencyShares Euro Currency Trust
A66: FXY | B66: Invesco CurrencyShares Japanese | C66: Invesco CurrencyShares Japanese Yen Trust | D66: The fund seeks to reflect the price in USD of the Japanese Yen. The sponsor believes that, for many investors, the shares represent a cost-effective investment relative to traditional means of investing in the foreign exchange market.
A67: FXF | B67: Invesco CurrencyShares Swiss Fr | C67: Invesco CurrencyShares Swiss Franc Trust | D67: The fund seeks to reflect the price of the Swiss Franc. The sponsor believes that, for many investors, the shares represent a cost-effective investment relative to traditional means of investing in the foreign exchange market.
A68: ^VIX | B68: CBOE Volatility Index | C68: CBOE Volatility Index
A69: VXX | B69: iPath Series B S&P 500 VIX Shor | C69: iPath Series B S&P 500 VIX Short-Term Futures ETN | D69: The ETN offers exposure to futures contracts of specified maturities on the VIX index and not direct exposure to the VIX index or its spot level. The index is designed to provide investors with exposure to one or more maturities of futures contracts on the CBOE Volatility Index®.
A70: ^VIX3M | B70: CBOE S&P 500 3-Month Volatility | C70: CBOE S&P 500 3-Month Volatility
A71: ^VVIX | B71: CBOE VIX VOLATILITY INDEX | C71: ^VVIX
A72: ^MOVE | B72: ICE BofAML MOVE Index | C72: ICE BofAML MOVE Index
A73: ^OVX | B73: CBOE Crude Oil Volatility Index | C73: ^OVX
A74: ^EVZ | B74: ^EVZ,92169,0 | C74: ^EVZ,92169,0
A75: ^GVZ | B75: CBOE Gold Volatility Index | C75: ^GVZ
A76: ^COR3M | B76: Cboe Implied Correlation Index | C76: Cboe Implied Correlation Index

Sheet election_fact
A6: asset_class | B6: region | C6: factor_name | D6: source | E6: diffusion_type | F6: multiplier | G6: factor_name_new | H6: description_override | I6: Description_GPT | J6: Underlying | K6: Active | L6: hyper_factor | M6: composite | N6: client | O6: ticker | P6: description | Q6: short_name_yf | R6: long_name_yf | S6: summary_yf | T6: note
A7: Theme | B7: USD | C7: ELECTION | D7: composite | E7: lognormal | F7: {=_xlfn.SWITCH(data[[#This Row],[diffusion_type]],"lognormal",0.0001,"normal",-0.01)*IF(data[[#This Row],[asset_class]]="Vol",1,1)} -> 0.0001 | J7: {=_xlfn.XLOOKUP(data[[#This Row],[factor_name]],_xlfn.ANCHORARRAY(composites!$I$2),_xlfn.ANCHORARRAY(composites!$J$2))} -> #N/A | K7: 1 | L7: 0 | M7: 0 | N7: 0 | O7: =data[[#This Row],[factor_name]] -> DIA | P7: {=_xlfn.IFS(data[[#This Row],[description_override]]<>"",data[[#This Row],[description_override]],data[[#This Row],[Description_GPT]]<>"",data[[#This Row],[Description_GPT]],data[[#This Row],[Underlying]]<>"",data[[#This Row],[Underlying]],TRUE,"-")} -> Dow Jones 30 | Q7: =_xlfn.XLOOKUP(data[[#This Row],[ticker]],yf_desc[ticker],yf_desc[shortName],"-") -> SPDR Dow Jones Industrial Avera | R7: =_xlfn.XLOOKUP(data[[#This Row],[ticker]],yf_desc[ticker],yf_desc[longName],"-") -> SPDR Dow Jones Industrial Average ETF Trust | S7: =_xlfn.XLOOKUP(data[[#This Row],[ticker]],yf_desc[ticker],yf_desc[longBusinessSummary],"-") -> The Trust’s Portfolio consists of substantially all of the component common stocks that comprise the DJIA, which are weighted in accordance with the terms of the Trust Agreement.
A12: ELECTION | B12: XLF | C12: 1.5
A13: ELECTION | B13: ICLN | C13: -1
A14: ELECTION | B14: IWM | C14: 1.5
A15: ELECTION | B15: FEZ | C15: -1

Sheet composites
A1: portfolio_name | B1: factor_name | C1: weight | N1: vol | O1: volweight
A2: FED | B2: SHY | C2: 1 | E2: {=_xlfn.XLOOKUP(composities[portfolio_name],data[factor_name],data[Active])} -> 1 | H2: {=TEXT(composities[weight],IF(INT(composities[weight]*100)/100=composities[weight],"General","0.00"))} -> 1 | I2: {=_xlfn.UNIQUE(composities[portfolio_name])} -> FED | J2: {=_xlfn.BYROW(_xlfn.ANCHORARRAY(I2),_xlfn.LAMBDA(_xlpm.portfolio,_xlfn.TEXTJOIN(", ",,_xlfn.BYROW(_xlfn._xlws.FILTER(_xlfn.HSTACK(composities[factor_name],_xlfn.ANCHORARRAY($H$2)),composities[portfolio_name]=_xlpm.portfolio),_xlfn.LAMBDA(_xlpm.factor,_xlfn.TEXTJOIN(" ",,_xlpm.factor))))))} -> SHY 1, BSV 1 | X2: {=composities[portfolio_name]<>OFFSET(composities[portfolio_name],-1,0)} -> TRUE | AE2: TRUMP | AF2: unit | AI2: AI | AJ2: FED
A3: FED | B3: BSV | C3: 1 | E3: 1 | H3: 1 | I3: AI | J3: AIQ 1, QQQ 0.25, IWM -0.25 | X3: FALSE | AD3: XLF | AE3: 1 | AF3: capital
A4: AI | B4: AIQ | C4: 1 | E4: 1 | H4: 1 | I4: GEOPOLITICS | J4: GLD 0.65, USO 0.3, ^VIX3M -0.15, FEZ -0.05 | X4: TRUE | AD4: ICLN | AE4: -1 | AF4: capital | AG4: or TEN
A5: AI | B5: QQQ | C5: 0.25 | E5: 1 | H5: 0.25 | I5: 2s10s | J5: SHY -3.86, IEF 1 | X5: FALSE | AD5: IWM | AE5: 1 | AF5: capital
A6: AI | B6: IWM | C6: -0.25 | E6: 1 | H6: -0.25 | I6: XLPXLY | J6: XLP 1, XLY -1 | X6: FALSE | AD6: SX5E | AE6: -1 | AF6: capital
A7: GEOPOLITICS | B7: GLD | C7: 0.65 | E7: 1 | H7: 0.65 | I7: TRADEWAR | J7: GLD 0.21, FXY 0.30, FXF 0.37, ^VIX3M -0.04, XLP 0.15, XLY -0.15 | X7: TRUE | AD7: USD02 | AE7: 1 | AF7: vol | AG7: govt spending
A8: GEOPOLITICS | B8: USO | C8: 0.3 | E8: 1 | H8: 0.3 | I8: IRAN | J8: USO 1 | X8: FALSE | AA8: AIQ | AB8: 1 | AD8: USD10 | AE8: -1 | AF8: vol
A9: GEOPOLITICS | B9: ^VIX3M | C9: -0.15 | E9: 1 | H9: -0.15 | I9: SEMI-SOFT | J9: SMH 1, IGV -1, QQQ 1 | X9: FALSE | AA9: QQQ | AB9: 1 | AD9: TIP | AE9: 1
A10: GEOPOLITICS | B10: FEZ | C10: -0.05 | E10: 1 | F10: x | H10: -0.05 | I10: PRIVATES | J10: PSP 0.5, XLF -0.5, BKLN 0.5, LQDH -0.5 | X10: FALSE | AA10: IWM | AB10: -1 | AD10: TLT | AE10: -1 | AG10: or TLT v. VTIP
A11: 2s10s | B11: SHY | C11: =-C12*Y15/Y13 -> -3.863388 | E11: 1 | H11: -3.86 | X11: TRUE | AD11: AIQ | AI11: 1
A12: 2s10s | B12: IEF | C12: 1 | E12: 1 | H12: 1 | X12: FALSE | AD12: RSP | AI12: -1
A13: XLPXLY | B13: XLP | C13: 1 | E13: 1 | H13: 1 | X13: TRUE | Y13: 1.83 | AD13: SOFRZ5
A14: XLPXLY | B14: XLY | C14: -1 | E14: 1 | H14: -1 | X14: FALSE
A15: TRADEWAR | B15: GLD | C15: {=O18/N18*$P$18/SUM(ABS(($O$18:$O$22)))} -> 0.20547945 | E15: 1 | H15: 0.21 | X15: TRUE | Y15: 7.07 | Z15: =Y15/Y13 -> 3.863388 | AD15: SOFRZ4
A16: TRADEWAR | B16: FXY | C16: =O19/N19*$P$18/COUNT($O$18:$O$22) -> 0.2970297 | E16: 1 | H16: 0.30 | O16: 3 | Q16: XLPXLY | R16: 22 | X16: FALSE
A17: TRADEWAR | B17: FXF | C17: =O20/N20*$P$18/COUNT($O$18:$O$22) -> 0.36585366 | E17: 1 | H17: 0.37 | R17: 16 | X17: FALSE
A18: TRADEWAR | B18: ^VIX3M | C18: =O21/N21*$P$18/COUNT($O$18:$O$22) -> -0.0375 | E18: 1 | H18: -0.04 | N18: 14.6 | O18: 1 | P18: 15 | W18: {=C15:C18*N18:N21} -> 3 | X18: FALSE
A19: TRADEWAR | B19: =B13 -> XLP | C19: =O22/N22*$P$18/COUNT($O$18:$O$22) -> 0.15 | E19: 1 | H19: 0.15 | N19: 10.1 | O19: 1 | W19: 3 | X19: FALSE
A20: TRADEWAR | B20: =B14 -> XLY | C20: =-C19 -> -0.15 | E20: 1 | H20: -0.15 | N20: 8.2 | O20: 1 | W20: 3 | X20: FALSE | Z20: Can also short discretionary/staples
A21: IRAN | B21: USO | C21: 1 | E21: 1 | H21: 1 | N21: 80 | O21: -1 | W21: -3 | X21: TRUE
A22: SEMI-SOFT | B22: SMH | C22: 1 | E22: 1 | H22: 1 | N22: 20 | O22: 1 | X22: TRUE
A23: SEMI-SOFT | B23: IGV | C23: -1 | E23: 1 | H23: -1 | X23: FALSE
A24: SEMI-SOFT | B24: QQQ | C24: 1 | E24: 1 | H24: 1 | X24: FALSE
A25: PRIVATES | B25: PSP | C25: 0.5 | E25: 1 | H25: 0.5 | X25: TRUE
A26: PRIVATES | B26: XLF | C26: -0.5 | E26: 1 | H26: -0.5 | X26: FALSE
A27: PRIVATES | B27: BKLN | C27: 0.5 | E27: 1 | H27: 0.5 | X27: FALSE
A28: PRIVATES | B28: LQDH | C28: -0.5 | E28: 1 | H28: -0.5 | X28: FALSE
Q34: =_xlfn.TEXTJOIN(", ",,_xlfn.ANCHORARRAY(Q36)) -> #VALUE!
N36: 14.6 | O36: 3 | Q36: {=_xlfn._xlws.FILTER(composities[[factor_name]:[weight]],composities[portfolio_name]="ELECTION")} -> #VALUE! | T36: {=_xlfn._xlws.FILTER(composities[[factor_name]:[weight]],composities[portfolio_name]="2s10s")} -> SHY | U36: -3.863388 | V36: {=_xlfn.LET(_xlpm.f,_xlfn._xlws.FILTER(composities[[factor_name]:[weight]],composities[portfolio_name]="ELECTION"),_xlfn.TEXTJOIN("; ",,_xlfn.BYROW(_xlpm.f,_xlfn.LAMBDA(_xlpm.row,_xlfn.TEXTJOIN(" ",,_xlpm.row)))))} -> #VALUE! | W36: {=C38:C41*N36:N39} -> 3
N37: 10.1 | O37: 3 | T37: IEF | U37: 1 | W37: 3
A38: TRADEWAR_OLD | B38: GLD | C38: =O36/N36 -> 0.20547945 | N38: 8.2 | O38: 3 | W38: 3 | Z38: Can also short discretionary/staples
A39: TRADEWAR_OLD | B39: FXY | C39: =O37/N37 -> 0.2970297 | N39: 80 | O39: =-SUM(O36:O38) -> -9 | W39: -9
A40: TRADEWAR_OLD | B40: FXF | C40: =O38/N38 -> 0.36585366
A41: TRADEWAR_OLD | B41: ^VIX3M | C41: =O39/N39 -> -0.1125

Sheet data
A1: asset_class | B1: region | C1: factor_name | D1: source | E1: diffusion_type | F1: multiplier | G1: factor_name_new | H1: description_override | I1: Description_GPT | J1: Underlying | K1: Active | L1: hyper_factor | M1: composite | N1: client | O1: ticker | P1: description | Q1: short_name_yf | R1: long_name_yf | S1: summary_yf | T1: note
A2: Equities | B2: USD | C2: SPY | D2: yfinance | E2: lognormal | F2: {=_xlfn.SWITCH(data[[#This Row],[diffusion_type]],"lognormal",0.0001,"normal",-0.01)*IF(data[[#This Row],[asset_class]]="Vol",1,1)} -> 0.0001 | G2: SPX | H2: S&P 500 | I2: SPDR S&P 500 ETF Trust | J2: S&P 500 Index | K2: 1 | L2: 1 | M2: 0 | N2: 0 | O2: =data[[#This Row],[factor_name]] -> SPY | P2: {=_xlfn.IFS(data[[#This Row],[description_override]]<>"",data[[#This Row],[description_override]],data[[#This Row],[Description_GPT]]<>"",data[[#This Row],[Description_GPT]],data[[#This Row],[Underlying]]<>"",data[[#This Row],[Underlying]],TRUE,"-")} -> S&P 500 | Q2: =_xlfn.XLOOKUP(data[[#This Row],[ticker]],yf_desc[ticker],yf_desc[shortName],"-") -> SPDR S&P 500 | R2: =_xlfn.XLOOKUP(data[[#This Row],[ticker]],yf_desc[ticker],yf_desc[longName],"-") -> SPDR S&P 500 ETF | S2: =_xlfn.XLOOKUP(data[[#This Row],[ticker]],yf_desc[ticker],yf_desc[longBusinessSummary],"-") -> The trust seeks to achieve its investment objective by holding a portfolio of the common stocks that are included in the index, with the weight of each stock in the portfolio substantially corresponding to the weight of such stock in the index.
A3: Equities | B3: USD | C3: IWM | D3: yfinance | E3: lognormal | F3: {=_xlfn.SWITCH(data[[#This Row],[diffusion_type]],"lognormal",0.0001,"normal",-0.01)*IF(data[[#This Row],[asset_class]]="Vol",1,1)} -> 0.0001 | G3: RTY | H3: Russell 2000 | I3: iShares Russell 2000 ETF | J3: Russell 2000 Index | K3: 1 | L3: 0 | M3: 0 | N3: 0 | O3: =data[[#This Row],[factor_name]] -> IWM | P3: {=_xlfn.IFS(data[[#This Row],[description_override]]<>"",data[[#This Row],[description_override]],data[[#This Row],[Description_GPT]]<>"",data[[#This Row],[Description_GPT]],data[[#This Row],[Underlying]]<>"",data[[#This Row],[Underlying]],TRUE,"-")} -> Russell 2000 | Q3: =_xlfn.XLOOKUP(data[[#This Row],[ticker]],yf_desc[ticker],yf_desc[shortName],"-") -> iShares Russell 2000 ETF | R3: =_xlfn.XLOOKUP(data[[#This Row],[ticker]],yf_desc[ticker],yf_desc[longName],"-") -> iShares Russell 2000 ETF | S3: =_xlfn.XLOOKUP(data[[#This Row],[ticker]],yf_desc[ticker],yf_desc[longBusinessSummary],"-") -> The fund generally invests at least 80% of its assets in the component securities of its underlying index and in investments that have economic characteristics that are substantially identical to the component securities of its underlying index (i.e., depositary receipts representing securities of the underlying index) and may invest up to 20% of its assets in certain futures, options and swap contracts, cash and cash equivalents. | Y3: L1 = L0 + chg(F)*M = L0 + R*M
A4: Equities | B4: USD | C4: MDY | D4: yfinance | E4: lognormal | F4: {=_xlfn.SWITCH(data[[#This Row],[diffusion_type]],"lognormal",0.0001,"normal",-0.01)*IF(data[[#This Row],[asset_class]]="Vol",1,1)} -> 0.0001 | G4: MCAP | H4: S&P 400 | I4: SPDR S&P MidCap 400 ETF Trust | J4: S&P MidCap 400 Index | K4: 1 | L4: 0 | M4: 0 | N4: 0 | O4: =data[[#This Row],[factor_name]] -> MDY | P4: {=_xlfn.IFS(data[[#This Row],[description_override]]<>"",data[[#This Row],[description_override]],data[[#This Row],[Description_GPT]]<>"",data[[#This Row],[Description_GPT]],data[[#This Row],[Underlying]]<>"",data[[#This Row],[Underlying]],TRUE,"-")} -> S&P 400 | Q4: =_xlfn.XLOOKUP(data[[#This Row],[ticker]],yf_desc[ticker],yf_desc[shortName],"-") -> SPDR S&P MidCap 400 ETF Trust | R4: =_xlfn.XLOOKUP(data[[#This Row],[ticker]],yf_desc[ticker],yf_desc[longName],"-") -> SPDR S&P MIDCAP 400 ETF Trust | S4: =_xlfn.XLOOKUP(data[[#This Row],[ticker]],yf_desc[ticker],yf_desc[longBusinessSummary],"-") -> The Trust seeks to achieve its investment objective by holding a portfolio of the common stocks that are included in the index (the “Portfolio”), with the weight of each stock in the Portfolio substantially corresponding to the weight of such stock in the index.
A5: Equities | B5: USD | C5: RSP | D5: yfinance | E5: lognormal | F5: {=_xlfn.SWITCH(data[[#This Row],[diffusion_type]],"lognormal",0.0001,"normal",-0.01)*IF(data[[#This Row],[asset_class]]="Vol",1,1)} -> 0.0001 | H5: S&P 500 EW | K5: 1 | L5: 0 | M5: 0 | N5: 0 | O5: =data[[#This Row],[factor_name]] -> RSP | P5: {=_xlfn.IFS(data[[#This Row],[description_override]]<>"",data[[#This Row],[description_override]],data[[#This Row],[Description_GPT]]<>"",data[[#This Row],[Description_GPT]],data[[#This Row],[Underlying]]<>"",data[[#This Row],[Underlying]],TRUE,"-")} -> S&P 500 EW | Q5: =_xlfn.XLOOKUP(data[[#This Row],[ticker]],yf_desc[ticker],yf_desc[shortName],"-") -> Invesco S&P 500 Equal Weight ET | R5: =_xlfn.XLOOKUP(data[[#This Row],[ticker]],yf_desc[ticker],yf_desc[longName],"-") -> Invesco S&P 500 Equal Weight ETF | S5: =_xlfn.XLOOKUP(data[[#This Row],[ticker]],yf_desc[ticker],yf_desc[longBusinessSummary],"-") -> The fund generally will invest at least 90% of its total assets in securities that comprise the underlying index. Strictly in accordance with its guidelines and mandated procedures, the index provider compiles, maintains and calculates the underlying index, which consists of all of the of the S&P 500® Index. | Y5: return = chg(factor) * multiplier
A6: Equities | B6: USD | C6: QQQ | D6: yfinance | E6: lognormal | F6: {=_xlfn.SWITCH(data[[#This Row],[diffusion_type]],"lognormal",0.0001,"normal",-0.01)*IF(data[[#This Row],[asset_class]]="Vol",1,1)} -> 0.0001 | G6: NDX | H6: Nasdaq 100 | I6: Invesco QQQ Trust | J6: Nasdaq-100 Index | K6: 1 | L6: 0 | M6: 0 | N6: 0 | O6: =data[[#This Row],[factor_name]] -> QQQ | P6: {=_xlfn.IFS(data[[#This Row],[description_override]]<>"",data[[#This Row],[description_override]],data[[#This Row],[Description_GPT]]<>"",data[[#This Row],[Description_GPT]],data[[#This Row],[Underlying]]<>"",data[[#This Row],[Underlying]],TRUE,"-")} -> Nasdaq 100 | Q6: =_xlfn.XLOOKUP(data[[#This Row],[ticker]],yf_desc[ticker],yf_desc[shortName],"-") -> Invesco QQQ Trust, Series 1 | R6: =_xlfn.XLOOKUP(data[[#This Row],[ticker]],yf_desc[ticker],yf_desc[longName],"-") -> Invesco QQQ Trust | S6: =_xlfn.XLOOKUP(data[[#This Row],[ticker]],yf_desc[ticker],yf_desc[longBusinessSummary],"-") -> To maintain the correspondence between the composition and weights of the securities in the trust (the "securities") and the stocks in the NASDAQ-100 Index®, the adviser adjusts the securities from time to time to conform to periodic changes in the identity and/or relative weights of index securities. The composition and weighting of the securities portion of a portfolio deposit are also adjusted to conform to changes in the index.
A7: Equities | B7: USD | C7: DIA | D7: yfinance | E7: lognormal | F7: {=_xlfn.SWITCH(data[[#This Row],[diffusion_type]],"lognormal",0.0001,"normal",-0.01)*IF(data[[#This Row],[asset_class]]="Vol",1,1)} -> 0.0001 | G7: DOW | H7: Dow Jones 30 | I7: SPDR Dow Jones Industrial Average ETF Trust | J7: Dow Jones Industrial Average | K7: 1 | L7: 0 | M7: 0 | N7: 0 | O7: =data[[#This Row],[factor_name]] -> DIA | P7: {=_xlfn.IFS(data[[#This Row],[description_override]]<>"",data[[#This Row],[description_override]],data[[#This Row],[Description_GPT]]<>"",data[[#This Row],[Description_GPT]],data[[#This Row],[Underlying]]<>"",data[[#This Row],[Underlying]],TRUE,"-")} -> Dow Jones 30 | Q7: =_xlfn.XLOOKUP(data[[#This Row],[ticker]],yf_desc[ticker],yf_desc[shortName],"-") -> SPDR Dow Jones Industrial Avera | R7: =_xlfn.XLOOKUP(data[[#This Row],[ticker]],yf_desc[ticker],yf_desc[longName],"-") -> SPDR Dow Jones Industrial Average ETF Trust | S7: =_xlfn.XLOOKUP(data[[#This Row],[ticker]],yf_desc[ticker],yf_desc[longBusinessSummary],"-") -> The Trust’s Portfolio consists of substantially all of the component common stocks that comprise the DJIA, which are weighted in accordance with the terms of the Trust Agreement.
A8: Sector | B8: USD | C8: XLK | D8: yfinance | E8: lognormal | F8: {=_xlfn.SWITCH(data[[#This Row],[diffusion_type]],"lognormal",0.0001,"normal",-0.01)*IF(data[[#This Row],[asset_class]]="Vol",1,1)} -> 0.0001 | H8: Technology | I8: Technology Select Sector SPDR Fund | K8: 1 | L8: 0 | M8: 0 | N8: 0 | O8: =data[[#This Row],[factor_name]] -> XLK | P8: {=_xlfn.IFS(data[[#This Row],[description_override]]<>"",data[[#This Row],[description_override]],data[[#This Row],[Description_GPT]]<>"",data[[#This Row],[Description_GPT]],data[[#This Row],[Underlying]]<>"",data[[#This Row],[Underlying]],TRUE,"-")} -> Technology | Q8: =_xlfn.XLOOKUP(data[[#This Row],[ticker]],yf_desc[ticker],yf_desc[shortName],"-") -> SPDR Select Sector Fund - Techn | R8: =_xlfn.XLOOKUP(data[[#This Row],[ticker]],yf_desc[ticker],yf_desc[longName],"-") -> The Technology Select Sector SPDR Fund | S8: =_xlfn.XLOOKUP(data[[#This Row],[ticker]],yf_desc[ticker],yf_desc[longBusinessSummary],"-") -> In seeking to track the performance of the index, the fund employs a replication strategy, which means that the fund typically invests in substantially all of the securities represented in the index in approximately the same proportions as the index. It generally invests substantially all, but at least 95%, of its total assets in the securities comprising the index. The fund is non-diversified.
A9: Sector | B9: USD | C9: XLI | D9: yfinance | E9: lognormal | F9: {=_xlfn.SWITCH(data[[#This Row],[diffusion_type]],"lognormal",0.0001,"normal",-0.01)*IF(data[[#This Row],[asset_class]]="Vol",1,1)} -> 0.0001 | H9: Industrials | I9: Industrial Select Sector SPDR Fund | K9: 1 | L9: 0 | M9: 0 | N9: 0 | O9: =data[[#This Row],[factor_name]] -> XLI | P9: {=_xlfn.IFS(data[[#This Row],[description_override]]<>"",data[[#This Row],[description_override]],data[[#This Row],[Description_GPT]]<>"",data[[#This Row],[Description_GPT]],data[[#This Row],[Underlying]]<>"",data[[#This Row],[Underlying]],TRUE,"-")} -> Industrials | Q9: =_xlfn.XLOOKUP(data[[#This Row],[ticker]],yf_desc[ticker],yf_desc[shortName],"-") -> SPDR Select Sector Fund - Indus | R9: =_xlfn.XLOOKUP(data[[#This Row],[ticker]],yf_desc[ticker],yf_desc[longName],"-") -> The Industrial Select Sector SPDR Fund | S9: =_xlfn.XLOOKUP(data[[#This Row],[ticker]],yf_desc[ticker],yf_desc[longBusinessSummary],"-") -> Under normal market conditions, the fund generally invests substantially all, but at least 95%, of its total assets in the securities comprising the index. The index includes companies that have been identified as Industrial companies by the Global Industry Classification Standard, including securities of companies from the following industries: aerospace and defense; industrial conglomerates; marine transportation. It is non-diversified.
A10: Sector | B10: USD | C10: XLF | D10: yfinance | E10: lognormal | F10: {=_xlfn.SWITCH(data[[#This Row],[diffusion_type]],"lognormal",0.0001,"normal",-0.01)*IF(data[[#This Row],[asset_class]]="Vol",1,1)} -> 0.0001 | H10: Financials | I10: Financial Select Sector SPDR Fund | K10: 1 | L10: 0 | M10: 0 | N10: 0 | O10: =data[[#This Row],[factor_name]] -> XLF | P10: {=_xlfn.IFS(data[[#This Row],[description_override]]<>"",data[[#This Row],[description_override]],data[[#This Row],[Description_GPT]]<>"",data[[#This Row],[Description_GPT]],data[[#This Row],[Underlying]]<>"",data[[#This Row],[Underlying]],TRUE,"-")} -> Financials | Q10: =_xlfn.XLOOKUP(data[[#This Row],[ticker]],yf_desc[ticker],yf_desc[shortName],"-") -> SPDR Select Sector Fund - Finan | R10: =_xlfn.XLOOKUP(data[[#This Row],[ticker]],yf_desc[ticker],yf_desc[longName],"-") -> The Financial Select Sector SPDR Fund | S10: =_xlfn.XLOOKUP(data[[#This Row],[ticker]],yf_desc[ticker],yf_desc[longBusinessSummary],"-") -> The fund generally invests substantially all, but at least 95%, of its total assets in the securities comprising the index. The index includes companies that have been identified as Financial companies by the Global Industry Classification Standard, including securities of companies from the following industries: financial services; insurance; banks; capital markets; mortgage real estate investment trusts; and consumer finance. The fund is non-diversified.
A11: Sector | B11: USD | C11: KRE | D11: yfinance | E11: lognormal | F11: {=_xlfn.SWITCH(data[[#This Row],[diffusion_type]],"lognormal",0.0001,"normal",-0.01)*IF(data[[#This Row],[asset_class]]="Vol",1,1)} -> 0.0001 | H11: Regional Banks | I11: SPDR S&P Regional Banking ETF | K11: 1 | L11: 0 | M11: 0 | N11: 0 | O11: =data[[#This Row],[factor_name]] -> KRE | P11: {=_xlfn.IFS(data[[#This Row],[description_override]]<>"",data[[#This Row],[description_override]],data[[#This Row],[Description_GPT]]<>"",data[[#This Row],[Description_GPT]],data[[#This Row],[Underlying]]<>"",data[[#This Row],[Underlying]],TRUE,"-")} -> Regional Banks | Q11: =_xlfn.XLOOKUP(data[[#This Row],[ticker]],yf_desc[ticker],yf_desc[shortName],"-") -> SPDR S&P Regional Banking ETF | R11: =_xlfn.XLOOKUP(data[[#This Row],[ticker]],yf_desc[ticker],yf_desc[longName],"-") -> SPDR S&P Regional Banking ETF | S11: =_xlfn.XLOOKUP(data[[#This Row],[ticker]],yf_desc[ticker],yf_desc[longBusinessSummary],"-") -> In seeking to track the performance of the S&P Regional Banks Select Industry Index (the "index"), the fund employs a sampling strategy. It generally invests substantially all, but at least 80%, of its total assets in the securities comprising the index. The index represents the regional banks segment of the S&P Total Market Index ("S&P TMI").
A12: Sector | B12: USD | C12: XLC | D12: yfinance | E12: lognormal | F12: {=_xlfn.SWITCH(data[[#This Row],[diffusion_type]],"lognormal",0.0001,"normal",-0.01)*IF(data[[#This Row],[asset_class]]="Vol",1,1)} -> 0.0001 | H12: Communications | I12: Communication Services Select Sector SPDR | K12: 1 | L12: 0 | M12: 0 | N12: 0 | O12: =data[[#This Row],[factor_name]] -> XLC | P12: {=_xlfn.IFS(data[[#This Row],[description_override]]<>"",data[[#This Row],[description_override]],data[[#This Row],[Description_GPT]]<>"",data[[#This Row],[Description_GPT]],data[[#This Row],[Underlying]]<>"",data[[#This Row],[Underlying]],TRUE,"-")} -> Communications | Q12: =_xlfn.XLOOKUP(data[[#This Row],[ticker]],yf_desc[ticker],yf_desc[shortName],"-") -> The Communication Services Sele | R12: =_xlfn.XLOOKUP(data[[#This Row],[ticker]],yf_desc[ticker],yf_desc[longName],"-") -> The Communication Services Select Sector SPDR ETF Fund | S12: =_xlfn.XLOOKUP(data[[#This Row],[ticker]],yf_desc[ticker],yf_desc[longBusinessSummary],"-") -> Normally, the fund generally invests substantially all, but at least 95%, of its total assets in the securities comprising the index. The index includes companies that have been identified as Communication Services companies by the GICS®, including securities of companies from the following industries: diversified telecommunication services; wireless telecommunication services; media; entertainment; and interactive media & services. The fund is non-diversified.
A13: Sector | B13: USD | C13: XLE | D13: yfinance | E13: lognormal | F13: {=_xlfn.SWITCH(data[[#This Row],[diffusion_type]],"lognormal",0.0001,"normal",-0.01)*IF(data[[#This Row],[asset_class]]="Vol",1,1)} -> 0.0001 | H13: Energy | I13: Energy Select Sector SPDR Fund | K13: 1 | L13: 0 | M13: 0 | N13: 0 | O13: =data[[#This Row],[factor_name]] -> XLE | P13: {=_xlfn.IFS(data[[#This Row],[description_override]]<>"",data[[#This Row],[description_override]],data[[#This Row],[Description_GPT]]<>"",data[[#This Row],[Description_GPT]],data[[#This Row],[Underlying]]<>"",data[[#This Row],[Underlying]],TRUE,"-")} -> Energy | Q13: =_xlfn.XLOOKUP(data[[#This Row],[ticker]],yf_desc[ticker],yf_desc[shortName],"-") -> SPDR Select Sector Fund - Energ | R13: =_xlfn.XLOOKUP(data[[#This Row],[ticker]],yf_desc[ticker],yf_desc[longName],"-") -> The Energy Select Sector SPDR Fund | S13: =_xlfn.XLOOKUP(data[[#This Row],[ticker]],yf_desc[ticker],yf_desc[longBusinessSummary],"-") -> In seeking to track the performance of the index, the fund employs a replication strategy. It generally invests substantially all, but at least 95%, of its total assets in the securities comprising the index. The index includes companies that have been identified as Energy companies by the GICS®, including securities of companies from the following industries: oil, gas and consumable fuels; and energy equipment and services. It is non-diversified.
A14: Sector | B14: USD | C14: XLY | D14: yfinance | E14: lognormal | F14: {=_xlfn.SWITCH(data[[#This Row],[diffusion_type]],"lognormal",0.0001,"normal",-0.01)*IF(data[[#This Row],[asset_class]]="Vol",1,1)} -> 0.0001 | H14: Discretionary | I14: Consumer Discretionary Select Sector SPDR | K14: 1 | L14: 0 | M14: 0 | N14: 0 | O14: =data[[#This Row],[factor_name]] -> XLY | P14: {=_xlfn.IFS(data[[#This Row],[description_override]]<>"",data[[#This Row],[description_override]],data[[#This Row],[Description_GPT]]<>"",data[[#This Row],[Description_GPT]],data[[#This Row],[Underlying]]<>"",data[[#This Row],[Underlying]],TRUE,"-")} -> Discretionary | Q14: =_xlfn.XLOOKUP(data[[#This Row],[ticker]],yf_desc[ticker],yf_desc[shortName],"-") -> SPDR Select Sector Fund - Consu | R14: =_xlfn.XLOOKUP(data[[#This Row],[ticker]],yf_desc[ticker],yf_desc[longName],"-") -> The Consumer Discretionary Select Sector SPDR Fund | S14: =_xlfn.XLOOKUP(data[[#This Row],[ticker]],yf_desc[ticker],yf_desc[longBusinessSummary],"-") -> The Advisor employs a replication strategy. The fund generally invests substantially all, but at least 95%, of its total assets in the securities comprising the index. The index includes companies that have been identified as Consumer Discretionary companies by the Global Industry Classification Standard (GICS®). It is non-diversified.
A15: Sector | B15: USD | C15: XLB | D15: yfinance | E15: lognormal | F15: {=_xlfn.SWITCH(data[[#This Row],[diffusion_type]],"lognormal",0.0001,"normal",-0.01)*IF(data[[#This Row],[asset_class]]="Vol",1,1)} -> 0.0001 | H15: Materials | I15: Materials Select Sector SPDR Fund | K15: 1 | L15: 0 | M15: 0 | N15: 0 | O15: =data[[#This Row],[factor_name]] -> XLB | P15: {=_xlfn.IFS(data[[#This Row],[description_override]]<>"",data[[#This Row],[description_override]],data[[#This Row],[Description_GPT]]<>"",data[[#This Row],[Description_GPT]],data[[#This Row],[Underlying]]<>"",data[[#This Row],[Underlying]],TRUE,"-")} -> Materials | Q15: =_xlfn.XLOOKUP(data[[#This Row],[ticker]],yf_desc[ticker],yf_desc[shortName],"-") -> Materials Select Sector SPDR | R15: =_xlfn.XLOOKUP(data[[#This Row],[ticker]],yf_desc[ticker],yf_desc[longName],"-") -> The Materials Select Sector SPDR Fund | S15: =_xlfn.XLOOKUP(data[[#This Row],[ticker]],yf_desc[ticker],yf_desc[longBusinessSummary],"-") -> In seeking to track the performance of the index, the fund employs a replication strategy. It generally invests substantially all, but at least 95%, of its total assets in the securities comprising the index. The index includes securities of companies from the following industries: chemicals; metals and mining; paper and forest products; containers and packaging; and construction materials. The fund is non-diversified.
A16: Sector | B16: USD | C16: XLV | D16: yfinance | E16: lognormal | F16: {=_xlfn.SWITCH(data[[#This Row],[diffusion_type]],"lognormal",0.0001,"normal",-0.01)*IF(data[[#This Row],[asset_class]]="Vol",1,1)} -> 0.0001 | H16: Health Care | I16: Health Care Select Sector SPDR Fund | K16: 1 | L16: 0 | M16: 0 | N16: 0 | O16: =data[[#This Row],[factor_name]] -> XLV | P16: {=_xlfn.IFS(data[[#This Row],[description_override]]<>"",data[[#This Row],[description_override]],data[[#This Row],[Description_GPT]]<>"",data[[#This Row],[Description_GPT]],data[[#This Row],[Underlying]]<>"",data[[#This Row],[Underlying]],TRUE,"-")} -> Health Care | Q16: =_xlfn.XLOOKUP(data[[#This Row],[ticker]],yf_desc[ticker],yf_desc[shortName],"-") -> SPDR Select Sector Fund - Healt | R16: =_xlfn.XLOOKUP(data[[#This Row],[ticker]],yf_desc[ticker],yf_desc[longName],"-") -> The Health Care Select Sector SPDR Fund | S16: =_xlfn.XLOOKUP(data[[#This Row],[ticker]],yf_desc[ticker],yf_desc[longBusinessSummary],"-") -> In seeking to track the performance of the index, the fund employs a replication strategy. It generally invests substantially all, but at least 95%, of its total assets in the securities comprising the index. The index includes companies from the following industries: pharmaceuticals; health care equipment & supplies; health care providers & services; biotechnology; life sciences tools & services; and health care technology. The fund is non-diversified.
A17: Sector | B17: USD | C17: XLU | D17: yfinance | E17: lognormal | F17: {=_xlfn.SWITCH(data[[#This Row],[diffusion_type]],"lognormal",0.0001,"normal",-0.01)*IF(data[[#This Row],[asset_class]]="Vol",1,1)} -> 0.0001 | H17: Utilities | I17: Utilities Select Sector SPDR Fund | K17: 1 | L17: 0 | M17: 0 | N17: 0 | O17: =data[[#This Row],[factor_name]] -> XLU | P17: {=_xlfn.IFS(data[[#This Row],[description_override]]<>"",data[[#This Row],[description_override]],data[[#This Row],[Description_GPT]]<>"",data[[#This Row],[Description_GPT]],data[[#This Row],[Underlying]]<>"",data[[#This Row],[Underlying]],TRUE,"-")} -> Utilities | Q17: =_xlfn.XLOOKUP(data[[#This Row],[ticker]],yf_desc[ticker],yf_desc[shortName],"-") -> SPDR Select Sector Fund - Utili | R17: =_xlfn.XLOOKUP(data[[#This Row],[ticker]],yf_desc[ticker],yf_desc[longName],"-") -> The Utilities Select Sector SPDR Fund | S17: =_xlfn.XLOOKUP(data[[#This Row],[ticker]],yf_desc[ticker],yf_desc[longBusinessSummary],"-") -> In seeking to track the performance of the index, the fund employs a replication strategy. It generally invests substantially all, but at least 95%, of its total assets in the securities comprising the index. The index includes securities of companies from the following industries: electric utilities; water utilities; multi-utilities; independent power and renewable electricity producers; and gas utilities. The fund is non-diversified.
A18: Sector | B18: USD | C18: XLP | D18: yfinance | E18: lognormal | F18: {=_xlfn.SWITCH(data[[#This Row],[diffusion_type]],"lognormal",0.0001,"normal",-0.01)*IF(data[[#This Row],[asset_class]]="Vol",1,1)} -> 0.0001 | H18: Staples | I18: Consumer Staples Select Sector SPDR Fund | K18: 1 | L18: 0 | M18: 0 | N18: 0 | O18: =data[[#This Row],[factor_name]] -> XLP | P18: {=_xlfn.IFS(data[[#This Row],[description_override]]<>"",data[[#This Row],[description_override]],data[[#This Row],[Description_GPT]]<>"",data[[#This Row],[Description_GPT]],data[[#This Row],[Underlying]]<>"",data[[#This Row],[Underlying]],TRUE,"-")} -> Staples | Q18: =_xlfn.XLOOKUP(data[[#This Row],[ticker]],yf_desc[ticker],yf_desc[shortName],"-") -> SPDR Select Sector Fund - Consu | R18: =_xlfn.XLOOKUP(data[[#This Row],[ticker]],yf_desc[ticker],yf_desc[longName],"-") -> The Consumer Staples Select Sector SPDR Fund | S18: =_xlfn.XLOOKUP(data[[#This Row],[ticker]],yf_desc[ticker],yf_desc[longBusinessSummary],"-") -> In seeking to track the performance of the index, the fund employs a replication strategy. It generally invests substantially all, but at least 95%, of its total assets in the securities comprising the index. The index includes companies that have been identified as Consumer Staples companies by the GICS®. It is non-diversified.
A19: Equities | B19: USD | C19: IYR | D19: yfinance | E19: lognormal | F19: {=_xlfn.SWITCH(data[[#This Row],[diffusion_type]],"lognormal",0.0001,"normal",-0.01)*IF(data[[#This Row],[asset_class]]="Vol",1,1)} -> 0.0001 | I19: iShares U.S. Real Estate ETF | K19: 1 | L19: 0 | M19: 0 | N19: 0 | O19: =data[[#This Row],[factor_name]] -> IYR | P19: {=_xlfn.IFS(data[[#This Row],[description_override]]<>"",data[[#This Row],[description_override]],data[[#This Row],[Description_GPT]]<>"",data[[#This Row],[Description_GPT]],data[[#This Row],[Underlying]]<>"",data[[#This Row],[Underlying]],TRUE,"-")} -> iShares U.S. Real Estate ETF | Q19: =_xlfn.XLOOKUP(data[[#This Row],[ticker]],yf_desc[ticker],yf_desc[shortName],"-") -> iShares U.S. Real Estate ETF | R19: =_xlfn.XLOOKUP(data[[#This Row],[ticker]],yf_desc[ticker],yf_desc[longName],"-") -> iShares U.S. Real Estate ETF | S19: =_xlfn.XLOOKUP(data[[#This Row],[ticker]],yf_desc[ticker],yf_desc[longBusinessSummary],"-") -> The fund seeks to track the investment results of the Dow Jones U.S. Real Estate Capped Index, which measures the performance of the real estate sector of the U.S. equity market, as defined by the "index provider". It generally invests at least 80% of its assets in the component securities of its underlying index and in investments that have economic characteristics that are substantially identical to the component securities of its underlying index.
A20: Equities | B20: USD | C20: VNQ | D20: yfinance | E20: lognormal | F20: {=_xlfn.SWITCH(data[[#This Row],[diffusion_type]],"lognormal",0.0001,"normal",-0.01)*IF(data[[#This Row],[asset_class]]="Vol",1,1)} -> 0.0001 | I20: Vanguard Real Estate ETF | K20: 1 | L20: 0 | M20: 0 | N20: 0 | O20: =data[[#This Row],[factor_name]] -> VNQ | P20: {=_xlfn.IFS(data[[#This Row],[description_override]]<>"",data[[#This Row],[description_override]],data[[#This Row],[Description_GPT]]<>"",data[[#This Row],[Description_GPT]],data[[#This Row],[Underlying]]<>"",data[[#This Row],[Underlying]],TRUE,"-")} -> Vanguard Real Estate ETF | Q20: =_xlfn.XLOOKUP(data[[#This Row],[ticker]],yf_desc[ticker],yf_desc[shortName],"-") -> Vanguard Real Estate ETF | R20: =_xlfn.XLOOKUP(data[[#This Row],[ticker]],yf_desc[ticker],yf_desc[longName],"-") -> Vanguard Real Estate Index Fund ETF Shares | S20: =_xlfn.XLOOKUP(data[[#This Row],[ticker]],yf_desc[ticker],yf_desc[longBusinessSummary],"-") -> The advisor attempts to track the index by investing all, or substantially all, of its assets-either directly or indirectly through a wholly owned subsidiary, which is itself a registered investment company-in the stocks that make up the index, holding each stock in approximately the same proportion as its weighting in the index. The fund is non-diversified.
A21: Equities | B21: USD | C21: SMH | D21: yfinance | E21: lognormal | F21: {=_xlfn.SWITCH(data[[#This Row],[diffusion_type]],"lognormal",0.0001,"normal",-0.01)*IF(data[[#This Row],[asset_class]]="Vol",1,1)} -> 0.0001 | H21: Semiconductors | I21: VanEck Semiconductor ETF | K21: 1 | L21: 0 | M21: 0 | N21: 0 | O21: =data[[#This Row],[factor_name]] -> SMH | P21: {=_xlfn.IFS(data[[#This Row],[description_override]]<>"",data[[#This Row],[description_override]],data[[#This Row],[Description_GPT]]<>"",data[[#This Row],[Description_GPT]],data[[#This Row],[Underlying]]<>"",data[[#This Row],[Underlying]],TRUE,"-")} -> Semiconductors | Q21: =_xlfn.XLOOKUP(data[[#This Row],[ticker]],yf_desc[ticker],yf_desc[shortName],"-") -> - | R21: =_xlfn.XLOOKUP(data[[#This Row],[ticker]],yf_desc[ticker],yf_desc[longName],"-") -> - | S21: =_xlfn.XLOOKUP(data[[#This Row],[ticker]],yf_desc[ticker],yf_desc[longBusinessSummary],"-") -> -
A22: Equities | B22: USD | C22: IGV | D22: yfinance | E22: lognormal | F22: {=_xlfn.SWITCH(data[[#This Row],[diffusion_type]],"lognormal",0.0001,"normal",-0.01)*IF(data[[#This Row],[asset_class]]="Vol",1,1)} -> 0.0001 | H22: Software | I22: iShares Expanded Tech-Software Sector ETF | K22: 1 | L22: 0 | M22: 0 | N22: 0 | O22: =data[[#This Row],[factor_name]] -> IGV | P22: {=_xlfn.IFS(data[[#This Row],[description_override]]<>"",data[[#This Row],[description_override]],data[[#This Row],[Description_GPT]]<>"",data[[#This Row],[Description_GPT]],data[[#This Row],[Underlying]]<>"",data[[#This Row],[Underlying]],TRUE,"-")} -> Software | Q22: =_xlfn.XLOOKUP(data[[#This Row],[ticker]],yf_desc[ticker],yf_desc[shortName],"-") -> - | R22: =_xlfn.XLOOKUP(data[[#This Row],[ticker]],yf_desc[ticker],yf_desc[longName],"-") -> - | S22: =_xlfn.XLOOKUP(data[[#This Row],[ticker]],yf_desc[ticker],yf_desc[longBusinessSummary],"-") -> -
A23: Equities | B23: USD | C23: AIQ | D23: yfinance | E23: lognormal | F23: {=_xlfn.SWITCH(data[[#This Row],[diffusion_type]],"lognormal",0.0001,"normal",-0.01)*IF(data[[#This Row],[asset_class]]="Vol",1,1)} -> 0.0001 | H23: Artificial Intelligence | I23: Global X Artificial Intelligence & Technology ETF | K23: 1 | L23: 0 | M23: 0 | N23: 0 | O23: =data[[#This Row],[factor_name]] -> AIQ | P23: {=_xlfn.IFS(data[[#This Row],[description_override]]<>"",data[[#This Row],[description_override]],data[[#This Row],[Description_GPT]]<>"",data[[#This Row],[Description_GPT]],data[[#This Row],[Underlying]]<>"",data[[#This Row],[Underlying]],TRUE,"-")} -> Artificial Intelligence | Q23: =_xlfn.XLOOKUP(data[[#This Row],[ticker]],yf_desc[ticker],yf_desc[shortName],"-") -> Global X Artificial Intelligenc | R23: =_xlfn.XLOOKUP(data[[#This Row],[ticker]],yf_desc[ticker],yf_desc[longName],"-") -> Global X Artificial Intelligence & Technology ETF | S23: =_xlfn.XLOOKUP(data[[#This Row],[ticker]],yf_desc[ticker],yf_desc[longBusinessSummary],"-") -> The fund invests at least 80% of its total assets in the securities of the underlying index. The underlying index is designed to track the performance of companies involved in the development and utilization of artificial intelligence ("AI") and big data. The fund is non-diversified.
A24: Equities | B24: USD | C24: ICLN | D24: yfinance | E24: lognormal | F24: {=_xlfn.SWITCH(data[[#This Row],[diffusion_type]],"lognormal",0.0001,"normal",-0.01)*IF(data[[#This Row],[asset_class]]="Vol",1,1)} -> 0.0001 | H24: Clean Energy | K24: 1 | L24: 0 | M24: 0 | N24: 0 | O24: =data[[#This Row],[factor_name]] -> ICLN | P24: {=_xlfn.IFS(data[[#This Row],[description_override]]<>"",data[[#This Row],[description_override]],data[[#This Row],[Description_GPT]]<>"",data[[#This Row],[Description_GPT]],data[[#This Row],[Underlying]]<>"",data[[#This Row],[Underlying]],TRUE,"-")} -> Clean Energy | Q24: =_xlfn.XLOOKUP(data[[#This Row],[ticker]],yf_desc[ticker],yf_desc[shortName],"-") -> iShares Global Clean Energy ETF | R24: =_xlfn.XLOOKUP(data[[#This Row],[ticker]],yf_desc[ticker],yf_desc[longName],"-") -> iShares Global Clean Energy ETF | S24: =_xlfn.XLOOKUP(data[[#This Row],[ticker]],yf_desc[ticker],yf_desc[longBusinessSummary],"-") -> The index is designed to track the performance of approximately 100 clean energy-related companies. The fund generally invests at least 80% of its assets in the component securities of the index and in investments that have economic characteristics that are substantially identical to the component securities of the index and may invest up to 20% of its assets in certain futures, options and swap contracts, cash and cash equivalents, as well as in securities not included in the index. It is non-diversified.
A25: Equities | B25: USD | C25: BIZD | D25: yfinance | E25: lognormal | F25: {=_xlfn.SWITCH(data[[#This Row],[diffusion_type]],"lognormal",0.0001,"normal",-0.01)*IF(data[[#This Row],[asset_class]]="Vol",1,1)} -> 0.0001 | H25: Private Debt | I25: VanEck BDC Income ETF | K25: 1 | L25: 0 | M25: 0 | N25: 0 | O25: =data[[#This Row],[factor_name]] -> BIZD | P25: {=_xlfn.IFS(data[[#This Row],[description_override]]<>"",data[[#This Row],[description_override]],data[[#This Row],[Description_GPT]]<>"",data[[#This Row],[Description_GPT]],data[[#This Row],[Underlying]]<>"",data[[#This Row],[Underlying]],TRUE,"-")} -> Private Debt | Q25: =_xlfn.XLOOKUP(data[[#This Row],[ticker]],yf_desc[ticker],yf_desc[shortName],"-") -> - | R25: =_xlfn.XLOOKUP(data[[#This Row],[ticker]],yf_desc[ticker],yf_desc[longName],"-") -> - | S25: =_xlfn.XLOOKUP(data[[#This Row],[ticker]],yf_desc[ticker],yf_desc[longBusinessSummary],"-") -> -
A26: Equities | B26: USD | C26: GPZ | D26: yfinance | E26: lognormal | F26: {=_xlfn.SWITCH(data[[#This Row],[diffusion_type]],"lognormal",0.0001,"normal",-0.01)*IF(data[[#This Row],[asset_class]]="Vol",1,1)} -> 0.0001 | H26: Private Alts | I26: VanEck Alternative Asset Manager ETF | K26: 0 | L26: 0 | M26: 0 | N26: 0 | O26: =data[[#This Row],[factor_name]] -> GPZ | P26: {=_xlfn.IFS(data[[#This Row],[description_override]]<>"",data[[#This Row],[description_override]],data[[#This Row],[Description_GPT]]<>"",data[[#This Row],[Description_GPT]],data[[#This Row],[Underlying]]<>"",data[[#This Row],[Underlying]],TRUE,"-")} -> Private Alts | Q26: =_xlfn.XLOOKUP(data[[#This Row],[ticker]],yf_desc[ticker],yf_desc[shortName],"-") -> - | R26: =_xlfn.XLOOKUP(data[[#This Row],[ticker]],yf_desc[ticker],yf_desc[longName],"-") -> - | S26: =_xlfn.XLOOKUP(data[[#This Row],[ticker]],yf_desc[ticker],yf_desc[longBusinessSummary],"-") -> -
A27: Equities | B27: USD | C27: PSP | D27: yfinance | E27: lognormal | F27: {=_xlfn.SWITCH(data[[#This Row],[diffusion_type]],"lognormal",0.0001,"normal",-0.01)*IF(data[[#This Row],[asset_class]]="Vol",1,1)} -> 0.0001 | H27: Private Equity | I27: Invesco Global Listed Private Equity ETF | K27: 1 | L27: 0 | M27: 0 | O27: =data[[#This Row],[factor_name]] -> PSP | P27: {=_xlfn.IFS(data[[#This Row],[description_override]]<>"",data[[#This Row],[description_override]],data[[#This Row],[Description_GPT]]<>"",data[[#This Row],[Description_GPT]],data[[#This Row],[Underlying]]<>"",data[[#This Row],[Underlying]],TRUE,"-")} -> Private Equity | Q27: =_xlfn.XLOOKUP(data[[#This Row],[ticker]],yf_desc[ticker],yf_desc[shortName],"-") -> - | R27: =_xlfn.XLOOKUP(data[[#This Row],[ticker]],yf_desc[ticker],yf_desc[longName],"-") -> - | S27: =_xlfn.XLOOKUP(data[[#This Row],[ticker]],yf_desc[ticker],yf_desc[longBusinessSummary],"-") -> -
A28: Equities | B28: USD | C28: PFF | D28: yfinance | E28: lognormal | F28: {=_xlfn.SWITCH(data[[#This Row],[diffusion_type]],"lognormal",0.0001,"normal",-0.01)*IF(data[[#This Row],[asset_class]]="Vol",1,1)} -> 0.0001 | H28: Preferred | I28: iShares Preferred and Income Securities ETF | K28: 1 | L28: 0 | M28: 0 | N28: 0 | O28: =data[[#This Row],[factor_name]] -> PFF | P28: {=_xlfn.IFS(data[[#This Row],[description_override]]<>"",data[[#This Row],[description_override]],data[[#This Row],[Description_GPT]]<>"",data[[#This Row],[Description_GPT]],data[[#This Row],[Underlying]]<>"",data[[#This Row],[Underlying]],TRUE,"-")} -> Preferred | Q28: =_xlfn.XLOOKUP(data[[#This Row],[ticker]],yf_desc[ticker],yf_desc[shortName],"-") -> iShares Preferred and Income Se | R28: =_xlfn.XLOOKUP(data[[#This Row],[ticker]],yf_desc[ticker],yf_desc[longName],"-") -> iShares Preferred and Income Securities ETF | S28: =_xlfn.XLOOKUP(data[[#This Row],[ticker]],yf_desc[ticker],yf_desc[longBusinessSummary],"-") -> The fund may invest at least 80% of its assets in the component securities of its underlying index and and may invest up to 20% of its assets in certain futures, options and swap contracts, cash and cash equivalents.
A29: Equities | B29: USD | C29: IWN | D29: yfinance | E29: lognormal | F29: {=_xlfn.SWITCH(data[[#This Row],[diffusion_type]],"lognormal",0.0001,"normal",-0.01)*IF(data[[#This Row],[asset_class]]="Vol",1,1)} -> 0.0001 | H29: Value | I29: iShares Russell 2000 Value ETF | O29: =data[[#This Row],[factor_name]] -> IWN | P29: {=_xlfn.IFS(data[[#This Row],[description_override]]<>"",data[[#This Row],[description_override]],data[[#This Row],[Description_GPT]]<>"",data[[#This Row],[Description_GPT]],data[[#This Row],[Underlying]]<>"",data[[#This Row],[Underlying]],TRUE,"-")} -> Value | Q29: =_xlfn.XLOOKUP(data[[#This Row],[ticker]],yf_desc[ticker],yf_desc[shortName],"-") -> - | R29: =_xlfn.XLOOKUP(data[[#This Row],[ticker]],yf_desc[ticker],yf_desc[longName],"-") -> - | S29: =_xlfn.XLOOKUP(data[[#This Row],[ticker]],yf_desc[ticker],yf_desc[longBusinessSummary],"-") -> -
A30: Equities | B30: USD | C30: IWO | D30: yfinance | E30: lognormal | F30: {=_xlfn.SWITCH(data[[#This Row],[diffusion_type]],"lognormal",0.0001,"normal",-0.01)*IF(data[[#This Row],[asset_class]]="Vol",1,1)} -> 0.0001 | H30: Growth | I30: iShares Russell 2000 Growth ETF | O30: =data[[#This Row],[factor_name]] -> IWO | P30: {=_xlfn.IFS(data[[#This Row],[description_override]]<>"",data[[#This Row],[description_override]],data[[#This Row],[Description_GPT]]<>"",data[[#This Row],[Description_GPT]],data[[#This Row],[Underlying]]<>"",data[[#This Row],[Underlying]],TRUE,"-")} -> Growth | Q30: =_xlfn.XLOOKUP(data[[#This Row],[ticker]],yf_desc[ticker],yf_desc[shortName],"-") -> - | R30: =_xlfn.XLOOKUP(data[[#This Row],[ticker]],yf_desc[ticker],yf_desc[longName],"-") -> - | S30: =_xlfn.XLOOKUP(data[[#This Row],[ticker]],yf_desc[ticker],yf_desc[longBusinessSummary],"-") -> -
A31: Equities | B31: USD | C31: MTUM | D31: yfinance | E31: lognormal | F31: {=_xlfn.SWITCH(data[[#This Row],[diffusion_type]],"lognormal",0.0001,"normal",-0.01)*IF(data[[#This Row],[asset_class]]="Vol",1,1)} -> 0.0001 | H31: Momentum | I31: iShares MSCI USA Momentum Factor ETF | O31: =data[[#This Row],[factor_name]] -> MTUM | P31: {=_xlfn.IFS(data[[#This Row],[description_override]]<>"",data[[#This Row],[description_override]],data[[#This Row],[Description_GPT]]<>"",data[[#This Row],[Description_GPT]],data[[#This Row],[Underlying]]<>"",data[[#This Row],[Underlying]],TRUE,"-")} -> Momentum | Q31: =_xlfn.XLOOKUP(data[[#This Row],[ticker]],yf_desc[ticker],yf_desc[shortName],"-") -> - | R31: =_xlfn.XLOOKUP(data[[#This Row],[ticker]],yf_desc[ticker],yf_desc[longName],"-") -> - | S31: =_xlfn.XLOOKUP(data[[#This Row],[ticker]],yf_desc[ticker],yf_desc[longBusinessSummary],"-") -> -
A32: Equities | B32: USD | C32: FEZ | D32: yfinance | E32: lognormal | F32: {=_xlfn.SWITCH(data[[#This Row],[diffusion_type]],"lognormal",0.0001,"normal",-0.01)*IF(data[[#This Row],[asset_class]]="Vol",1,1)} -> 0.0001 | G32: SX5E | H32: Eurostoxx 50 | I32: SPDR EURO STOXX 50 ETF | J32: EURO STOXX 50 Index | K32: 1 | L32: 0 | M32: 0 | N32: 0 | O32: =data[[#This Row],[factor_name]] -> FEZ | P32: {=_xlfn.IFS(data[[#This Row],[description_override]]<>"",data[[#This Row],[description_override]],data[[#This Row],[Description_GPT]]<>"",data[[#This Row],[Description_GPT]],data[[#This Row],[Underlying]]<>"",data[[#This Row],[Underlying]],TRUE,"-")} -> Eurostoxx 50 | Q32: =_xlfn.XLOOKUP(data[[#This Row],[ticker]],yf_desc[ticker],yf_desc[shortName],"-") -> SPDR DJ Euro STOXX 50 Etf | R32: =_xlfn.XLOOKUP(data[[#This Row],[ticker]],yf_desc[ticker],yf_desc[longName],"-") -> SPDR EURO STOXX 50 ETF | S32: =_xlfn.XLOOKUP(data[[#This Row],[ticker]],yf_desc[ticker],yf_desc[longBusinessSummary],"-") -> The fund employs a sampling strategy, which means that the fund is not required to purchase all of the securities represented in the index. It generally invests substantially all, but at least 80%, of its total assets in the securities comprising the index. The index is a market capitalization weighted index designed to represent the performance of some of the largest companies across components of the 20 EURO STOXX Supersector Indexes. The EURO STOXX Supersector Indexes are subsets of the EURO STOXX Index.
A33: Equities | B33: EUR | C33: SX7E | D33: yfinance | E33: lognormal | F33: {=_xlfn.SWITCH(data[[#This Row],[diffusion_type]],"lognormal",0.0001,"normal",-0.01)*IF(data[[#This Row],[asset_class]]="Vol",1,1)} -> 0.0001 | G33: SX7E | H33: Eurostoxx Banks | K33: 0 | L33: 0 | M33: 0 | N33: 0 | O33: =data[[#This Row],[factor_name]] -> SX7E | P33: {=_xlfn.IFS(data[[#This Row],[description_override]]<>"",data[[#This Row],[description_override]],data[[#This Row],[Description_GPT]]<>"",data[[#This Row],[Description_GPT]],data[[#This Row],[Underlying]]<>"",data[[#This Row],[Underlying]],TRUE,"-")} -> Eurostoxx Banks | Q33: =_xlfn.XLOOKUP(data[[#This Row],[ticker]],yf_desc[ticker],yf_desc[shortName],"-") -> - | R33: =_xlfn.XLOOKUP(data[[#This Row],[ticker]],yf_desc[ticker],yf_desc[longName],"-") -> - | S33: =_xlfn.XLOOKUP(data[[#This Row],[ticker]],yf_desc[ticker],yf_desc[longBusinessSummary],"-") -> -
A34: Equities | B34: GBP | C34: EWU | D34: yfinance | E34: lognormal | F34: {=_xlfn.SWITCH(data[[#This Row],[diffusion_type]],"lognormal",0.0001,"normal",-0.01)*IF(data[[#This Row],[asset_class]]="Vol",1,1)} -> 0.0001 | H34: FTSE 100 | I34: iShares FTSE United Kingdom ETF | J34: FTSE 100 Index for the UK | K34: 1 | L34: 0 | M34: 0 | N34: 0 | O34: =data[[#This Row],[factor_name]] -> EWU | P34: {=_xlfn.IFS(data[[#This Row],[description_override]]<>"",data[[#This Row],[description_override]],data[[#This Row],[Description_GPT]]<>"",data[[#This Row],[Description_GPT]],data[[#This Row],[Underlying]]<>"",data[[#This Row],[Underlying]],TRUE,"-")} -> FTSE 100 | Q34: =_xlfn.XLOOKUP(data[[#This Row],[ticker]],yf_desc[ticker],yf_desc[shortName],"-") -> iShares MSCI | R34: =_xlfn.XLOOKUP(data[[#This Row],[ticker]],yf_desc[ticker],yf_desc[longName],"-") -> iShares MSCI United Kingdom ETF | S34: =_xlfn.XLOOKUP(data[[#This Row],[ticker]],yf_desc[ticker],yf_desc[longBusinessSummary],"-") -> The fund generally will invest at least 80% of its assets in the component securities of its underlying index and in investments that have economic characteristics that are substantially identical to the component securities of its underlying index. The underlying index is designed to measure the performance of the large- and mid-capitalization segments of the UK market. The fund is non-diversified.
A35: Equities | B35: EUR | C35: DAX | D35: yfinance | E35: lognormal | F35: {=_xlfn.SWITCH(data[[#This Row],[diffusion_type]],"lognormal",0.0001,"normal",-0.01)*IF(data[[#This Row],[asset_class]]="Vol",1,1)} -> 0.0001 | G35: DAX | H35: DAX (Germany) | I35: Xtrackers DAX Equity ETF | J35: DAX Index for Germany | K35: 1 | L35: 0 | M35: 0 | N35: 0 | O35: =data[[#This Row],[factor_name]] -> DAX | P35: {=_xlfn.IFS(data[[#This Row],[description_override]]<>"",data[[#This Row],[description_override]],data[[#This Row],[Description_GPT]]<>"",data[[#This Row],[Description_GPT]],data[[#This Row],[Underlying]]<>"",data[[#This Row],[Underlying]],TRUE,"-")} -> DAX (Germany) | Q35: =_xlfn.XLOOKUP(data[[#This Row],[ticker]],yf_desc[ticker],yf_desc[shortName],"-") -> Global X DAX Germany ETF | R35: =_xlfn.XLOOKUP(data[[#This Row],[ticker]],yf_desc[ticker],yf_desc[longName],"-") -> Global X DAX Germany ETF | S35: =_xlfn.XLOOKUP(data[[#This Row],[ticker]],yf_desc[ticker],yf_desc[longBusinessSummary],"-") -> The fund invests at least 80% of its total assets in the securities of the underlying index and in American Depositary Receipts ("ADRs") and Global Depositary Receipts ("GDRs") based on the securities in the underlying index. The index tracks the segment of the largest and most actively traded companies - known as blue chips - on the German equities market. The fund is non-diversified.
A36: Equities | B36: CAD | C36: EWC | D36: yfinance | E36: lognormal | F36: {=_xlfn.SWITCH(data[[#This Row],[diffusion_type]],"lognormal",0.0001,"normal",-0.01)*IF(data[[#This Row],[asset_class]]="Vol",1,1)} -> 0.0001 | H36: MSCI Canada | I36: iShares MSCI Canada ETF | J36: Canadian equities | K36: 1 | L36: 0 | M36: 0 | N36: 0 | O36: =data[[#This Row],[factor_name]] -> EWC | P36: {=_xlfn.IFS(data[[#This Row],[description_override]]<>"",data[[#This Row],[description_override]],data[[#This Row],[Description_GPT]]<>"",data[[#This Row],[Description_GPT]],data[[#This Row],[Underlying]]<>"",data[[#This Row],[Underlying]],TRUE,"-")} -> MSCI Canada | Q36: =_xlfn.XLOOKUP(data[[#This Row],[ticker]],yf_desc[ticker],yf_desc[shortName],"-") -> iShares MSCI Canada Index Fund | R36: =_xlfn.XLOOKUP(data[[#This Row],[ticker]],yf_desc[ticker],yf_desc[longName],"-") -> iShares MSCI Canada ETF | S36: =_xlfn.XLOOKUP(data[[#This Row],[ticker]],yf_desc[ticker],yf_desc[longBusinessSummary],"-") -> The fund generally will invest at least 80% of its assets in the component securities of its underlying index and in investments that have economic characteristics that are substantially identical to the component securities of its underlying index. The underlying index is designed to measure broad-based equity performance in Canada. The underlying index includes large- and mid-capitalization companies and may change over time.
A37: Equities | B37: EUR | C37: FTSEMIB.MI | D37: yfinance | E37: lognormal | F37: {=_xlfn.SWITCH(data[[#This Row],[diffusion_type]],"lognormal",0.0001,"normal",-0.01)*IF(data[[#This Row],[asset_class]]="Vol",1,1)} -> 0.0001 | G37: BTP | H37: FTSE MIB (Italy) | K37: 0 | L37: 0 | M37: 0 | N37: 0 | O37: =data[[#This Row],[factor_name]] -> FTSEMIB.MI | P37: {=_xlfn.IFS(data[[#This Row],[description_override]]<>"",data[[#This Row],[description_override]],data[[#This Row],[Description_GPT]]<>"",data[[#This Row],[Description_GPT]],data[[#This Row],[Underlying]]<>"",data[[#This Row],[Underlying]],TRUE,"-")} -> FTSE MIB (Italy) | Q37: =_xlfn.XLOOKUP(data[[#This Row],[ticker]],yf_desc[ticker],yf_desc[shortName],"-") -> FTSE MIB Index | R37: =_xlfn.XLOOKUP(data[[#This Row],[ticker]],yf_desc[ticker],yf_desc[longName],"-") -> FTSE MIB Index | S37: =_xlfn.XLOOKUP(data[[#This Row],[ticker]],yf_desc[ticker],yf_desc[longBusinessSummary],"-") -> 0
A38: Equities | B38: EUR | C38: CAC | D38: yfinance | E38: lognormal | F38: {=_xlfn.SWITCH(data[[#This Row],[diffusion_type]],"lognormal",0.0001,"normal",-0.01)*IF(data[[#This Row],[asset_class]]="Vol",1,1)} -> 0.0001 | G38: CAC | H38: CAC 40 (France) | I38: Lyxor CAC 40 ETF | J38: CAC 40 Index for France | K38: 0 | L38: 0 | M38: 0 | N38: 0 | O38: =data[[#This Row],[factor_name]] -> CAC | P38: {=_xlfn.IFS(data[[#This Row],[description_override]]<>"",data[[#This Row],[description_override]],data[[#This Row],[Description_GPT]]<>"",data[[#This Row],[Description_GPT]],data[[#This Row],[Underlying]]<>"",data[[#This Row],[Underlying]],TRUE,"-")} -> CAC 40 (France) | Q38: =_xlfn.XLOOKUP(data[[#This Row],[ticker]],yf_desc[ticker],yf_desc[shortName],"-") -> Camden National Corporation | R38: =_xlfn.XLOOKUP(data[[#This Row],[ticker]],yf_desc[ticker],yf_desc[longName],"-") -> Camden National Corporation | S38: =_xlfn.XLOOKUP(data[[#This Row],[ticker]],yf_desc[ticker],yf_desc[longBusinessSummary],"-") -> Camden National Corporation operates as the bank holding company for Camden National Bank that provides various commercial and consumer banking products and services for consumer, institutional, municipal, non-profit, and commercial customers in the United States. The company accepts checking, savings, time, and brokered deposits, as well as deposits with the certificate of deposit account registry system. Its loan products include non-owner-occupied commercial real estate loans; owner-occupied commercial real estate loans; commercial loans; residential real estate loans, including one- to four-family residences; and consumer and home equity loans. In addition, the company provides brokerage and insurance services through its financial offerings consisting of college, retirement, estate planning, mutual funds, strategic asset management accounts, and variable and fixed annuities. Further, it offers a range of fiduciary and asset management, wealth management, investment management and advisory, financial planning, and trustee services. Camden National Corporation was founded in 1875 and is headquartered in Camden, Maine.
A39: Equities | B39: EUR | C39: EWI | D39: yfinance | E39: lognormal | F39: {=_xlfn.SWITCH(data[[#This Row],[diffusion_type]],"lognormal",0.0001,"normal",-0.01)*IF(data[[#This Row],[asset_class]]="Vol",1,1)} -> 0.0001 | H39: MSCI Italy | I39: iShares MSCI Italy ETF | J39: Italian equities | K39: 1 | L39: 0 | M39: 0 | N39: 0 | O39: =data[[#This Row],[factor_name]] -> EWI | P39: {=_xlfn.IFS(data[[#This Row],[description_override]]<>"",data[[#This Row],[description_override]],data[[#This Row],[Description_GPT]]<>"",data[[#This Row],[Description_GPT]],data[[#This Row],[Underlying]]<>"",data[[#This Row],[Underlying]],TRUE,"-")} -> MSCI Italy | Q39: =_xlfn.XLOOKUP(data[[#This Row],[ticker]],yf_desc[ticker],yf_desc[shortName],"-") -> iShares Inc iShares MSCI Italy | R39: =_xlfn.XLOOKUP(data[[#This Row],[ticker]],yf_desc[ticker],yf_desc[longName],"-") -> iShares MSCI Italy ETF | S39: =_xlfn.XLOOKUP(data[[#This Row],[ticker]],yf_desc[ticker],yf_desc[longBusinessSummary],"-") -> The fund generally will invest at least 80% of its assets in the component securities of its underlying index and in investments that have economic characteristics that are substantially identical to the component securities of its underlying index. The underlying index is a free float-adjusted market capitalization-weighted index that is designed to measure the performance of the large- and mid-capitalization segments of the equity market in Italy. The fund is non-diversified.
A40: Equities | B40: EUR | C40: ^IBEX | D40: yfinance | E40: lognormal | F40: {=_xlfn.SWITCH(data[[#This Row],[diffusion_type]],"lognormal",0.0001,"normal",-0.01)*IF(data[[#This Row],[asset_class]]="Vol",1,1)} -> 0.0001 | G40: IBEX | H40: IBEX 35 (Spain) | J40: Spanish equities | K40: 0 | L40: 0 | M40: 0 | N40: 0 | O40: =data[[#This Row],[factor_name]] -> ^IBEX | P40: {=_xlfn.IFS(data[[#This Row],[description_override]]<>"",data[[#This Row],[description_override]],data[[#This Row],[Description_GPT]]<>"",data[[#This Row],[Description_GPT]],data[[#This Row],[Underlying]]<>"",data[[#This Row],[Underlying]],TRUE,"-")} -> IBEX 35 (Spain) | Q40: =_xlfn.XLOOKUP(data[[#This Row],[ticker]],yf_desc[ticker],yf_desc[shortName],"-") -> IBEX 35... | R40: =_xlfn.XLOOKUP(data[[#This Row],[ticker]],yf_desc[ticker],yf_desc[longName],"-") -> IBEX 35... | S40: =_xlfn.XLOOKUP(data[[#This Row],[ticker]],yf_desc[ticker],yf_desc[longBusinessSummary],"-") -> 0
A41: Equities | B41: EUR | C41: EWP | D41: yfinance | E41: lognormal | F41: {=_xlfn.SWITCH(data[[#This Row],[diffusion_type]],"lognormal",0.0001,"normal",-0.01)*IF(data[[#This Row],[asset_class]]="Vol",1,1)} -> 0.0001 | H41: MSCI Spain | I41: iShares MSCI Spain ETF | J41: Spanish equities | K41: 0 | L41: 0 | M41: 0 | N41: 0 | O41: =data[[#This Row],[factor_name]] -> EWP | P41: {=_xlfn.IFS(data[[#This Row],[description_override]]<>"",data[[#This Row],[description_override]],data[[#This Row],[Description_GPT]]<>"",data[[#This Row],[Description_GPT]],data[[#This Row],[Underlying]]<>"",data[[#This Row],[Underlying]],TRUE,"-")} -> MSCI Spain | Q41: =_xlfn.XLOOKUP(data[[#This Row],[ticker]],yf_desc[ticker],yf_desc[shortName],"-") -> iShares Inc iShares MSCI Spain | R41: =_xlfn.XLOOKUP(data[[#This Row],[ticker]],yf_desc[ticker],yf_desc[longName],"-") -> iShares MSCI Spain ETF | S41: =_xlfn.XLOOKUP(data[[#This Row],[ticker]],yf_desc[ticker],yf_desc[longBusinessSummary],"-") -> The fund generally will invest at least 80% of its assets in the component securities of its underlying index and in investments that have economic characteristics that are substantially identical to the component securities of its underlying index. The index is a free float-adjusted market capitalization-weighted index that is designed to measure the performance of the large- and mid-capitalization segments of the equity market in Spain. The fund is non-diversified.
A42: Equities | B42: JPY | C42: ^N225 | D42: yfinance | E42: lognormal | F42: {=_xlfn.SWITCH(data[[#This Row],[diffusion_type]],"lognormal",0.0001,"normal",-0.01)*IF(data[[#This Row],[asset_class]]="Vol",1,1)} -> 0.0001 | G42: NKY | H42: Nikkei 225 | I42: Nikkei 225 ETF | J42: Nikkei 225 Index for Japan | K42: 1 | L42: 0 | M42: 0 | N42: 0 | O42: =data[[#This Row],[factor_name]] -> ^N225 | P42: {=_xlfn.IFS(data[[#This Row],[description_override]]<>"",data[[#This Row],[description_override]],data[[#This Row],[Description_GPT]]<>"",data[[#This Row],[Description_GPT]],data[[#This Row],[Underlying]]<>"",data[[#This Row],[Underlying]],TRUE,"-")} -> Nikkei 225 | Q42: =_xlfn.XLOOKUP(data[[#This Row],[ticker]],yf_desc[ticker],yf_desc[shortName],"-") -> Nikkei 225 | R42: =_xlfn.XLOOKUP(data[[#This Row],[ticker]],yf_desc[ticker],yf_desc[longName],"-") -> Nikkei 225 | S42: =_xlfn.XLOOKUP(data[[#This Row],[ticker]],yf_desc[ticker],yf_desc[longBusinessSummary],"-") -> 0
A43: Equities | B43: JPY | C43: TPX | D43: yfinance | E43: lognormal | F43: {=_xlfn.SWITCH(data[[#This Row],[diffusion_type]],"lognormal",0.0001,"normal",-0.01)*IF(data[[#This Row],[asset_class]]="Vol",1,1)} -> 0.0001 | G43: TPX | H43: TOPIX | I43: iShares TOPIX ETF | J43: Tokyo Stock Price Index (TOPIX) | K43: 0 | L43: 0 | M43: 0 | N43: 0 | O43: =data[[#This Row],[factor_name]] -> TPX | P43: {=_xlfn.IFS(data[[#This Row],[description_override]]<>"",data[[#This Row],[description_override]],data[[#This Row],[Description_GPT]]<>"",data[[#This Row],[Description_GPT]],data[[#This Row],[Underlying]]<>"",data[[#This Row],[Underlying]],TRUE,"-")} -> TOPIX | Q43: =_xlfn.XLOOKUP(data[[#This Row],[ticker]],yf_desc[ticker],yf_desc[shortName],"-") -> - | R43: =_xlfn.XLOOKUP(data[[#This Row],[ticker]],yf_desc[ticker],yf_desc[longName],"-") -> - | S43: =_xlfn.XLOOKUP(data[[#This Row],[ticker]],yf_desc[ticker],yf_desc[longBusinessSummary],"-") -> - | T43: Ticker delisted?
A44: Equities | B44: CNH | C44: FXI | D44: yfinance | E44: lognormal | F44: {=_xlfn.SWITCH(data[[#This Row],[diffusion_type]],"lognormal",0.0001,"normal",-0.01)*IF(data[[#This Row],[asset_class]]="Vol",1,1)} -> 0.0001 | G44: FXI | H44: China Large-Cap | I44: iShares China Large-Cap ETF | J44: Large-cap Chinese stocks | K44: 1 | L44: 0 | M44: 0 | N44: 0 | O44: =data[[#This Row],[factor_name]] -> FXI | P44: {=_xlfn.IFS(data[[#This Row],[description_override]]<>"",data[[#This Row],[description_override]],data[[#This Row],[Description_GPT]]<>"",data[[#This Row],[Description_GPT]],data[[#This Row],[Underlying]]<>"",data[[#This Row],[Underlying]],TRUE,"-")} -> China Large-Cap | Q44: =_xlfn.XLOOKUP(data[[#This Row],[ticker]],yf_desc[ticker],yf_desc[shortName],"-") -> iShares China Large-Cap ETF | R44: =_xlfn.XLOOKUP(data[[#This Row],[ticker]],yf_desc[ticker],yf_desc[longName],"-") -> iShares China Large-Cap ETF | S44: =_xlfn.XLOOKUP(data[[#This Row],[ticker]],yf_desc[ticker],yf_desc[longBusinessSummary],"-") -> The fund generally will invest at least 80% of its assets in the component securities of its underlying index and in investments that have economic characteristics that are substantially identical to the component securities of its underlying index. The index designed to measure the performance of the largest companies in the Chinese equity market that trade on the Stock Exchange of Hong Kong and are available to international investors. The fund is non-diversified.
A45: Equities | B45: CNH | C45: ASHR | D45: yfinance | E45: lognormal | F45: {=_xlfn.SWITCH(data[[#This Row],[diffusion_type]],"lognormal",0.0001,"normal",-0.01)*IF(data[[#This Row],[asset_class]]="Vol",1,1)} -> 0.0001 | G45: ASHR | H45: CSI 300 (China) | I45: Xtrackers Harvest CSI 300 China A-Shares ETF | J45: A-shares of the 300 largest companies in China | K45: 1 | L45: 0 | M45: 0 | N45: 0 | O45: =data[[#This Row],[factor_name]] -> ASHR | P45: {=_xlfn.IFS(data[[#This Row],[description_override]]<>"",data[[#This Row],[description_override]],data[[#This Row],[Description_GPT]]<>"",data[[#This Row],[Description_GPT]],data[[#This Row],[Underlying]]<>"",data[[#This Row],[Underlying]],TRUE,"-")} -> CSI 300 (China) | Q45: =_xlfn.XLOOKUP(data[[#This Row],[ticker]],yf_desc[ticker],yf_desc[shortName],"-") -> Xtrackers Harvest CSI 300 China | R45: =_xlfn.XLOOKUP(data[[#This Row],[ticker]],yf_desc[ticker],yf_desc[longName],"-") -> Xtrackers Harvest CSI 300 China A-Shares ETF | S45: =_xlfn.XLOOKUP(data[[#This Row],[ticker]],yf_desc[ticker],yf_desc[longBusinessSummary],"-") -> The fund will normally invest at least 80% of its total assets in securities of issuers that comprise the underlying index. The underlying index is designed to reflect the price fluctuation and performance of the China A-Share market and is composed of the 300 largest and most liquid stocks in the China A-Share market. The underlying index includes small-cap, mid-cap, and large-cap stocks. It is non-diversified.
A46: Equities | B46: CNH | C46: KWEB | D46: yfinance | E46: lognormal | F46: {=_xlfn.SWITCH(data[[#This Row],[diffusion_type]],"lognormal",0.0001,"normal",-0.01)*IF(data[[#This Row],[asset_class]]="Vol",1,1)} -> 0.0001 | G46: KWEB | H46: CSI China Internet | I46: KraneShares CSI China Internet ETF | K46: 1 | L46: 0 | M46: 0 | N46: 0 | O46: =data[[#This Row],[factor_name]] -> KWEB | P46: {=_xlfn.IFS(data[[#This Row],[description_override]]<>"",data[[#This Row],[description_override]],data[[#This Row],[Description_GPT]]<>"",data[[#This Row],[Description_GPT]],data[[#This Row],[Underlying]]<>"",data[[#This Row],[Underlying]],TRUE,"-")} -> CSI China Internet | Q46: =_xlfn.XLOOKUP(data[[#This Row],[ticker]],yf_desc[ticker],yf_desc[shortName],"-") -> KraneShares Trust KraneShares C | R46: =_xlfn.XLOOKUP(data[[#This Row],[ticker]],yf_desc[ticker],yf_desc[longName],"-") -> KraneShares CSI China Internet ETF | S46: =_xlfn.XLOOKUP(data[[#This Row],[ticker]],yf_desc[ticker],yf_desc[longBusinessSummary],"-") -> The fund will invest at least 80% of its net assets in instruments in its underlying index or in instruments that have economic characteristics similar to those in the underlying index. The index is designed to measure the equity market performance of investable publicly traded "China-based companies" whose primary business or businesses are in the Internet and Internet-related sectors, and are listed outside of Mainland China, as determined by the index provider. The fund is non-diversified.
A47: Equities | B47: EM | C47: EEM | D47: yfinance | E47: lognormal | F47: {=_xlfn.SWITCH(data[[#This Row],[diffusion_type]],"lognormal",0.0001,"normal",-0.01)*IF(data[[#This Row],[asset_class]]="Vol",1,1)} -> 0.0001 | H47: MSCI EM | J47: iShares MSCI Emerging Markets ETF | K47: 1 | L47: 0 | M47: 0 | N47: 0 | O47: =data[[#This Row],[factor_name]] -> EEM | P47: {=_xlfn.IFS(data[[#This Row],[description_override]]<>"",data[[#This Row],[description_override]],data[[#This Row],[Description_GPT]]<>"",data[[#This Row],[Description_GPT]],data[[#This Row],[Underlying]]<>"",data[[#This Row],[Underlying]],TRUE,"-")} -> MSCI EM | Q47: =_xlfn.XLOOKUP(data[[#This Row],[ticker]],yf_desc[ticker],yf_desc[shortName],"-") -> iShares MSCI Emerging Index Fun | R47: =_xlfn.XLOOKUP(data[[#This Row],[ticker]],yf_desc[ticker],yf_desc[longName],"-") -> iShares MSCI Emerging Markets ETF | S47: =_xlfn.XLOOKUP(data[[#This Row],[ticker]],yf_desc[ticker],yf_desc[longBusinessSummary],"-") -> The fund generally will invest at least 80% of its assets in the component securities of its underlying index and in investments that have economic characteristics that are substantially identical to the component securities of its underlying index. The index is designed to measure equity market performance in the global emerging markets. The underlying index includes large- and mid-capitalization companies and may change over time.
A48: Credit | B48: USD | C48: LQD | D48: yfinance | E48: lognormal | F48: {=_xlfn.SWITCH(data[[#This Row],[diffusion_type]],"lognormal",0.0001,"normal",-0.01)*IF(data[[#This Row],[asset_class]]="Vol",1,1)} -> 0.0001 | G48: IGB | I48: iShares iBoxx $ Investment Grade Corporate Bond ETF | J48: Investment-grade corporate bonds | K48: 1 | L48: 0 | M48: 0 | N48: 0 | O48: =data[[#This Row],[factor_name]] -> LQD | P48: {=_xlfn.IFS(data[[#This Row],[description_override]]<>"",data[[#This Row],[description_override]],data[[#This Row],[Description_GPT]]<>"",data[[#This Row],[Description_GPT]],data[[#This Row],[Underlying]]<>"",data[[#This Row],[Underlying]],TRUE,"-")} -> iShares iBoxx $ Investment Grade Corporate Bond ETF | Q48: =_xlfn.XLOOKUP(data[[#This Row],[ticker]],yf_desc[ticker],yf_desc[shortName],"-") -> iShares iBoxx $ Investment Grad | R48: =_xlfn.XLOOKUP(data[[#This Row],[ticker]],yf_desc[ticker],yf_desc[longName],"-") -> iShares iBoxx $ Investment Grade Corporate Bond ETF | S48: =_xlfn.XLOOKUP(data[[#This Row],[ticker]],yf_desc[ticker],yf_desc[longBusinessSummary],"-") -> The fund will invest at least 80% of its assets in the component securities of the underlying index, and it will invest at least 90% of its assets in fixed income securities of the types included in the underlying index that the advisor believes will help the fund track the underlying index. The underlying index is designed to provide a broad representation of the U.S. dollar-denominated liquid investment-grade corporate bond market.
A49: Credit | B49: USD | C49: BSV | D49: yfinance | E49: lognormal | F49: {=_xlfn.SWITCH(data[[#This Row],[diffusion_type]],"lognormal",0.0001,"normal",-0.01)*IF(data[[#This Row],[asset_class]]="Vol",1,1)} -> 0.0001 | I49: Vanguard Short-Term Bond Index Fund ETF | J49: Investment-grade short-dated bonds | K49: 1 | L49: 0 | M49: 0 | N49: 0 | O49: =data[[#This Row],[factor_name]] -> BSV | P49: {=_xlfn.IFS(data[[#This Row],[description_override]]<>"",data[[#This Row],[description_override]],data[[#This Row],[Description_GPT]]<>"",data[[#This Row],[Description_GPT]],data[[#This Row],[Underlying]]<>"",data[[#This Row],[Underlying]],TRUE,"-")} -> Vanguard Short-Term Bond Index Fund ETF | Q49: =_xlfn.XLOOKUP(data[[#This Row],[ticker]],yf_desc[ticker],yf_desc[shortName],"-") -> Vanguard Short-Term Bond ETF | R49: =_xlfn.XLOOKUP(data[[#This Row],[ticker]],yf_desc[ticker],yf_desc[longName],"-") -> Vanguard Short-Term Bond Index Fund ETF Shares | S49: =_xlfn.XLOOKUP(data[[#This Row],[ticker]],yf_desc[ticker],yf_desc[longBusinessSummary],"-") -> This index includes all medium and larger issues of U.S. government, investment-grade corporate, and investment-grade international dollar-denominated bonds that have maturities between 1 and 5 years and are publicly issued. All of the fund's investments will be selected through the sampling process, and at least 80% of its assets will be invested in bonds held in the index.
A50: Credit | B50: USD | C50: HYG | D50: yfinance | E50: lognormal | F50: {=_xlfn.SWITCH(data[[#This Row],[diffusion_type]],"lognormal",0.0001,"normal",-0.01)*IF(data[[#This Row],[asset_class]]="Vol",1,1)} -> 0.0001 | G50: HYB | I50: iShares iBoxx $ High Yield Corporate Bond ETF | J50: High-yield corporate bonds | K50: 1 | L50: 0 | M50: 0 | N50: 0 | O50: =data[[#This Row],[factor_name]] -> HYG | P50: {=_xlfn.IFS(data[[#This Row],[description_override]]<>"",data[[#This Row],[description_override]],data[[#This Row],[Description_GPT]]<>"",data[[#This Row],[Description_GPT]],data[[#This Row],[Underlying]]<>"",data[[#This Row],[Underlying]],TRUE,"-")} -> iShares iBoxx $ High Yield Corporate Bond ETF | Q50: =_xlfn.XLOOKUP(data[[#This Row],[ticker]],yf_desc[ticker],yf_desc[shortName],"-") -> iShares iBoxx $ High Yield Corp | R50: =_xlfn.XLOOKUP(data[[#This Row],[ticker]],yf_desc[ticker],yf_desc[longName],"-") -> iShares iBoxx $ High Yield Corporate Bond ETF | S50: =_xlfn.XLOOKUP(data[[#This Row],[ticker]],yf_desc[ticker],yf_desc[longBusinessSummary],"-") -> The underlying index is a rules-based index consisting of U.S. dollar-denominated, high yield corporate bonds for sale in the U.S. The fund will invest at least 80% of its assets in the component securities of the underlying index, and the fund will invest at least 90% of its assets in fixed income securities of the types included in the underlying index that the advisor believes will help the fund track the underlying index.
A51: Credit | B51: USD | C51: LQDH | D51: yfinance | E51: lognormal | F51: {=_xlfn.SWITCH(data[[#This Row],[diffusion_type]],"lognormal",0.0001,"normal",-0.01)*IF(data[[#This Row],[asset_class]]="Vol",1,1)} -> 0.0001 | G51: IG | H51: Hedged LQD | J51: iShares Interest Rate Hedged Corporate Bond ETF | K51: 1 | L51: 1 | M51: 0 | N51: 0 | O51: =data[[#This Row],[factor_name]] -> LQDH | P51: {=_xlfn.IFS(data[[#This Row],[description_override]]<>"",data[[#This Row],[description_override]],data[[#This Row],[Description_GPT]]<>"",data[[#This Row],[Description_GPT]],data[[#This Row],[Underlying]]<>"",data[[#This Row],[Underlying]],TRUE,"-")} -> Hedged LQD | Q51: =_xlfn.XLOOKUP(data[[#This Row],[ticker]],yf_desc[ticker],yf_desc[shortName],"-") -> iShares Interest Rate Hedged Co | R51: =_xlfn.XLOOKUP(data[[#This Row],[ticker]],yf_desc[ticker],yf_desc[longName],"-") -> iShares Interest Rate Hedged Corporate Bond ETF | S51: =_xlfn.XLOOKUP(data[[#This Row],[ticker]],yf_desc[ticker],yf_desc[longBusinessSummary],"-") -> The index is designed to minimize the interest-rate risk exposure of a portfolio composed of U.S. dollar-denominated, investment grade bonds, represented in the index by the underlying fund, by including a series of up to 10 interest rate swap contracts with different maturities. The fund invests, under normal circumstances, at least 80% of its net assets, plus the amount of any borrowings for investment purposes, in component securities and instruments in the index and/or bonds included in the underlying index of the underlying fund.
A52: Credit | B52: USD | C52: HYGH | D52: yfinance | E52: lognormal | F52: {=_xlfn.SWITCH(data[[#This Row],[diffusion_type]],"lognormal",0.0001,"normal",-0.01)*IF(data[[#This Row],[asset_class]]="Vol",1,1)} -> 0.0001 | G52: HY | H52: Hedged HYG | J52: iShares Interest Rate Hedged High Yield Bond ETF | K52: 1 | L52: 0 | M52: 0 | N52: 0 | O52: =data[[#This Row],[factor_name]] -> HYGH | P52: {=_xlfn.IFS(data[[#This Row],[description_override]]<>"",data[[#This Row],[description_override]],data[[#This Row],[Description_GPT]]<>"",data[[#This Row],[Description_GPT]],data[[#This Row],[Underlying]]<>"",data[[#This Row],[Underlying]],TRUE,"-")} -> Hedged HYG | Q52: =_xlfn.XLOOKUP(data[[#This Row],[ticker]],yf_desc[ticker],yf_desc[shortName],"-") -> iShares Interest Rate Hedged Hi | R52: =_xlfn.XLOOKUP(data[[#This Row],[ticker]],yf_desc[ticker],yf_desc[longName],"-") -> iShares Interest Rate Hedged High Yield Bond ETF | S52: =_xlfn.XLOOKUP(data[[#This Row],[ticker]],yf_desc[ticker],yf_desc[longBusinessSummary],"-") -> The fund seeks to track the investment results of the underlying index, which is designed to minimize the interest-rate risk of a portfolio composed of U.S. dollar-denominated, high yield corporate bonds, represented in the underlying index by the underlying fund. It invests at least 80% of its net assets in component securities and instruments in the fund’s underlying index.
A53: Credit | B53: USD | C53: BKLN | D53: yfinance | E53: lognormal | F53: {=_xlfn.SWITCH(data[[#This Row],[diffusion_type]],"lognormal",0.0001,"normal",-0.01)*IF(data[[#This Row],[asset_class]]="Vol",1,1)} -> 0.0001 | G53: HY | H53: Bank Loans | K53: 1 | L53: 0 | M53: 0 | N53: 0 | O53: =data[[#This Row],[factor_name]] -> BKLN | P53: {=_xlfn.IFS(data[[#This Row],[description_override]]<>"",data[[#This Row],[description_override]],data[[#This Row],[Description_GPT]]<>"",data[[#This Row],[Description_GPT]],data[[#This Row],[Underlying]]<>"",data[[#This Row],[Underlying]],TRUE,"-")} -> Bank Loans | Q53: =_xlfn.XLOOKUP(data[[#This Row],[ticker]],yf_desc[ticker],yf_desc[shortName],"-") -> - | R53: =_xlfn.XLOOKUP(data[[#This Row],[ticker]],yf_desc[ticker],yf_desc[longName],"-") -> - | S53: =_xlfn.XLOOKUP(data[[#This Row],[ticker]],yf_desc[ticker],yf_desc[longBusinessSummary],"-") -> -
A54: Credit | B54: USD | C54: AGG | D54: yfinance | E54: lognormal | F54: {=_xlfn.SWITCH(data[[#This Row],[diffusion_type]],"lognormal",0.0001,"normal",-0.01)*IF(data[[#This Row],[asset_class]]="Vol",1,1)} -> 0.0001 | H54: US Agg | J54: iShares Core US Aggregate Bond ETF | K54: 1 | L54: 0 | M54: 0 | N54: 0 | O54: =data[[#This Row],[factor_name]] -> AGG | P54: {=_xlfn.IFS(data[[#This Row],[description_override]]<>"",data[[#This Row],[description_override]],data[[#This Row],[Description_GPT]]<>"",data[[#This Row],[Description_GPT]],data[[#This Row],[Underlying]]<>"",data[[#This Row],[Underlying]],TRUE,"-")} -> US Agg | Q54: =_xlfn.XLOOKUP(data[[#This Row],[ticker]],yf_desc[ticker],yf_desc[shortName],"-") -> iShares Core U.S. Aggregate Bon | R54: =_xlfn.XLOOKUP(data[[#This Row],[ticker]],yf_desc[ticker],yf_desc[longName],"-") -> iShares Core U.S. Aggregate Bond ETF | S54: =_xlfn.XLOOKUP(data[[#This Row],[ticker]],yf_desc[ticker],yf_desc[longBusinessSummary],"-") -> The index measures the performance of the total U.S. investment-grade bond market. The fund will invest at least 80% of its assets in the component securities of the underlying index and TBAs that have economic characteristics that are substantially identical to the economic characteristics of the component securities of the underlying index, and the fund will invest at least 90% of its assets in fixed income securities of the types included in the underlying index that the advisor believes will help the fund track the underlying index.
A55: Rates | B55: USD | C55: ^TNX | D55: yfinance | E55: normal | F55: {=_xlfn.SWITCH(data[[#This Row],[diffusion_type]],"lognormal",0.0001,"normal",-0.01)*IF(data[[#This Row],[asset_class]]="Vol",1,1)} -> -0.01 | J55: CBOE Interest Rate 10 Year | K55: 1 | L55: 0 | M55: 0 | N55: 0 | O55: =data[[#This Row],[factor_name]] -> ^TNX | P55: {=_xlfn.IFS(data[[#This Row],[description_override]]<>"",data[[#This Row],[description_override]],data[[#This Row],[Description_GPT]]<>"",data[[#This Row],[Description_GPT]],data[[#This Row],[Underlying]]<>"",data[[#This Row],[Underlying]],TRUE,"-")} -> CBOE Interest Rate 10 Year | Q55: =_xlfn.XLOOKUP(data[[#This Row],[ticker]],yf_desc[ticker],yf_desc[shortName],"-") -> CBOE Interest Rate 10 Year T No | R55: =_xlfn.XLOOKUP(data[[#This Row],[ticker]],yf_desc[ticker],yf_desc[longName],"-") -> CBOE Interest Rate 10 Year T No | S55: =_xlfn.XLOOKUP(data[[#This Row],[ticker]],yf_desc[ticker],yf_desc[longBusinessSummary],"-") -> 0
A56: Rates | B56: USD | C56: SHY | D56: yfinance | E56: lognormal | F56: {=_xlfn.SWITCH(data[[#This Row],[diffusion_type]],"lognormal",0.0001,"normal",-0.01)*IF(data[[#This Row],[asset_class]]="Vol",1,1)} -> 0.0001 | G56: USD02 | H56: =_xlfn.TEXTBEFORE(_xlfn.TEXTAFTER(data[[#This Row],[Description_GPT]],"iShares ")," Bond") -> 1-3 Year Treasury | I56: iShares 1-3 Year Treasury Bond ETF | J56: Short-term U.S. Treasury bonds (1-3 years) | K56: 1 | L56: 0 | M56: 0 | N56: 0 | O56: =data[[#This Row],[factor_name]] -> SHY | P56: {=_xlfn.IFS(data[[#This Row],[description_override]]<>"",data[[#This Row],[description_override]],data[[#This Row],[Description_GPT]]<>"",data[[#This Row],[Description_GPT]],data[[#This Row],[Underlying]]<>"",data[[#This Row],[Underlying]],TRUE,"-")} -> 1-3 Year Treasury | Q56: =_xlfn.XLOOKUP(data[[#This Row],[ticker]],yf_desc[ticker],yf_desc[shortName],"-") -> iShares 1-3 Year Treasury Bond | R56: =_xlfn.XLOOKUP(data[[#This Row],[ticker]],yf_desc[ticker],yf_desc[longName],"-") -> iShares 1-3 Year Treasury Bond ETF | S56: =_xlfn.XLOOKUP(data[[#This Row],[ticker]],yf_desc[ticker],yf_desc[longBusinessSummary],"-") -> The fund will invest at least 80% of its assets in the component securities of the underlying index and it will invest at least 90% of its assets in U.S. Treasury securities that BFA believes will help the fund track the underlying index. The underlying index measures the performance of public obligations of the U.S. Treasury that have a remaining maturity of greater than or equal to one year and less than three years.
A57: Rates | B57: USD | C57: IEI | D57: yfinance | E57: lognormal | F57: {=_xlfn.SWITCH(data[[#This Row],[diffusion_type]],"lognormal",0.0001,"normal",-0.01)*IF(data[[#This Row],[asset_class]]="Vol",1,1)} -> 0.0001 | G57: USD05 | H57: =_xlfn.TEXTBEFORE(_xlfn.TEXTAFTER(data[[#This Row],[Description_GPT]],"iShares ")," Bond") -> 3-7 Year Treasury | I57: iShares 3-7 Year Treasury Bond ETF | J57: Intermediate-term U.S. Treasury bonds (3-7 years) | K57: 1 | L57: 0 | M57: 0 | N57: 0 | O57: =data[[#This Row],[factor_name]] -> IEI | P57: {=_xlfn.IFS(data[[#This Row],[description_override]]<>"",data[[#This Row],[description_override]],data[[#This Row],[Description_GPT]]<>"",data[[#This Row],[Description_GPT]],data[[#This Row],[Underlying]]<>"",data[[#This Row],[Underlying]],TRUE,"-")} -> 3-7 Year Treasury | Q57: =_xlfn.XLOOKUP(data[[#This Row],[ticker]],yf_desc[ticker],yf_desc[shortName],"-") -> iShares 3-7 Year Treasury Bond | R57: =_xlfn.XLOOKUP(data[[#This Row],[ticker]],yf_desc[ticker],yf_desc[longName],"-") -> iShares 3-7 Year Treasury Bond ETF | S57: =_xlfn.XLOOKUP(data[[#This Row],[ticker]],yf_desc[ticker],yf_desc[longBusinessSummary],"-") -> The index measures the performance of public obligations of the U.S. Treasury that have a remaining maturity of greater than or equal to three years and less than seven years. The fund will invest at least 80% of its assets in the component securities of the index, and the fund will invest at least 90% of its assets in U.S. Treasury securities that BFA believes will help the fund track the index.
A58: Rates | B58: USD | C58: IEF | D58: yfinance | E58: lognormal | F58: {=_xlfn.SWITCH(data[[#This Row],[diffusion_type]],"lognormal",0.0001,"normal",-0.01)*IF(data[[#This Row],[asset_class]]="Vol",1,1)} -> 0.0001 | G58: USD10 | H58: =_xlfn.TEXTBEFORE(_xlfn.TEXTAFTER(data[[#This Row],[Description_GPT]],"iShares ")," Bond") -> 7-10 Year Treasury | I58: iShares 7-10 Year Treasury Bond ETF | J58: Intermediate-term U.S. Treasury bonds (7-10 years) | K58: 1 | L58: 1 | M58: 0 | N58: 0 | O58: =data[[#This Row],[factor_name]] -> IEF | P58: {=_xlfn.IFS(data[[#This Row],[description_override]]<>"",data[[#This Row],[description_override]],data[[#This Row],[Description_GPT]]<>"",data[[#This Row],[Description_GPT]],data[[#This Row],[Underlying]]<>"",data[[#This Row],[Underlying]],TRUE,"-")} -> 7-10 Year Treasury | Q58: =_xlfn.XLOOKUP(data[[#This Row],[ticker]],yf_desc[ticker],yf_desc[shortName],"-") -> iShares 7-10 Year Treasury Bond | R58: =_xlfn.XLOOKUP(data[[#This Row],[ticker]],yf_desc[ticker],yf_desc[longName],"-") -> iShares 7-10 Year Treasury Bond ETF | S58: =_xlfn.XLOOKUP(data[[#This Row],[ticker]],yf_desc[ticker],yf_desc[longBusinessSummary],"-") -> The underlying index measures the performance of public obligations of the U.S. Treasury that have a remaining maturity of greater than or equal to seven years and less than ten years. The fund will invest at least 80% of its assets in the component securities of the underlying index, and the fund will invest at least 90% of its assets in U.S. Treasury securities that the advisor believes will help the fund track the underlying index.
A59: Rates | B59: USD | C59: TLT | D59: yfinance | E59: lognormal | F59: {=_xlfn.SWITCH(data[[#This Row],[diffusion_type]],"lognormal",0.0001,"normal",-0.01)*IF(data[[#This Row],[asset_class]]="Vol",1,1)} -> 0.0001 | G59: USD30 | H59: =_xlfn.TEXTBEFORE(_xlfn.TEXTAFTER(data[[#This Row],[Description_GPT]],"iShares ")," Bond") -> 20+ Year Treasury | I59: iShares 20+ Year Treasury Bond ETF | J59: Long-term U.S. Treasury bonds (20+ years) | K59: 1 | L59: 0 | M59: 0 | N59: 0 | O59: =data[[#This Row],[factor_name]] -> TLT | P59: {=_xlfn.IFS(data[[#This Row],[description_override]]<>"",data[[#This Row],[description_override]],data[[#This Row],[Description_GPT]]<>"",data[[#This Row],[Description_GPT]],data[[#This Row],[Underlying]]<>"",data[[#This Row],[Underlying]],TRUE,"-")} -> 20+ Year Treasury | Q59: =_xlfn.XLOOKUP(data[[#This Row],[ticker]],yf_desc[ticker],yf_desc[shortName],"-") -> iShares 20+ Year Treasury Bond | R59: =_xlfn.XLOOKUP(data[[#This Row],[ticker]],yf_desc[ticker],yf_desc[longName],"-") -> iShares 20+ Year Treasury Bond ETF | S59: =_xlfn.XLOOKUP(data[[#This Row],[ticker]],yf_desc[ticker],yf_desc[longBusinessSummary],"-") -> The fund will invest at least 80% of its assets in the component securities of the underlying index, and it will invest at least 90% of its assets in U.S. Treasury securities that the advisor believes will help the fund track the underlying index. The underlying index measures the performance of public obligations of the U.S. Treasury that have a remaining maturity greater than or equal to twenty years.
A60: Rates | B60: USD | C60: TIP | D60: yfinance | E60: lognormal | F60: {=_xlfn.SWITCH(data[[#This Row],[diffusion_type]],"lognormal",0.0001,"normal",-0.01)*IF(data[[#This Row],[asset_class]]="Vol",1,1)} -> 0.0001 | I60: iShares TIPS Bond ETF | J60: U.S. Treasury Inflation-Protected Securities (TIPS) | K60: 1 | L60: 0 | M60: 0 | N60: 0 | O60: =data[[#This Row],[factor_name]] -> TIP | P60: {=_xlfn.IFS(data[[#This Row],[description_override]]<>"",data[[#This Row],[description_override]],data[[#This Row],[Description_GPT]]<>"",data[[#This Row],[Description_GPT]],data[[#This Row],[Underlying]]<>"",data[[#This Row],[Underlying]],TRUE,"-")} -> iShares TIPS Bond ETF | Q60: =_xlfn.XLOOKUP(data[[#This Row],[ticker]],yf_desc[ticker],yf_desc[shortName],"-") -> iShares TIPS Bond ETF | R60: =_xlfn.XLOOKUP(data[[#This Row],[ticker]],yf_desc[ticker],yf_desc[longName],"-") -> iShares TIPS Bond ETF | S60: =_xlfn.XLOOKUP(data[[#This Row],[ticker]],yf_desc[ticker],yf_desc[longBusinessSummary],"-") -> The index tracks the performance of inflation-protected public obligations of the U.S. Treasury, commonly known as “TIPS,” that have a remaining maturity of more than one year. The fund will invest at least 80% of its assets in the component securities of the index, and it will invest at least 90% of its assets in U.S. Treasury securities that BFA believes will help the fund track the index.
A61: Rates | B61: USD | C61: VTIP | D61: yfinance | E61: lognormal | F61: {=_xlfn.SWITCH(data[[#This Row],[diffusion_type]],"lognormal",0.0001,"normal",-0.01)*IF(data[[#This Row],[asset_class]]="Vol",1,1)} -> 0.0001 | J61: Short-Term Inflation-Protected Securities ETF | K61: 1 | L61: 0 | M61: 0 | N61: 0 | O61: =data[[#This Row],[factor_name]] -> VTIP | P61: {=_xlfn.IFS(data[[#This Row],[description_override]]<>"",data[[#This Row],[description_override]],data[[#This Row],[Description_GPT]]<>"",data[[#This Row],[Description_GPT]],data[[#This Row],[Underlying]]<>"",data[[#This Row],[Underlying]],TRUE,"-")} -> Short-Term Inflation-Protected Securities ETF | Q61: =_xlfn.XLOOKUP(data[[#This Row],[ticker]],yf_desc[ticker],yf_desc[shortName],"-") -> Vanguard Short-Term Inflation-P | R61: =_xlfn.XLOOKUP(data[[#This Row],[ticker]],yf_desc[ticker],yf_desc[longName],"-") -> Vanguard Short-Term Inflation-Protected Securities Index Fund ETF Shares | S61: =_xlfn.XLOOKUP(data[[#This Row],[ticker]],yf_desc[ticker],yf_desc[longBusinessSummary],"-") -> The index is a market-capitalization-weighted index that includes all inflation-protected public obligations issued by the U.S. Treasury with remaining maturities of less than 5 years.
A62: Rates | B62: USD | C62: MBB | D62: yfinance | E62: lognormal | F62: {=_xlfn.SWITCH(data[[#This Row],[diffusion_type]],"lognormal",0.0001,"normal",-0.01)*IF(data[[#This Row],[asset_class]]="Vol",1,1)} -> 0.0001 | I62: iShares MBS ETF | J62: U.S. mortgage-backed securities | K62: 0 | L62: 0 | M62: 0 | N62: 0 | O62: =data[[#This Row],[factor_name]] -> MBB | P62: {=_xlfn.IFS(data[[#This Row],[description_override]]<>"",data[[#This Row],[description_override]],data[[#This Row],[Description_GPT]]<>"",data[[#This Row],[Description_GPT]],data[[#This Row],[Underlying]]<>"",data[[#This Row],[Underlying]],TRUE,"-")} -> iShares MBS ETF | Q62: =_xlfn.XLOOKUP(data[[#This Row],[ticker]],yf_desc[ticker],yf_desc[shortName],"-") -> iShares MBS ETF | R62: =_xlfn.XLOOKUP(data[[#This Row],[ticker]],yf_desc[ticker],yf_desc[longName],"-") -> iShares MBS ETF | S62: =_xlfn.XLOOKUP(data[[#This Row],[ticker]],yf_desc[ticker],yf_desc[longBusinessSummary],"-") -> The fund will invest at least 80% of its assets in the component securities of the underlying index and TBAs that have economic characteristics that are substantially identical to the economic characteristics of the component securities of the index, and the fund will invest at least 90% of its assets in fixed income securities of the types included in the underlying index that BFA believes will help the fund track the index.
A63: Rates | B63: USD | C63: MBTA | D63: yfinance | E63: lognormal | F63: {=_xlfn.SWITCH(data[[#This Row],[diffusion_type]],"lognormal",0.0001,"normal",-0.01)*IF(data[[#This Row],[asset_class]]="Vol",1,1)} -> 0.0001 | I63: Simplify Mortgage Backed Securities ETF | J63: U.S. mortgage-backed securities (short duration) | K63: 0 | L63: 0 | M63: 0 | N63: 0 | O63: =data[[#This Row],[factor_name]] -> MBTA | P63: {=_xlfn.IFS(data[[#This Row],[description_override]]<>"",data[[#This Row],[description_override]],data[[#This Row],[Description_GPT]]<>"",data[[#This Row],[Description_GPT]],data[[#This Row],[Underlying]]<>"",data[[#This Row],[Underlying]],TRUE,"-")} -> Simplify Mortgage Backed Securities ETF | Q63: =_xlfn.XLOOKUP(data[[#This Row],[ticker]],yf_desc[ticker],yf_desc[shortName],"-") -> - | R63: =_xlfn.XLOOKUP(data[[#This Row],[ticker]],yf_desc[ticker],yf_desc[longName],"-") -> - | S63: =_xlfn.XLOOKUP(data[[#This Row],[ticker]],yf_desc[ticker],yf_desc[longBusinessSummary],"-") -> -
A64: Rates | B64: USD | C64: AGNC | D64: yfinance | E64: lognormal | F64: {=_xlfn.SWITCH(data[[#This Row],[diffusion_type]],"lognormal",0.0001,"normal",-0.01)*IF(data[[#This Row],[asset_class]]="Vol",1,1)} -> 0.0001 | I64: AGNC Investment Corp. | J64: Agency mortgage-backed securities | K64: 1 | L64: 0 | M64: 0 | N64: 0 | O64: =data[[#This Row],[factor_name]] -> AGNC | P64: {=_xlfn.IFS(data[[#This Row],[description_override]]<>"",data[[#This Row],[description_override]],data[[#This Row],[Description_GPT]]<>"",data[[#This Row],[Description_GPT]],data[[#This Row],[Underlying]]<>"",data[[#This Row],[Underlying]],TRUE,"-")} -> AGNC Investment Corp. | Q64: =_xlfn.XLOOKUP(data[[#This Row],[ticker]],yf_desc[ticker],yf_desc[shortName],"-") -> AGNC Investment Corp. | R64: =_xlfn.XLOOKUP(data[[#This Row],[ticker]],yf_desc[ticker],yf_desc[longName],"-") -> AGNC Investment Corp. | S64: =_xlfn.XLOOKUP(data[[#This Row],[ticker]],yf_desc[ticker],yf_desc[longBusinessSummary],"-") -> AGNC Investment Corp. provides private capital to housing market in the United States. The company invests in residential mortgage pass-through securities and collateralized mortgage obligations for which the principal and interest payments are guaranteed by the United States government-sponsored enterprise or by the United States government agency. It qualifies as a real estate investment trust for federal income tax purposes. The company generally would not be subject to federal or state corporate income taxes if it distributes at least 90% of its taxable income to its stockholders. The company was formerly known as American Capital Agency Corp. and changed its name to AGNC Investment Corp. in September 2016. AGNC Investment Corp. was incorporated in 2008 and is headquartered in Bethesda, Maryland.
A65: Rates | B65: USD | C65: VMBS | D65: yfinance | E65: lognormal | F65: {=_xlfn.SWITCH(data[[#This Row],[diffusion_type]],"lognormal",0.0001,"normal",-0.01)*IF(data[[#This Row],[asset_class]]="Vol",1,1)} -> 0.0001 | J65: Mortgage-Backed Securities ETF | K65: 1 | L65: 0 | M65: 0 | N65: 0 | O65: =data[[#This Row],[factor_name]] -> VMBS | P65: {=_xlfn.IFS(data[[#This Row],[description_override]]<>"",data[[#This Row],[description_override]],data[[#This Row],[Description_GPT]]<>"",data[[#This Row],[Description_GPT]],data[[#This Row],[Underlying]]<>"",data[[#This Row],[Underlying]],TRUE,"-")} -> Mortgage-Backed Securities ETF | Q65: =_xlfn.XLOOKUP(data[[#This Row],[ticker]],yf_desc[ticker],yf_desc[shortName],"-") -> Vanguard Mortgage-Backed Securi | R65: =_xlfn.XLOOKUP(data[[#This Row],[ticker]],yf_desc[ticker],yf_desc[longName],"-") -> Vanguard Mortgage-Backed Securities Index Fund ETF Shares | S65: =_xlfn.XLOOKUP(data[[#This Row],[ticker]],yf_desc[ticker],yf_desc[longBusinessSummary],"-") -> The fund employs an indexing investment approach designed to track the performance of the Bloomberg U.S. MBS Float Adjusted Index. This index covers U.S. agency mortgage-backed pass-through securities issued by the GNMA, the FNMA, and the FHLMC. To be included in the index, pool aggregates must have at least $1 billion currently outstanding and a weighted average maturity of at least 1 year. All of the fund's investments will be selected through the sampling process, and at least 80% of the fund's assets will be invested in bonds included in the index.
A66: Rates | B66: USD | C66: CMBS | D66: yfinance | E66: lognormal | F66: {=_xlfn.SWITCH(data[[#This Row],[diffusion_type]],"lognormal",0.0001,"normal",-0.01)*IF(data[[#This Row],[asset_class]]="Vol",1,1)} -> 0.0001 | J66: iShares CMBS ETF | K66: 1 | L66: 0 | M66: 0 | N66: 0 | O66: =data[[#This Row],[factor_name]] -> CMBS | P66: {=_xlfn.IFS(data[[#This Row],[description_override]]<>"",data[[#This Row],[description_override]],data[[#This Row],[Description_GPT]]<>"",data[[#This Row],[Description_GPT]],data[[#This Row],[Underlying]]<>"",data[[#This Row],[Underlying]],TRUE,"-")} -> iShares CMBS ETF | Q66: =_xlfn.XLOOKUP(data[[#This Row],[ticker]],yf_desc[ticker],yf_desc[shortName],"-") -> iShares CMBS Bond ETF | R66: =_xlfn.XLOOKUP(data[[#This Row],[ticker]],yf_desc[ticker],yf_desc[longName],"-") -> iShares CMBS ETF | S66: =_xlfn.XLOOKUP(data[[#This Row],[ticker]],yf_desc[ticker],yf_desc[longBusinessSummary],"-") -> The index measures the performance of investment-grade commercial mortgage-backed securities ("CMBS"), which are classes of securities (known as "certificates") that represent interests in "pools" of commercial mortgages. The fund will invest at least 80% of its assets in the component securities of the underlying index, and it will invest at least 90% of its assets in fixed income securities of the types included in the underlying index that BFA believes will help the fund track the underlying index.
A67: Rates | B67: EM | C67: EMB | D67: yfinance | E67: lognormal | F67: {=_xlfn.SWITCH(data[[#This Row],[diffusion_type]],"lognormal",0.0001,"normal",-0.01)*IF(data[[#This Row],[asset_class]]="Vol",1,1)} -> 0.0001 | I67: iShares J.P. Morgan USD Emerging Markets Bond ETF | J67: U.S. dollar-denominated bonds issued by emerging market governments | K67: 1 | L67: 0 | M67: 0 | N67: 0 | O67: =data[[#This Row],[factor_name]] -> EMB | P67: {=_xlfn.IFS(data[[#This Row],[description_override]]<>"",data[[#This Row],[description_override]],data[[#This Row],[Description_GPT]]<>"",data[[#This Row],[Description_GPT]],data[[#This Row],[Underlying]]<>"",data[[#This Row],[Underlying]],TRUE,"-")} -> iShares J.P. Morgan USD Emerging Markets Bond ETF | Q67: =_xlfn.XLOOKUP(data[[#This Row],[ticker]],yf_desc[ticker],yf_desc[shortName],"-") -> iShares J.P. Morgan USD Emergin | R67: =_xlfn.XLOOKUP(data[[#This Row],[ticker]],yf_desc[ticker],yf_desc[longName],"-") -> iShares J.P. Morgan USD Emerging Markets Bond ETF | S67: =_xlfn.XLOOKUP(data[[#This Row],[ticker]],yf_desc[ticker],yf_desc[longBusinessSummary],"-") -> The fund will invest at least 80% of its assets in the component securities of the underlying index and will invest at least 90% of its assets in fixed income securities of the types included in the underlying index. The index is a broad, diverse U.S. dollar-denominated emerging markets debt benchmark that tracks the total return of actively traded external debt instruments in emerging market countries.
A68: Rates | B68: EM | C68: EMHY | D68: yfinance | E68: lognormal | F68: {=_xlfn.SWITCH(data[[#This Row],[diffusion_type]],"lognormal",0.0001,"normal",-0.01)*IF(data[[#This Row],[asset_class]]="Vol",1,1)} -> 0.0001 | J68: iShares JP Morgan EM High Yield Bond ETF | K68: 0 | L68: 0 | M68: 0 | N68: 0 | O68: =data[[#This Row],[factor_name]] -> EMHY | P68: {=_xlfn.IFS(data[[#This Row],[description_override]]<>"",data[[#This Row],[description_override]],data[[#This Row],[Description_GPT]]<>"",data[[#This Row],[Description_GPT]],data[[#This Row],[Underlying]]<>"",data[[#This Row],[Underlying]],TRUE,"-")} -> iShares JP Morgan EM High Yield Bond ETF | Q68: =_xlfn.XLOOKUP(data[[#This Row],[ticker]],yf_desc[ticker],yf_desc[shortName],"-") -> iShares J.P. Morgan EM High Yie | R68: =_xlfn.XLOOKUP(data[[#This Row],[ticker]],yf_desc[ticker],yf_desc[longName],"-") -> iShares J.P. Morgan EM High Yield Bond ETF | S68: =_xlfn.XLOOKUP(data[[#This Row],[ticker]],yf_desc[ticker],yf_desc[longBusinessSummary],"-") -> The fund will invest at least 80% of its assets in the component securities of the underlying index, and the fund will invest at least 90% of its assets in fixed income securities of the types included in the underlying index that BFA believes will help the fund track the underlying index. The index tracks the performance of below investment-grade U.S. dollar-denominated, emerging market fixed and floating-rate debt securities issued by corporate, sovereign, and quasi-sovereign entities.
A69: Rates | B69: EM | C69: CEW | D69: yfinance | E69: lognormal | F69: {=_xlfn.SWITCH(data[[#This Row],[diffusion_type]],"lognormal",0.0001,"normal",-0.01)*IF(data[[#This Row],[asset_class]]="Vol",1,1)} -> 0.0001 | I69: WisdomTree Emerging Markets Local Debt Fund | J69: Local currency emerging market debt | K69: 0 | L69: 0 | M69: 0 | N69: 0 | O69: =data[[#This Row],[factor_name]] -> CEW | P69: {=_xlfn.IFS(data[[#This Row],[description_override]]<>"",data[[#This Row],[description_override]],data[[#This Row],[Description_GPT]]<>"",data[[#This Row],[Description_GPT]],data[[#This Row],[Underlying]]<>"",data[[#This Row],[Underlying]],TRUE,"-")} -> WisdomTree Emerging Markets Local Debt Fund | Q69: =_xlfn.XLOOKUP(data[[#This Row],[ticker]],yf_desc[ticker],yf_desc[shortName],"-") -> WisdomTree Emerging Currency St | R69: =_xlfn.XLOOKUP(data[[#This Row],[ticker]],yf_desc[ticker],yf_desc[longName],"-") -> WisdomTree Emerging Currency Strategy Fund | S69: =_xlfn.XLOOKUP(data[[#This Row],[ticker]],yf_desc[ticker],yf_desc[longBusinessSummary],"-") -> The fund will invest, under normal circumstances, at least 80% of its net assets, plus the amount of any borrowings for investment purposes, in investments whose combined performance is tied economically to selected emerging market countries. It generally will maintain a weighted average portfolio maturity of 90 days or less with respect to the money market securities in its portfolio. The fund is non-diversified.
A70: Rates | B70: EM | C70: IGOV | D70: yfinance | E70: lognormal | F70: {=_xlfn.SWITCH(data[[#This Row],[diffusion_type]],"lognormal",0.0001,"normal",-0.01)*IF(data[[#This Row],[asset_class]]="Vol",1,1)} -> 0.0001 | I70: iShares International Government Bonds ETF | J70: Government bonds in developed markets | K70: 0 | L70: 0 | M70: 0 | N70: 0 | O70: =data[[#This Row],[factor_name]] -> IGOV | P70: {=_xlfn.IFS(data[[#This Row],[description_override]]<>"",data[[#This Row],[description_override]],data[[#This Row],[Description_GPT]]<>"",data[[#This Row],[Description_GPT]],data[[#This Row],[Underlying]]<>"",data[[#This Row],[Underlying]],TRUE,"-")} -> iShares International Government Bonds ETF | Q70: =_xlfn.XLOOKUP(data[[#This Row],[ticker]],yf_desc[ticker],yf_desc[shortName],"-") -> iShares International Treasury | R70: =_xlfn.XLOOKUP(data[[#This Row],[ticker]],yf_desc[ticker],yf_desc[longName],"-") -> iShares International Treasury Bond ETF | S70: =_xlfn.XLOOKUP(data[[#This Row],[ticker]],yf_desc[ticker],yf_desc[longBusinessSummary],"-") -> The fund will invest at least 80% of its assets in the component securities of the underlying index and will invest at least 90% of its assets in fixed income securities of the types included in the underlying index. The underlying index measures the performance of fixed-rate, local currency, investment-grade, sovereign bonds from certain developed markets. The fund is non-diversified.
A71: Commodities | B71: USD | C71: GLD | D71: yfinance | E71: lognormal | F71: {=_xlfn.SWITCH(data[[#This Row],[diffusion_type]],"lognormal",0.0001,"normal",-0.01)*IF(data[[#This Row],[asset_class]]="Vol",1,1)} -> 0.0001 | G71: GOLD | I71: SPDR Gold Shares | J71: Price of gold | K71: 1 | L71: 0 | M71: 0 | N71: 0 | O71: =data[[#This Row],[factor_name]] -> GLD | P71: {=_xlfn.IFS(data[[#This Row],[description_override]]<>"",data[[#This Row],[description_override]],data[[#This Row],[Description_GPT]]<>"",data[[#This Row],[Description_GPT]],data[[#This Row],[Underlying]]<>"",data[[#This Row],[Underlying]],TRUE,"-")} -> SPDR Gold Shares | Q71: =_xlfn.XLOOKUP(data[[#This Row],[ticker]],yf_desc[ticker],yf_desc[shortName],"-") -> SPDR Gold Trust | R71: =_xlfn.XLOOKUP(data[[#This Row],[ticker]],yf_desc[ticker],yf_desc[longName],"-") -> SPDR Gold Shares | S71: =_xlfn.XLOOKUP(data[[#This Row],[ticker]],yf_desc[ticker],yf_desc[longBusinessSummary],"-") -> The Trust holds gold bars and from time to time, issues Baskets in exchange for deposits of gold and distributes gold in connection with redemptions of Baskets. The investment objective of the Trust is for the Shares to reflect the performance of the price of gold bullion, less the Trust’s expenses. The Sponsor believes that, for many investors, the Shares represent a cost-effective investment in gold.
A72: Commodities | B72: USD | C72: SLV | D72: yfinance | E72: lognormal | F72: {=_xlfn.SWITCH(data[[#This Row],[diffusion_type]],"lognormal",0.0001,"normal",-0.01)*IF(data[[#This Row],[asset_class]]="Vol",1,1)} -> 0.0001 | G72: SILVER | I72: iShares Silver Trust | J72: Price of silver | K72: 1 | L72: 0 | M72: 0 | N72: 0 | O72: =data[[#This Row],[factor_name]] -> SLV | P72: {=_xlfn.IFS(data[[#This Row],[description_override]]<>"",data[[#This Row],[description_override]],data[[#This Row],[Description_GPT]]<>"",data[[#This Row],[Description_GPT]],data[[#This Row],[Underlying]]<>"",data[[#This Row],[Underlying]],TRUE,"-")} -> iShares Silver Trust | Q72: =_xlfn.XLOOKUP(data[[#This Row],[ticker]],yf_desc[ticker],yf_desc[shortName],"-") -> iShares Silver Trust | R72: =_xlfn.XLOOKUP(data[[#This Row],[ticker]],yf_desc[ticker],yf_desc[longName],"-") -> iShares Silver Trust | S72: =_xlfn.XLOOKUP(data[[#This Row],[ticker]],yf_desc[ticker],yf_desc[longBusinessSummary],"-") -> The Trust seeks to reflect such performance before payment of the Trust's expenses and liabilities. It is not actively managed. The Trust does not engage in any activities designed to obtain a profit from, or to ameliorate losses caused by, changes in the price of silver.
A73: Commodities | B73: USD | C73: USO | D73: yfinance | E73: lognormal | F73: {=_xlfn.SWITCH(data[[#This Row],[diffusion_type]],"lognormal",0.0001,"normal",-0.01)*IF(data[[#This Row],[asset_class]]="Vol",1,1)} -> 0.0001 | G73: OIL | I73: United States Oil Fund | J73: Price of West Texas Intermediate crude oil | K73: 1 | L73: 0 | M73: 0 | N73: 0 | O73: =data[[#This Row],[factor_name]] -> USO | P73: {=_xlfn.IFS(data[[#This Row],[description_override]]<>"",data[[#This Row],[description_override]],data[[#This Row],[Description_GPT]]<>"",data[[#This Row],[Description_GPT]],data[[#This Row],[Underlying]]<>"",data[[#This Row],[Underlying]],TRUE,"-")} -> United States Oil Fund | Q73: =_xlfn.XLOOKUP(data[[#This Row],[ticker]],yf_desc[ticker],yf_desc[shortName],"-") -> United States Oil Fund | R73: =_xlfn.XLOOKUP(data[[#This Row],[ticker]],yf_desc[ticker],yf_desc[longName],"-") -> United States Oil Fund, LP | S73: =_xlfn.XLOOKUP(data[[#This Row],[ticker]],yf_desc[ticker],yf_desc[longBusinessSummary],"-") -> USO invests primarily in futures contracts for light, sweet crude oil, other types of crude oil, diesel-heating oil, gasoline, natural gas, and other petroleum-based fuels.
A74: Commodities | B74: USD | C74: DBA | D74: yfinance | E74: lognormal | F74: {=_xlfn.SWITCH(data[[#This Row],[diffusion_type]],"lognormal",0.0001,"normal",-0.01)*IF(data[[#This Row],[asset_class]]="Vol",1,1)} -> 0.0001 | G74: AGRI | O74: =data[[#This Row],[factor_name]] -> DBA | P74: {=_xlfn.IFS(data[[#This Row],[description_override]]<>"",data[[#This Row],[description_override]],data[[#This Row],[Description_GPT]]<>"",data[[#This Row],[Description_GPT]],data[[#This Row],[Underlying]]<>"",data[[#This Row],[Underlying]],TRUE,"-")} -> - | Q74: =_xlfn.XLOOKUP(data[[#This Row],[ticker]],yf_desc[ticker],yf_desc[shortName],"-") -> - | R74: =_xlfn.XLOOKUP(data[[#This Row],[ticker]],yf_desc[ticker],yf_desc[longName],"-") -> - | S74: =_xlfn.XLOOKUP(data[[#This Row],[ticker]],yf_desc[ticker],yf_desc[longBusinessSummary],"-") -> -
A75: Commodities | B75: USD | C75: DBB | D75: yfinance | E75: lognormal | F75: {=_xlfn.SWITCH(data[[#This Row],[diffusion_type]],"lognormal",0.0001,"normal",-0.01)*IF(data[[#This Row],[asset_class]]="Vol",1,1)} -> 0.0001 | G75: METAL_BASE | O75: =data[[#This Row],[factor_name]] -> DBB | P75: {=_xlfn.IFS(data[[#This Row],[description_override]]<>"",data[[#This Row],[description_override]],data[[#This Row],[Description_GPT]]<>"",data[[#This Row],[Description_GPT]],data[[#This Row],[Underlying]]<>"",data[[#This Row],[Underlying]],TRUE,"-")} -> - | Q75: =_xlfn.XLOOKUP(data[[#This Row],[ticker]],yf_desc[ticker],yf_desc[shortName],"-") -> - | R75: =_xlfn.XLOOKUP(data[[#This Row],[ticker]],yf_desc[ticker],yf_desc[longName],"-") -> - | S75: =_xlfn.XLOOKUP(data[[#This Row],[ticker]],yf_desc[ticker],yf_desc[longBusinessSummary],"-") -> -
A76: Commodities | B76: USD | C76: DBC | D76: yfinance | E76: lognormal | F76: {=_xlfn.SWITCH(data[[#This Row],[diffusion_type]],"lognormal",0.0001,"normal",-0.01)*IF(data[[#This Row],[asset_class]]="Vol",1,1)} -> 0.0001 | G76: COMMOD | I76: Invesco DB Commodity Index Tracking Fund | J76: Broad commodity index | K76: 0 | L76: 0 | M76: 0 | N76: 0 | O76: =data[[#This Row],[factor_name]] -> DBC | P76: {=_xlfn.IFS(data[[#This Row],[description_override]]<>"",data[[#This Row],[description_override]],data[[#This Row],[Description_GPT]]<>"",data[[#This Row],[Description_GPT]],data[[#This Row],[Underlying]]<>"",data[[#This Row],[Underlying]],TRUE,"-")} -> Invesco DB Commodity Index Tracking Fund | Q76: =_xlfn.XLOOKUP(data[[#This Row],[ticker]],yf_desc[ticker],yf_desc[shortName],"-") -> Invesco DB Commodity Index Trac | R76: =_xlfn.XLOOKUP(data[[#This Row],[ticker]],yf_desc[ticker],yf_desc[longName],"-") -> Invesco DB Commodity Index Tracking Fund | S76: =_xlfn.XLOOKUP(data[[#This Row],[ticker]],yf_desc[ticker],yf_desc[longBusinessSummary],"-") -> The fund pursues its investment objective by investing in a portfolio of exchange-traded futures on Light Sweet Crude Oil (WTI), Heating Oil, RBOB Gasoline, Natural Gas, Brent Crude, Gold, Silver, Aluminum, Zinc, Copper Grade A, Corn, Wheat, Soybeans, and Sugar. The index is composed of notional amounts of each of these commodities.
A77: Commodities | B77: USD | C77: DBE | D77: yfinance | E77: lognormal | F77: {=_xlfn.SWITCH(data[[#This Row],[diffusion_type]],"lognormal",0.0001,"normal",-0.01)*IF(data[[#This Row],[asset_class]]="Vol",1,1)} -> 0.0001 | G77: ENERGY | O77: =data[[#This Row],[factor_name]] -> DBE | P77: {=_xlfn.IFS(data[[#This Row],[description_override]]<>"",data[[#This Row],[description_override]],data[[#This Row],[Description_GPT]]<>"",data[[#This Row],[Description_GPT]],data[[#This Row],[Underlying]]<>"",data[[#This Row],[Underlying]],TRUE,"-")} -> - | Q77: =_xlfn.XLOOKUP(data[[#This Row],[ticker]],yf_desc[ticker],yf_desc[shortName],"-") -> - | R77: =_xlfn.XLOOKUP(data[[#This Row],[ticker]],yf_desc[ticker],yf_desc[longName],"-") -> - | S77: =_xlfn.XLOOKUP(data[[#This Row],[ticker]],yf_desc[ticker],yf_desc[longBusinessSummary],"-") -> -
A78: Commodities | B78: USD | C78: DBO | D78: yfinance | E78: lognormal | F78: {=_xlfn.SWITCH(data[[#This Row],[diffusion_type]],"lognormal",0.0001,"normal",-0.01)*IF(data[[#This Row],[asset_class]]="Vol",1,1)} -> 0.0001 | G78: OIL | O78: =data[[#This Row],[factor_name]] -> DBO | P78: {=_xlfn.IFS(data[[#This Row],[description_override]]<>"",data[[#This Row],[description_override]],data[[#This Row],[Description_GPT]]<>"",data[[#This Row],[Description_GPT]],data[[#This Row],[Underlying]]<>"",data[[#This Row],[Underlying]],TRUE,"-")} -> - | Q78: =_xlfn.XLOOKUP(data[[#This Row],[ticker]],yf_desc[ticker],yf_desc[shortName],"-") -> - | R78: =_xlfn.XLOOKUP(data[[#This Row],[ticker]],yf_desc[ticker],yf_desc[longName],"-") -> - | S78: =_xlfn.XLOOKUP(data[[#This Row],[ticker]],yf_desc[ticker],yf_desc[longBusinessSummary],"-") -> -
A79: Commodities | B79: USD | C79: DBP | D79: yfinance | E79: lognormal | F79: {=_xlfn.SWITCH(data[[#This Row],[diffusion_type]],"lognormal",0.0001,"normal",-0.01)*IF(data[[#This Row],[asset_class]]="Vol",1,1)} -> 0.0001 | G79: METALS_PREC | O79: =data[[#This Row],[factor_name]] -> DBP | P79: {=_xlfn.IFS(data[[#This Row],[description_override]]<>"",data[[#This Row],[description_override]],data[[#This Row],[Description_GPT]]<>"",data[[#This Row],[Description_GPT]],data[[#This Row],[Underlying]]<>"",data[[#This Row],[Underlying]],TRUE,"-")} -> - | Q79: =_xlfn.XLOOKUP(data[[#This Row],[ticker]],yf_desc[ticker],yf_desc[shortName],"-") -> - | R79: =_xlfn.XLOOKUP(data[[#This Row],[ticker]],yf_desc[ticker],yf_desc[longName],"-") -> - | S79: =_xlfn.XLOOKUP(data[[#This Row],[ticker]],yf_desc[ticker],yf_desc[longBusinessSummary],"-") -> -
A80: Currencies | B80: USD | C80: UUP | D80: yfinance | E80: lognormal | F80: {=_xlfn.SWITCH(data[[#This Row],[diffusion_type]],"lognormal",0.0001,"normal",-0.01)*IF(data[[#This Row],[asset_class]]="Vol",1,1)} -> 0.0001 | I80: Invesco DB US Dollar Index Bullish Fund | J80: U.S. Dollar Index | K80: 1 | L80: 0 | M80: 0 | N80: 0 | O80: =data[[#This Row],[factor_name]] -> UUP | P80: {=_xlfn.IFS(data[[#This Row],[description_override]]<>"",data[[#This Row],[description_override]],data[[#This Row],[Description_GPT]]<>"",data[[#This Row],[Description_GPT]],data[[#This Row],[Underlying]]<>"",data[[#This Row],[Underlying]],TRUE,"-")} -> Invesco DB US Dollar Index Bullish Fund | Q80: =_xlfn.XLOOKUP(data[[#This Row],[ticker]],yf_desc[ticker],yf_desc[shortName],"-") -> Invesco DB USD Index Bullish Fu | R80: =_xlfn.XLOOKUP(data[[#This Row],[ticker]],yf_desc[ticker],yf_desc[longName],"-") -> Invesco DB US Dollar Index Bullish Fund | S80: =_xlfn.XLOOKUP(data[[#This Row],[ticker]],yf_desc[ticker],yf_desc[longBusinessSummary],"-") -> The fund invests in futures contracts in an attempt to track its index. The index is calculated to reflect the changes in market value over time, whether positive or negative, of long positions in DX Contracts.
A81: Currencies | B81: USD | C81: DX-Y.NYB | D81: yfinance | E81: lognormal | F81: {=_xlfn.SWITCH(data[[#This Row],[diffusion_type]],"lognormal",0.0001,"normal",-0.01)*IF(data[[#This Row],[asset_class]]="Vol",1,1)} -> 0.0001 | G81: DXY | J81: U.S. Dollar Index | K81: 1 | L81: 0 | M81: 0 | N81: 0 | O81: =data[[#This Row],[factor_name]] -> DX-Y.NYB | P81: {=_xlfn.IFS(data[[#This Row],[description_override]]<>"",data[[#This Row],[description_override]],data[[#This Row],[Description_GPT]]<>"",data[[#This Row],[Description_GPT]],data[[#This Row],[Underlying]]<>"",data[[#This Row],[Underlying]],TRUE,"-")} -> U.S. Dollar Index | Q81: =_xlfn.XLOOKUP(data[[#This Row],[ticker]],yf_desc[ticker],yf_desc[shortName],"-") -> ICE US Dollar Index - Index - C | R81: =_xlfn.XLOOKUP(data[[#This Row],[ticker]],yf_desc[ticker],yf_desc[longName],"-") -> US Dollar Index | S81: =_xlfn.XLOOKUP(data[[#This Row],[ticker]],yf_desc[ticker],yf_desc[longBusinessSummary],"-") -> 0
A82: Currencies | B82: EUR | C82: FXE | D82: yfinance | E82: lognormal | F82: {=_xlfn.SWITCH(data[[#This Row],[diffusion_type]],"lognormal",0.0001,"normal",-0.01)*IF(data[[#This Row],[asset_class]]="Vol",1,1)} -> 0.0001 | G82: EURUSD | I82: Invesco CurrencyShares Euro Trust | J82: Euro against the U.S. dollar | K82: 1 | L82: 0 | M82: 0 | N82: 0 | O82: =data[[#This Row],[factor_name]] -> FXE | P82: {=_xlfn.IFS(data[[#This Row],[description_override]]<>"",data[[#This Row],[description_override]],data[[#This Row],[Description_GPT]]<>"",data[[#This Row],[Description_GPT]],data[[#This Row],[Underlying]]<>"",data[[#This Row],[Underlying]],TRUE,"-")} -> Invesco CurrencyShares Euro Trust | Q82: =_xlfn.XLOOKUP(data[[#This Row],[ticker]],yf_desc[ticker],yf_desc[shortName],"-") -> Invesco CurrencyShares Euro Cur | R82: =_xlfn.XLOOKUP(data[[#This Row],[ticker]],yf_desc[ticker],yf_desc[longName],"-") -> Invesco CurrencyShares Euro Currency Trust | S82: =_xlfn.XLOOKUP(data[[#This Row],[ticker]],yf_desc[ticker],yf_desc[longBusinessSummary],"-") -> 0
A83: Currencies | B83: EUR | C83: FXF | D83: yfinance | E83: lognormal | F83: {=_xlfn.SWITCH(data[[#This Row],[diffusion_type]],"lognormal",0.0001,"normal",-0.01)*IF(data[[#This Row],[asset_class]]="Vol",1,1)} -> 0.0001 | G83: CHFUSD | I83: Invesco CurrencyShares Swiss Franc Trust | J83: Swiss franc against the U.S. dollar | K83: 1 | L83: 0 | M83: 0 | N83: 0 | O83: =data[[#This Row],[factor_name]] -> FXF | P83: {=_xlfn.IFS(data[[#This Row],[description_override]]<>"",data[[#This Row],[description_override]],data[[#This Row],[Description_GPT]]<>"",data[[#This Row],[Description_GPT]],data[[#This Row],[Underlying]]<>"",data[[#This Row],[Underlying]],TRUE,"-")} -> Invesco CurrencyShares Swiss Franc Trust | Q83: =_xlfn.XLOOKUP(data[[#This Row],[ticker]],yf_desc[ticker],yf_desc[shortName],"-") -> Invesco CurrencyShares Swiss Fr | R83: =_xlfn.XLOOKUP(data[[#This Row],[ticker]],yf_desc[ticker],yf_desc[longName],"-") -> Invesco CurrencyShares Swiss Franc Trust | S83: =_xlfn.XLOOKUP(data[[#This Row],[ticker]],yf_desc[ticker],yf_desc[longBusinessSummary],"-") -> The fund seeks to reflect the price of the Swiss Franc. The sponsor believes that, for many investors, the shares represent a cost-effective investment relative to traditional means of investing in the foreign exchange market.
A84: Currencies | B84: Commod | C84: FXA | D84: yfinance | E84: lognormal | F84: {=_xlfn.SWITCH(data[[#This Row],[diffusion_type]],"lognormal",0.0001,"normal",-0.01)*IF(data[[#This Row],[asset_class]]="Vol",1,1)} -> 0.0001 | G84: AUDUSD | I84: Invesco CurrencyShares Australian Dollar Trust | K84: 1 | L84: 0 | M84: 0 | N84: 0 | O84: =data[[#This Row],[factor_name]] -> FXA | P84: {=_xlfn.IFS(data[[#This Row],[description_override]]<>"",data[[#This Row],[description_override]],data[[#This Row],[Description_GPT]]<>"",data[[#This Row],[Description_GPT]],data[[#This Row],[Underlying]]<>"",data[[#This Row],[Underlying]],TRUE,"-")} -> Invesco CurrencyShares Australian Dollar Trust | Q84: =_xlfn.XLOOKUP(data[[#This Row],[ticker]],yf_desc[ticker],yf_desc[shortName],"-") -> - | R84: =_xlfn.XLOOKUP(data[[#This Row],[ticker]],yf_desc[ticker],yf_desc[longName],"-") -> - | S84: =_xlfn.XLOOKUP(data[[#This Row],[ticker]],yf_desc[ticker],yf_desc[longBusinessSummary],"-") -> -
A85: Currencies | B85: GBP | C85: FXB | D85: yfinance | E85: lognormal | F85: {=_xlfn.SWITCH(data[[#This Row],[diffusion_type]],"lognormal",0.0001,"normal",-0.01)*IF(data[[#This Row],[asset_class]]="Vol",1,1)} -> 0.0001 | G85: GBPUSD | I85: Invesco CurrencyShares British Pound Sterling Trust | K85: 1 | L85: 0 | M85: 0 | N85: 0 | O85: =data[[#This Row],[factor_name]] -> FXB | P85: {=_xlfn.IFS(data[[#This Row],[description_override]]<>"",data[[#This Row],[description_override]],data[[#This Row],[Description_GPT]]<>"",data[[#This Row],[Description_GPT]],data[[#This Row],[Underlying]]<>"",data[[#This Row],[Underlying]],TRUE,"-")} -> Invesco CurrencyShares British Pound Sterling Trust | Q85: =_xlfn.XLOOKUP(data[[#This Row],[ticker]],yf_desc[ticker],yf_desc[shortName],"-") -> - | R85: =_xlfn.XLOOKUP(data[[#This Row],[ticker]],yf_desc[ticker],yf_desc[longName],"-") -> - | S85: =_xlfn.XLOOKUP(data[[#This Row],[ticker]],yf_desc[ticker],yf_desc[longBusinessSummary],"-") -> -
A86: Currencies | B86: USD | C86: FXC | D86: yfinance | E86: lognormal | F86: {=_xlfn.SWITCH(data[[#This Row],[diffusion_type]],"lognormal",0.0001,"normal",-0.01)*IF(data[[#This Row],[asset_class]]="Vol",1,1)} -> 0.0001 | G86: CADUSD | I86: Invesco CurrencyShares Canadian Dollar Trust | K86: 1 | L86: 0 | M86: 0 | N86: 0 | O86: =data[[#This Row],[factor_name]] -> FXC | P86: {=_xlfn.IFS(data[[#This Row],[description_override]]<>"",data[[#This Row],[description_override]],data[[#This Row],[Description_GPT]]<>"",data[[#This Row],[Description_GPT]],data[[#This Row],[Underlying]]<>"",data[[#This Row],[Underlying]],TRUE,"-")} -> Invesco CurrencyShares Canadian Dollar Trust | Q86: =_xlfn.XLOOKUP(data[[#This Row],[ticker]],yf_desc[ticker],yf_desc[shortName],"-") -> - | R86: =_xlfn.XLOOKUP(data[[#This Row],[ticker]],yf_desc[ticker],yf_desc[longName],"-") -> - | S86: =_xlfn.XLOOKUP(data[[#This Row],[ticker]],yf_desc[ticker],yf_desc[longBusinessSummary],"-") -> -
A87: Currencies | B87: JPY | C87: FXY | D87: yfinance | E87: lognormal | F87: {=_xlfn.SWITCH(data[[#This Row],[diffusion_type]],"lognormal",0.0001,"normal",-0.01)*IF(data[[#This Row],[asset_class]]="Vol",1,1)} -> 0.0001 | G87: JPYUSD | I87: Invesco CurrencyShares Japanese Yen Trust | J87: Japanese yen against the U.S. dollar | K87: 1 | L87: 0 | M87: 0 | N87: 0 | O87: =data[[#This Row],[factor_name]] -> FXY | P87: {=_xlfn.IFS(data[[#This Row],[description_override]]<>"",data[[#This Row],[description_override]],data[[#This Row],[Description_GPT]]<>"",data[[#This Row],[Description_GPT]],data[[#This Row],[Underlying]]<>"",data[[#This Row],[Underlying]],TRUE,"-")} -> Invesco CurrencyShares Japanese Yen Trust | Q87: =_xlfn.XLOOKUP(data[[#This Row],[ticker]],yf_desc[ticker],yf_desc[shortName],"-") -> Invesco CurrencyShares Japanese | R87: =_xlfn.XLOOKUP(data[[#This Row],[ticker]],yf_desc[ticker],yf_desc[longName],"-") -> Invesco CurrencyShares Japanese Yen Trust | S87: =_xlfn.XLOOKUP(data[[#This Row],[ticker]],yf_desc[ticker],yf_desc[longBusinessSummary],"-") -> The fund seeks to reflect the price in USD of the Japanese Yen. The sponsor believes that, for many investors, the shares represent a cost-effective investment relative to traditional means of investing in the foreign exchange market.
A88: Vol | B88: USD | C88: ^VIX | D88: yfinance | E88: normal | F88: {=_xlfn.SWITCH(data[[#This Row],[diffusion_type]],"lognormal",0.0001,"normal",-0.01)*IF(data[[#This Row],[asset_class]]="Vol",1,1)} -> -0.01 | I88: CBOE Volatility Index | K88: 1 | L88: 0 | M88: 0 | N88: 0 | O88: =data[[#This Row],[factor_name]] -> ^VIX | P88: {=_xlfn.IFS(data[[#This Row],[description_override]]<>"",data[[#This Row],[description_override]],data[[#This Row],[Description_GPT]]<>"",data[[#This Row],[Description_GPT]],data[[#This Row],[Underlying]]<>"",data[[#This Row],[Underlying]],TRUE,"-")} -> CBOE Volatility Index | Q88: =_xlfn.XLOOKUP(data[[#This Row],[ticker]],yf_desc[ticker],yf_desc[shortName],"-") -> CBOE Volatility Index | R88: =_xlfn.XLOOKUP(data[[#This Row],[ticker]],yf_desc[ticker],yf_desc[longName],"-") -> CBOE Volatility Index | S88: =_xlfn.XLOOKUP(data[[#This Row],[ticker]],yf_desc[ticker],yf_desc[longBusinessSummary],"-") -> 0
A89: Vol | B89: USD | C89: VXX | D89: yfinance | E89: normal | F89: {=_xlfn.SWITCH(data[[#This Row],[diffusion_type]],"lognormal",0.0001,"normal",-0.01)*IF(data[[#This Row],[asset_class]]="Vol",1,1)} -> -0.01 | I89: VIX Short-Term Futures ETN | K89: 1 | L89: 0 | M89: 0 | N89: 0 | O89: =data[[#This Row],[factor_name]] -> VXX | P89: {=_xlfn.IFS(data[[#This Row],[description_override]]<>"",data[[#This Row],[description_override]],data[[#This Row],[Description_GPT]]<>"",data[[#This Row],[Description_GPT]],data[[#This Row],[Underlying]]<>"",data[[#This Row],[Underlying]],TRUE,"-")} -> VIX Short-Term Futures ETN | Q89: =_xlfn.XLOOKUP(data[[#This Row],[ticker]],yf_desc[ticker],yf_desc[shortName],"-") -> iPath Series B S&P 500 VIX Shor | R89: =_xlfn.XLOOKUP(data[[#This Row],[ticker]],yf_desc[ticker],yf_desc[longName],"-") -> iPath Series B S&P 500 VIX Short-Term Futures ETN | S89: =_xlfn.XLOOKUP(data[[#This Row],[ticker]],yf_desc[ticker],yf_desc[longBusinessSummary],"-") -> The ETN offers exposure to futures contracts of specified maturities on the VIX index and not direct exposure to the VIX index or its spot level. The index is designed to provide investors with exposure to one or more maturities of futures contracts on the CBOE Volatility Index®.
A90: Vol | B90: USD | C90: ^VIX3M | D90: yfinance | E90: normal | F90: {=_xlfn.SWITCH(data[[#This Row],[diffusion_type]],"lognormal",0.0001,"normal",-0.01)*IF(data[[#This Row],[asset_class]]="Vol",1,1)} -> -0.01 | I90: CBOE S&P 500 3-Month Volatility | K90: 1 | L90: 0 | M90: 0 | N90: 0 | O90: =data[[#This Row],[factor_name]] -> ^VIX3M | P90: {=_xlfn.IFS(data[[#This Row],[description_override]]<>"",data[[#This Row],[description_override]],data[[#This Row],[Description_GPT]]<>"",data[[#This Row],[Description_GPT]],data[[#This Row],[Underlying]]<>"",data[[#This Row],[Underlying]],TRUE,"-")} -> CBOE S&P 500 3-Month Volatility | Q90: =_xlfn.XLOOKUP(data[[#This Row],[ticker]],yf_desc[ticker],yf_desc[shortName],"-") -> CBOE S&P 500 3-Month Volatility | R90: =_xlfn.XLOOKUP(data[[#This Row],[ticker]],yf_desc[ticker],yf_desc[longName],"-") -> CBOE S&P 500 3-Month Volatility | S90: =_xlfn.XLOOKUP(data[[#This Row],[ticker]],yf_desc[ticker],yf_desc[longBusinessSummary],"-") -> 0 | X90: {=_xlfn._xlws.FILTER(composities[weight],composities[portfolio_name]=data[[#This Row],[factor_name]])} -> #VALUE!
A91: Vol | B91: USD | C91: ^VVIX | D91: yfinance | E91: normal | F91: {=_xlfn.SWITCH(data[[#This Row],[diffusion_type]],"lognormal",0.0001,"normal",-0.01)*IF(data[[#This Row],[asset_class]]="Vol",1,1)} -> -0.01 | I91: CBOE VIX VOLATILITY INDEX | K91: 0 | L91: 0 | M91: 0 | N91: 0 | O91: =data[[#This Row],[factor_name]] -> ^VVIX | P91: {=_xlfn.IFS(data[[#This Row],[description_override]]<>"",data[[#This Row],[description_override]],data[[#This Row],[Description_GPT]]<>"",data[[#This Row],[Description_GPT]],data[[#This Row],[Underlying]]<>"",data[[#This Row],[Underlying]],TRUE,"-")} -> CBOE VIX VOLATILITY INDEX | Q91: =_xlfn.XLOOKUP(data[[#This Row],[ticker]],yf_desc[ticker],yf_desc[shortName],"-") -> CBOE VIX VOLATILITY INDEX | R91: =_xlfn.XLOOKUP(data[[#This Row],[ticker]],yf_desc[ticker],yf_desc[longName],"-") -> ^VVIX | S91: =_xlfn.XLOOKUP(data[[#This Row],[ticker]],yf_desc[ticker],yf_desc[longBusinessSummary],"-") -> 0
A92: Vol | B92: USD | C92: ^MOVE | D92: yfinance | E92: normal | F92: {=_xlfn.SWITCH(data[[#This Row],[diffusion_type]],"lognormal",0.0001,"normal",-0.01)*IF(data[[#This Row],[asset_class]]="Vol",1,1)} -> -0.01 | I92: ICE BofAML MOVE Index | K92: 1 | L92: 0 | M92: 0 | N92: 0 | O92: =data[[#This Row],[factor_name]] -> ^MOVE | P92: {=_xlfn.IFS(data[[#This Row],[description_override]]<>"",data[[#This Row],[description_override]],data[[#This Row],[Description_GPT]]<>"",data[[#This Row],[Description_GPT]],data[[#This Row],[Underlying]]<>"",data[[#This Row],[Underlying]],TRUE,"-")} -> ICE BofAML MOVE Index | Q92: =_xlfn.XLOOKUP(data[[#This Row],[ticker]],yf_desc[ticker],yf_desc[shortName],"-") -> ICE BofAML MOVE Index | R92: =_xlfn.XLOOKUP(data[[#This Row],[ticker]],yf_desc[ticker],yf_desc[longName],"-") -> ICE BofAML MOVE Index | S92: =_xlfn.XLOOKUP(data[[#This Row],[ticker]],yf_desc[ticker],yf_desc[longBusinessSummary],"-") -> 0
A93: Vol | B93: USD | C93: ^OVX | D93: yfinance | E93: normal | F93: {=_xlfn.SWITCH(data[[#This Row],[diffusion_type]],"lognormal",0.0001,"normal",-0.01)*IF(data[[#This Row],[asset_class]]="Vol",1,1)} -> -0.01 | I93: CBOE Crude Oil Volatility Index | K93: 1 | L93: 0 | M93: 0 | N93: 0 | O93: =data[[#This Row],[factor_name]] -> ^OVX | P93: {=_xlfn.IFS(data[[#This Row],[description_override]]<>"",data[[#This Row],[description_override]],data[[#This Row],[Description_GPT]]<>"",data[[#This Row],[Description_GPT]],data[[#This Row],[Underlying]]<>"",data[[#This Row],[Underlying]],TRUE,"-")} -> CBOE Crude Oil Volatility Index | Q93: =_xlfn.XLOOKUP(data[[#This Row],[ticker]],yf_desc[ticker],yf_desc[shortName],"-") -> CBOE Crude Oil Volatility Index | R93: =_xlfn.XLOOKUP(data[[#This Row],[ticker]],yf_desc[ticker],yf_desc[longName],"-") -> ^OVX | S93: =_xlfn.XLOOKUP(data[[#This Row],[ticker]],yf_desc[ticker],yf_desc[longBusinessSummary],"-") -> 0
A94: Vol | B94: USD | C94: ^EVZ | D94: yfinance | E94: normal | F94: {=_xlfn.SWITCH(data[[#This Row],[diffusion_type]],"lognormal",0.0001,"normal",-0.01)*IF(data[[#This Row],[asset_class]]="Vol",1,1)} -> -0.01 | I94: CBOE Euro currency Volatility I | K94: 0 | L94: 0 | M94: 0 | N94: 0 | O94: =data[[#This Row],[factor_name]] -> ^EVZ | P94: {=_xlfn.IFS(data[[#This Row],[description_override]]<>"",data[[#This Row],[description_override]],data[[#This Row],[Description_GPT]]<>"",data[[#This Row],[Description_GPT]],data[[#This Row],[Underlying]]<>"",data[[#This Row],[Underlying]],TRUE,"-")} -> CBOE Euro currency Volatility I | Q94: =_xlfn.XLOOKUP(data[[#This Row],[ticker]],yf_desc[ticker],yf_desc[shortName],"-") -> ^EVZ,92169,0 | R94: =_xlfn.XLOOKUP(data[[#This Row],[ticker]],yf_desc[ticker],yf_desc[longName],"-") -> ^EVZ,92169,0 | S94: =_xlfn.XLOOKUP(data[[#This Row],[ticker]],yf_desc[ticker],yf_desc[longBusinessSummary],"-") -> 0
A95: Vol | B95: USD | C95: ^GVZ | D95: yfinance | E95: normal | F95: {=_xlfn.SWITCH(data[[#This Row],[diffusion_type]],"lognormal",0.0001,"normal",-0.01)*IF(data[[#This Row],[asset_class]]="Vol",1,1)} -> -0.01 | I95: CBOE Gold Volatility Index | K95: 1 | L95: 0 | M95: 0 | N95: 0 | O95: =data[[#This Row],[factor_name]] -> ^GVZ | P95: {=_xlfn.IFS(data[[#This Row],[description_override]]<>"",data[[#This Row],[description_override]],data[[#This Row],[Description_GPT]]<>"",data[[#This Row],[Description_GPT]],data[[#This Row],[Underlying]]<>"",data[[#This Row],[Underlying]],TRUE,"-")} -> CBOE Gold Volatility Index | Q95: =_xlfn.XLOOKUP(data[[#This Row],[ticker]],yf_desc[ticker],yf_desc[shortName],"-") -> CBOE Gold Volatility Index | R95: =_xlfn.XLOOKUP(data[[#This Row],[ticker]],yf_desc[ticker],yf_desc[longName],"-") -> ^GVZ | S95: =_xlfn.XLOOKUP(data[[#This Row],[ticker]],yf_desc[ticker],yf_desc[longBusinessSummary],"-") -> 0
A96: Vol | B96: USD | C96: ^COR3M | D96: yfinance | E96: normal | F96: {=_xlfn.SWITCH(data[[#This Row],[diffusion_type]],"lognormal",0.0001,"normal",-0.01)*IF(data[[#This Row],[asset_class]]="Vol",1,1)} -> -0.01 | I96: Cboe Implied Correlation Index | K96: 0 | L96: 0 | M96: 0 | N96: 0 | O96: =data[[#This Row],[factor_name]] -> ^COR3M | P96: {=_xlfn.IFS(data[[#This Row],[description_override]]<>"",data[[#This Row],[description_override]],data[[#This Row],[Description_GPT]]<>"",data[[#This Row],[Description_GPT]],data[[#This Row],[Underlying]]<>"",data[[#This Row],[Underlying]],TRUE,"-")} -> Cboe Implied Correlation Index | Q96: =_xlfn.XLOOKUP(data[[#This Row],[ticker]],yf_desc[ticker],yf_desc[shortName],"-") -> Cboe Implied Correlation Index | R96: =_xlfn.XLOOKUP(data[[#This Row],[ticker]],yf_desc[ticker],yf_desc[longName],"-") -> Cboe Implied Correlation Index | S96: =_xlfn.XLOOKUP(data[[#This Row],[ticker]],yf_desc[ticker],yf_desc[longBusinessSummary],"-") -> 0
A97: Portfolio | B97: USD | C97: MWTIX | D97: yfinance | E97: lognormal | F97: {=_xlfn.SWITCH(data[[#This Row],[diffusion_type]],"lognormal",0.0001,"normal",-0.01)*IF(data[[#This Row],[asset_class]]="Vol",1,1)} -> 0.0001 | J97: TCW MetWest Total Return Bd I | K97: 1 | L97: 1 | M97: 0 | N97: 0 | O97: =data[[#This Row],[factor_name]] -> MWTIX | P97: {=_xlfn.IFS(data[[#This Row],[description_override]]<>"",data[[#This Row],[description_override]],data[[#This Row],[Description_GPT]]<>"",data[[#This Row],[Description_GPT]],data[[#This Row],[Underlying]]<>"",data[[#This Row],[Underlying]],TRUE,"-")} -> TCW MetWest Total Return Bd I | Q97: =_xlfn.XLOOKUP(data[[#This Row],[ticker]],yf_desc[ticker],yf_desc[shortName],"-") -> - | R97: =_xlfn.XLOOKUP(data[[#This Row],[ticker]],yf_desc[ticker],yf_desc[longName],"-") -> - | S97: =_xlfn.XLOOKUP(data[[#This Row],[ticker]],yf_desc[ticker],yf_desc[longBusinessSummary],"-") -> -
A98: Portfolio | B98: USD | C98: FCNTX | D98: yfinance | E98: lognormal | F98: {=_xlfn.SWITCH(data[[#This Row],[diffusion_type]],"lognormal",0.0001,"normal",-0.01)*IF(data[[#This Row],[asset_class]]="Vol",1,1)} -> 0.0001 | J98: Fidelity Contrafund | K98: 1 | L98: 0 | M98: 0 | N98: 0 | O98: =data[[#This Row],[factor_name]] -> FCNTX | P98: {=_xlfn.IFS(data[[#This Row],[description_override]]<>"",data[[#This Row],[description_override]],data[[#This Row],[Description_GPT]]<>"",data[[#This Row],[Description_GPT]],data[[#This Row],[Underlying]]<>"",data[[#This Row],[Underlying]],TRUE,"-")} -> Fidelity Contrafund | Q98: =_xlfn.XLOOKUP(data[[#This Row],[ticker]],yf_desc[ticker],yf_desc[shortName],"-") -> - | R98: =_xlfn.XLOOKUP(data[[#This Row],[ticker]],yf_desc[ticker],yf_desc[longName],"-") -> - | S98: =_xlfn.XLOOKUP(data[[#This Row],[ticker]],yf_desc[ticker],yf_desc[longBusinessSummary],"-") -> -
A99: Theme | B99: USD | C99: PRIVATES | D99: composite | E99: lognormal | F99: {=_xlfn.SWITCH(data[[#This Row],[diffusion_type]],"lognormal",0.0001,"normal",-0.01)*IF(data[[#This Row],[asset_class]]="Vol",1,1)} -> 0.0001 | J99: {=_xlfn.XLOOKUP(data[[#This Row],[factor_name]],_xlfn.ANCHORARRAY(composites!$I$2),_xlfn.ANCHORARRAY(composites!$J$2))} -> PSP 0.5, XLF -0.5, BKLN 0.5, LQDH -0.5 | K99: 1 | L99: 1 | M99: 1 | N99: 0 | O99: =data[[#This Row],[factor_name]] -> PRIVATES | P99: {=_xlfn.IFS(data[[#This Row],[description_override]]<>"",data[[#This Row],[description_override]],data[[#This Row],[Description_GPT]]<>"",data[[#This Row],[Description_GPT]],data[[#This Row],[Underlying]]<>"",data[[#This Row],[Underlying]],TRUE,"-")} -> PSP 0.5, XLF -0.5, BKLN 0.5, LQDH -0.5 | Q99: =_xlfn.XLOOKUP(data[[#This Row],[ticker]],yf_desc[ticker],yf_desc[shortName],"-") -> - | R99: =_xlfn.XLOOKUP(data[[#This Row],[ticker]],yf_desc[ticker],yf_desc[longName],"-") -> - | S99: =_xlfn.XLOOKUP(data[[#This Row],[ticker]],yf_desc[ticker],yf_desc[longBusinessSummary],"-") -> -
A100: Theme | B100: USD | C100: FED | D100: composite | E100: lognormal | F100: {=_xlfn.SWITCH(data[[#This Row],[diffusion_type]],"lognormal",0.0001,"normal",-0.01)*IF(data[[#This Row],[asset_class]]="Vol",1,1)} -> 0.0001 | J100: {=_xlfn.XLOOKUP(data[[#This Row],[factor_name]],_xlfn.ANCHORARRAY(composites!$I$2),_xlfn.ANCHORARRAY(composites!$J$2))} -> SHY 1, BSV 1 | K100: 1 | L100: 1 | M100: 1 | N100: 0 | O100: =data[[#This Row],[factor_name]] -> FED | P100: {=_xlfn.IFS(data[[#This Row],[description_override]]<>"",data[[#This Row],[description_override]],data[[#This Row],[Description_GPT]]<>"",data[[#This Row],[Description_GPT]],data[[#This Row],[Underlying]]<>"",data[[#This Row],[Underlying]],TRUE,"-")} -> SHY 1, BSV 1 | Q100: =_xlfn.XLOOKUP(data[[#This Row],[ticker]],yf_desc[ticker],yf_desc[shortName],"-") -> - | R100: =_xlfn.XLOOKUP(data[[#This Row],[ticker]],yf_desc[ticker],yf_desc[longName],"-") -> - | S100: =_xlfn.XLOOKUP(data[[#This Row],[ticker]],yf_desc[ticker],yf_desc[longBusinessSummary],"-") -> -
...

Sheet read_new
A1: factor_name | B1: asset_class | C1: region | D1: source | E1: ticker | F1: diffusion_type | G1: na_lag_tolerance | H1: na_method
A2: SPX | B2: Equities | C2: USD | D2: yfinance | E2: SPY | F2: lognormal | G2: lag, 5 | H2: 0
A3: RUT | B3: Equities | C3: USD | D3: yfinance | E3: IWM | F3: lognormal | G3: lag, 5 | H3: spx, beta=1
A4: CAC | B4: Equities | C4: EUR | D4: yfinance | E4: ^FCHI | F4: lognormal | G4: lag, 5 | H4: 0
A5: USD10 | B5: Rates | C5: USD | D5: yfinance | E5: ^TNX | F5: normal | G5: lag, 5 | H5: 0
A6: TY | B6: Rates | C6: USD | D6: yfinance | E6: IEF | F6: lognormal | G6: lag, 1 | H6: allna

Sheet read_tcw
A1: factor_name | B1: asset_class | C1: region | D1: hyper_factor | E1: composite | F1: description | G1: source | H1: ticker | I1: diffusion_type | J1: multiplier
A2: {=_xlfn._xlws.FILTER(data[factor_name],data[Active])} -> SPY | B2: {=INDEX(data[],_xlfn.XMATCH(_xlfn.ANCHORARRAY(A2),data[factor_name]),_xlfn.XMATCH(B1:J1,data[#Headers]))} -> Equities | C2: USD | D2: 1 | E2: 0 | F2: S&P 500 | G2: yfinance | H2: SPY | I2: lognormal | J2: 0.0001
A3: IWM | B3: Equities | C3: USD | D3: 0 | E3: 0 | F3: Russell 2000 | G3: yfinance | H3: IWM | I3: lognormal | J3: 0.0001
A4: MDY | B4: Equities | C4: USD | D4: 0 | E4: 0 | F4: S&P 400 | G4: yfinance | H4: MDY | I4: lognormal | J4: 0.0001
A5: RSP | B5: Equities | C5: USD | D5: 0 | E5: 0 | F5: S&P 500 EW | G5: yfinance | H5: RSP | I5: lognormal | J5: 0.0001
A6: QQQ | B6: Equities | C6: USD | D6: 0 | E6: 0 | F6: Nasdaq 100 | G6: yfinance | H6: QQQ | I6: lognormal | J6: 0.0001
A7: DIA | B7: Equities | C7: USD | D7: 0 | E7: 0 | F7: Dow Jones 30 | G7: yfinance | H7: DIA | I7: lognormal | J7: 0.0001
A8: XLK | B8: Sector | C8: USD | D8: 0 | E8: 0 | F8: Technology | G8: yfinance | H8: XLK | I8: lognormal | J8: 0.0001
A9: XLI | B9: Sector | C9: USD | D9: 0 | E9: 0 | F9: Industrials | G9: yfinance | H9: XLI | I9: lognormal | J9: 0.0001
A10: XLF | B10: Sector | C10: USD | D10: 0 | E10: 0 | F10: Financials | G10: yfinance | H10: XLF | I10: lognormal | J10: 0.0001
A11: KRE | B11: Sector | C11: USD | D11: 0 | E11: 0 | F11: Regional Banks | G11: yfinance | H11: KRE | I11: lognormal | J11: 0.0001
A12: XLC | B12: Sector | C12: USD | D12: 0 | E12: 0 | F12: Communications | G12: yfinance | H12: XLC | I12: lognormal | J12: 0.0001
A13: XLE | B13: Sector | C13: USD | D13: 0 | E13: 0 | F13: Energy | G13: yfinance | H13: XLE | I13: lognormal | J13: 0.0001
A14: XLY | B14: Sector | C14: USD | D14: 0 | E14: 0 | F14: Discretionary | G14: yfinance | H14: XLY | I14: lognormal | J14: 0.0001
... A85: BTC_vol | B85: Vol | C85: USD | D85: 0 | E85: 0 | F85: - | G85: lmxl | H85: BTC1_atm | I85: normal | J85: -0.01

Sheet read_nocomposite
A1: factor_name | B1: asset_class | C1: region | D1: hyper_factor | E1: composite | F1: description | G1: source | H1: ticker | I1: diffusion_type | J1: multiplier
A2: {=_xlfn._xlws.FILTER(data[factor_name],(data[Active])*(data[source]="yfinance"))} -> SPY | B2: {=INDEX(data[],_xlfn.XMATCH(_xlfn.ANCHORARRAY(A2),data[factor_name]),_xlfn.XMATCH(B1:J1,data[#Headers]))} -> Equities | C2: USD | D2: 1 | E2: 0 | F2: S&P 500 | G2: yfinance | H2: SPY | I2: lognormal | J2: 0.0001
A3: IWM | B3: Equities | C3: USD | D3: 0 | E3: 0 | F3: Russell 2000 | G3: yfinance | H3: IWM | I3: lognormal | J3: 0.0001
A4: MDY | B4: Equities | C4: USD | D4: 0 | E4: 0 | F4: S&P 400 | G4: yfinance | H4: MDY | I4: lognormal | J4: 0.0001
A5: RSP | B5: Equities | C5: USD | D5: 0 | E5: 0 | F5: S&P 500 EW | G5: yfinance | H5: RSP | I5: lognormal | J5: 0.0001
A6: QQQ | B6: Equities | C6: USD | D6: 0 | E6: 0 | F6: Nasdaq 100 | G6: yfinance | H6: QQQ | I6: lognormal | J6: 0.0001
A7: DIA | B7: Equities | C7: USD | D7: 0 | E7: 0 | F7: Dow Jones 30 | G7: yfinance | H7: DIA | I7: lognormal | J7: 0.0001
A8: XLK | B8: Sector | C8: USD | D8: 0 | E8: 0 | F8: Technology | G8: yfinance | H8: XLK | I8: lognormal | J8: 0.0001
A9: XLI | B9: Sector | C9: USD | D9: 0 | E9: 0 | F9: Industrials | G9: yfinance | H9: XLI | I9: lognormal | J9: 0.0001
A10: XLF | B10: Sector | C10: USD | D10: 0 | E10: 0 | F10: Financials | G10: yfinance | H10: XLF | I10: lognormal | J10: 0.0001
A11: KRE | B11: Sector | C11: USD | D11: 0 | E11: 0 | F11: Regional Banks | G11: yfinance | H11: KRE | I11: lognormal | J11: 0.0001
A12: XLC | B12: Sector | C12: USD | D12: 0 | E12: 0 | F12: Communications | G12: yfinance | H12: XLC | I12: lognormal | J12: 0.0001
A13: XLE | B13: Sector | C13: USD | D13: 0 | E13: 0 | F13: Energy | G13: yfinance | H13: XLE | I13: lognormal | J13: 0.0001
A14: XLY | B14: Sector | C14: USD | D14: 0 | E14: 0 | F14: Discretionary | G14: yfinance | H14: XLY | I14: lognormal | J14: 0.0001
... A74: FCNTX | B74: Portfolio | C74: USD | D74: 0 | E74: 0 | F74: Fidelity Contrafund | G74: yfinance | H74: FCNTX | I74: lognormal | J74: 0.0001

Sheet read
A1: factor_name | B1: asset_class | C1: region | D1: hyper_factor | E1: composite | F1: description | G1: source | H1: ticker | I1: diffusion_type | J1: multiplier
A2: {=_xlfn._xlws.FILTER(data[factor_name],data[Active]*(data[client]=0))} -> SPY | B2: {=INDEX(data[],_xlfn.XMATCH(_xlfn.ANCHORARRAY(A2),data[factor_name]),_xlfn.XMATCH(B1:J1,data[#Headers]))} -> Equities | C2: USD | D2: 1 | E2: 0 | F2: S&P 500 | G2: yfinance | H2: SPY | I2: lognormal | J2: 0.0001
A3: IWM | B3: Equities | C3: USD | D3: 0 | E3: 0 | F3: Russell 2000 | G3: yfinance | H3: IWM | I3: lognormal | J3: 0.0001
A4: MDY | B4: Equities | C4: USD | D4: 0 | E4: 0 | F4: S&P 400 | G4: yfinance | H4: MDY | I4: lognormal | J4: 0.0001
A5: RSP | B5: Equities | C5: USD | D5: 0 | E5: 0 | F5: S&P 500 EW | G5: yfinance | H5: RSP | I5: lognormal | J5: 0.0001
A6: QQQ | B6: Equities | C6: USD | D6: 0 | E6: 0 | F6: Nasdaq 100 | G6: yfinance | H6: QQQ | I6: lognormal | J6: 0.0001
A7: DIA | B7: Equities | C7: USD | D7: 0 | E7: 0 | F7: Dow Jones 30 | G7: yfinance | H7: DIA | I7: lognormal | J7: 0.0001
A8: XLK | B8: Sector | C8: USD | D8: 0 | E8: 0 | F8: Technology | G8: yfinance | H8: XLK | I8: lognormal | J8: 0.0001
A9: XLI | B9: Sector | C9: USD | D9: 0 | E9: 0 | F9: Industrials | G9: yfinance | H9: XLI | I9: lognormal | J9: 0.0001
A10: XLF | B10: Sector | C10: USD | D10: 0 | E10: 0 | F10: Financials | G10: yfinance | H10: XLF | I10: lognormal | J10: 0.0001
A11: KRE | B11: Sector | C11: USD | D11: 0 | E11: 0 | F11: Regional Banks | G11: yfinance | H11: KRE | I11: lognormal | J11: 0.0001
A12: XLC | B12: Sector | C12: USD | D12: 0 | E12: 0 | F12: Communications | G12: yfinance | H12: XLC | I12: lognormal | J12: 0.0001
A13: XLE | B13: Sector | C13: USD | D13: 0 | E13: 0 | F13: Energy | G13: yfinance | H13: XLE | I13: lognormal | J13: 0.0001
A14: XLY | B14: Sector | C14: USD | D14: 0 | E14: 0 | F14: Discretionary | G14: yfinance | H14: XLY | I14: lognormal | J14: 0.0001
... A85: BTC_vol | B85: Vol | C85: USD | D85: 0 | E85: 0 | F85: - | G85: lmxl | H85: BTC1_atm | I85: normal | J85: -0.01

Sheet read_short
A1: =read!A1 -> factor_name | B1: {=_xlfn.DROP(_xlfn.TRIMRANGE(read!1:1),,1)} -> asset_class | C1: region | D1: hyper_factor | E1: composite | F1: description | G1: source | H1: ticker | I1: diffusion_type | J1: multiplier
A2: {=_xlfn.CHOOSEROWS(_xlfn.ANCHORARRAY(read!A2),_xlfn.SEQUENCE(5))} -> SPY | B2: {=INDEX(data[],_xlfn.XMATCH(_xlfn.ANCHORARRAY(A2),data[factor_name]),_xlfn.XMATCH(_xlfn.ANCHORARRAY(B1),data[#Headers]))} -> Equities | C2: USD | D2: 1 | E2: 0 | F2: S&P 500 | G2: yfinance | H2: SPY | I2: lognormal | J2: 0.0001
A3: IWM | B3: Equities | C3: USD | D3: 0 | E3: 0 | F3: Russell 2000 | G3: yfinance | H3: IWM | I3: lognormal | J3: 0.0001
A4: MDY | B4: Equities | C4: USD | D4: 0 | E4: 0 | F4: S&P 400 | G4: yfinance | H4: MDY | I4: lognormal | J4: 0.0001
A5: RSP | B5: Equities | C5: USD | D5: 0 | E5: 0 | F5: S&P 500 EW | G5: yfinance | H5: RSP | I5: lognormal | J5: 0.0001
A6: QQQ | B6: Equities | C6: USD | D6: 0 | E6: 0 | F6: Nasdaq 100 | G6: yfinance | H6: QQQ | I6: lognormal | J6: 0.0001

Sheet read_old2
A1: factor_name | B1: asset_class | C1: region | D1: hyper_factor | E1: description
A2: {=_xlfn._xlws.FILTER(data[factor_name],data[Active]*NOT(data[composite]))} -> SPY | B2: {=INDEX(data[],_xlfn.XMATCH(_xlfn.ANCHORARRAY(A2),data[factor_name]),_xlfn.XMATCH(B1:E1,data[#Headers]))} -> Equities | C2: USD | D2: 1 | E2: S&P 500
A3: IWM | B3: Equities | C3: USD | D3: 0 | E3: Russell 2000
A4: MDY | B4: Equities | C4: USD | D4: 0 | E4: S&P 400
A5: RSP | B5: Equities | C5: USD | D5: 0 | E5: S&P 500 EW
A6: QQQ | B6: Equities | C6: USD | D6: 0 | E6: Nasdaq 100
A7: DIA | B7: Equities | C7: USD | D7: 0 | E7: Dow Jones 30
A8: XLK | B8: Sector | C8: USD | D8: 0 | E8: Technology
A9: XLI | B9: Sector | C9: USD | D9: 0 | E9: Industrials
A10: XLF | B10: Sector | C10: USD | D10: 0 | E10: Financials
A11: KRE | B11: Sector | C11: USD | D11: 0 | E11: Regional Banks
A12: XLC | B12: Sector | C12: USD | D12: 0 | E12: Communications
A13: XLE | B13: Sector | C13: USD | D13: 0 | E13: Energy
A14: XLY | B14: Sector | C14: USD | D14: 0 | E14: Discretionary
... A76: BTC_vol | B76: Vol | C76: USD | D76: 0 | E76: -

Sheet Sheet1
A1: ETF | B1: Description | C1: Underlying Index
A2: SPY | B2: SPDR S&P 500 ETF Trust; tracks the performance of the S&P 500 Index. | C2: S&P 500 Index
A3: IWM | B3: iShares Russell 2000 ETF; provides exposure to small-cap U.S. stocks. | C3: Russell 2000 Index
A4: QQQ | B4: Invesco QQQ Trust; focuses on large-cap growth stocks in the Nasdaq-100 Index. | C4: Nasdaq-100 Index
A5: FEZ | B5: SPDR EURO STOXX 50 ETF Trust; represents 50 of the largest companies in the Eurozone. | C5: EURO STOXX 50 Index
A6: LQD | B6: iShares iBoxx $ Investment Grade Corporate Bond ETF; invests in U.S. dollar-denominated, investment-grade corporate bonds. | C6: Markit iBoxx USD Liquid Investment Grade Index
A7: HYG | B7: iShares iBoxx $ High Yield Corporate Bond ETF; targets U.S. dollar-denominated high yield corporate bonds. | C7: Markit iBoxx USD Liquid High Yield Index
A8: MBTA | B8: Invesco Municipal Bond ETF; invests in a diversified portfolio of municipal bonds. | C8: S&P National AMT-Free Municipal Bond Index
A9: AGNC | B9: AGNC Investment Corp.; focuses on income-generating investments in mortgage-backed securities. | C9: Not an ETF but typically referenced alongside fixed-income investments.

Sheet read_old
A1: factor_name | B1: etf | C1: description | D1: active
A2: SPX | B2: SPY | D2: 1
A3: RTY | B3: IWM | D3: 1
A4: NDX | B4: QQQ | D4: 1
A5: SX5E | B5: FEZ | D5: 1
A6: IG | B6: LQD | D6: 1
A7: HY | B7: HYG | D7: 1
A8: MBS_short | B8: MBTA | D8: 0
A9: MBS | B9: AGNC | D9: 0

Sheet data_old
A1: asset_class | B1: region | C1: factor_name | D1: factor_name_new | E1: description_override | F1: Description_GPT | G1: Underlying | H1: Active | I1: description
A2: Equities | B2: USD | C2: SPY | D2: SPX | E2: S&P 500 | F2: SPDR S&P 500 ETF Trust | G2: S&P 500 Index | H2: 1 | I2: =IF(data_old[[#This Row],[description_override]]="",data_old[[#This Row],[Description_GPT]],data_old[[#This Row],[description_override]]) -> S&P 500 | L2: tip | M2: {=_xlfn.XMATCH(_xlfn._TRO_ALL(L:L),gpt!C2:C61)} -> 40
A3: Equities | B3: USD | C3: IWM | D3: RTY | E3: Russell 2000 | F3: iShares Russell 2000 ETF | G3: Russell 2000 Index | H3: 1 | I3: =IF(data_old[[#This Row],[description_override]]="",data_old[[#This Row],[Description_GPT]],data_old[[#This Row],[description_override]]) -> Russell 2000 | L3: vtip | M3: 41
A4: Equities | B4: USD | C4: QQQ | D4: NDX | E4: Nasdaq 100 | F4: Invesco QQQ Trust | G4: Nasdaq-100 Index | H4: 1 | I4: =IF(data_old[[#This Row],[description_override]]="",data_old[[#This Row],[Description_GPT]],data_old[[#This Row],[description_override]]) -> Nasdaq 100 | L4: cmbs | M4: 50
A5: Equities | B5: USD | C5: DIA | D5: DOW | E5: Dow Jones 30 | F5: SPDR Dow Jones Industrial Average ETF Trust | G5: Dow Jones Industrial Average | H5: 1 | I5: =IF(data_old[[#This Row],[description_override]]="",data_old[[#This Row],[Description_GPT]],data_old[[#This Row],[description_override]]) -> Dow Jones 30 | L5: vmbs | M5: 49
A6: Equities | B6: EUR | C6: FEZ | D6: SX5E | E6: Eurostoxx 50 | F6: SPDR EURO STOXX 50 ETF | G6: EURO STOXX 50 Index | H6: 1 | I6: =IF(data_old[[#This Row],[description_override]]="",data_old[[#This Row],[Description_GPT]],data_old[[#This Row],[description_override]]) -> Eurostoxx 50 | L6: gld | M6: 57
A7: Equities | B7: EUR | C7: SX7E | D7: SX7E | E7: Eurostoxx Banks | H7: 0 | I7: =IF(data_old[[#This Row],[description_override]]="",data_old[[#This Row],[Description_GPT]],data_old[[#This Row],[description_override]]) -> Eurostoxx Banks | L7: lqd | M7: 35
A8: Equities | B8: GBP | C8: EWU | F8: iShares FTSE United Kingdom ETF | G8: FTSE 100 Index for the UK | H8: 1 | I8: =IF(data_old[[#This Row],[description_override]]="",data_old[[#This Row],[Description_GPT]],data_old[[#This Row],[description_override]]) -> iShares FTSE United Kingdom ETF | L8: lqdh | M8: 36
A9: Equities | B9: EUR | C9: DAX | D9: DAX | E9: DAX (Germany) | F9: Xtrackers DAX Equity ETF | G9: DAX Index for Germany | H9: 1 | I9: =IF(data_old[[#This Row],[description_override]]="",data_old[[#This Row],[Description_GPT]],data_old[[#This Row],[description_override]]) -> DAX (Germany) | L9: hyg | M9: 37
A10: Equities | B10: CAD | C10: EWC | F10: iShares MSCI Canada ETF | G10: Canadian equities | H10: 1 | I10: =IF(data_old[[#This Row],[description_override]]="",data_old[[#This Row],[Description_GPT]],data_old[[#This Row],[description_override]]) -> iShares MSCI Canada ETF | L10: hygh | M10: 38
A11: Equities | B11: EUR | C11: FTSEMIB.MI | D11: BTP | E11: FTSE MIB (Italy) | H11: 0 | I11: =IF(data_old[[#This Row],[description_override]]="",data_old[[#This Row],[Description_GPT]],data_old[[#This Row],[description_override]]) -> FTSE MIB (Italy) | L11: Emhy | M11: 39
A12: Equities | B12: EUR | C12: CAC | D12: CAC | E12: CAC 40 (France) | F12: Lyxor CAC 40 ETF | G12: CAC 40 Index for France | H12: 1 | I12: =IF(data_old[[#This Row],[description_override]]="",data_old[[#This Row],[Description_GPT]],data_old[[#This Row],[description_override]]) -> CAC 40 (France) | L12: mdy | M12: 5
A13: Equities | B13: EUR | C13: EWI | F13: iShares MSCI Italy ETF | G13: Italian equities | H13: 1 | I13: =IF(data_old[[#This Row],[description_override]]="",data_old[[#This Row],[Description_GPT]],data_old[[#This Row],[description_override]]) -> iShares MSCI Italy ETF | L13: vnq | M13: 6
A14: Equities | B14: EUR | C14: ^IBEX | D14: IBEX | E14: IBEX 35 (Spain) | F14: iShares MSCI Spain ETF | G14: Spanish equities | H14: 0 | I14: =IF(data_old[[#This Row],[description_override]]="",data_old[[#This Row],[Description_GPT]],data_old[[#This Row],[description_override]]) -> IBEX 35 (Spain) | L14: pff | M14: 7
A15: Equities | B15: EUR | C15: EWP | F15: iShares MSCI Spain ETF | G15: Spanish equities | H15: 0 | I15: =IF(data_old[[#This Row],[description_override]]="",data_old[[#This Row],[Description_GPT]],data_old[[#This Row],[description_override]]) -> iShares MSCI Spain ETF | L15: ashr | M15: 32
A16: Equities | B16: JPY | C16: ^N225 | D16: NKY | E16: Nikkei 225 | F16: Nikkei 225 ETF | G16: Nikkei 225 Index for Japan | H16: 1 | I16: =IF(data_old[[#This Row],[description_override]]="",data_old[[#This Row],[Description_GPT]],data_old[[#This Row],[description_override]]) -> Nikkei 225 | L16: kweb | M16: 33
A17: Equities | B17: JPY | C17: TPX | D17: TPX | E17: TOPIX | F17: iShares TOPIX ETF | G17: Tokyo Stock Price Index (TOPIX) | H17: 1 | I17: =IF(data_old[[#This Row],[description_override]]="",data_old[[#This Row],[Description_GPT]],data_old[[#This Row],[description_override]]) -> TOPIX | L17: fxi | M17: 31
A18: Equities | B18: CNH | C18: FXI | D18: FXI | F18: iShares China Large-Cap ETF | G18: Large-cap Chinese stocks | H18: 1 | I18: =IF(data_old[[#This Row],[description_override]]="",data_old[[#This Row],[Description_GPT]],data_old[[#This Row],[description_override]]) -> iShares China Large-Cap ETF | L18: aiq | M18: 34
A19: Equities | B19: CNH | C19: ASHR | D19: ASHR | F19: Xtrackers Harvest CSI 300 China A-Shares ETF | G19: A-shares of the 300 largest companies in China | H19: 1 | I19: =IF(data_old[[#This Row],[description_override]]="",data_old[[#This Row],[Description_GPT]],data_old[[#This Row],[description_override]]) -> Xtrackers Harvest CSI 300 China A-Shares ETF | L19: SPY | M19: 1
A20: Credit | B20: USD | C20: LQD | D20: IG | F20: iShares iBoxx $ Investment Grade Corporate Bond ETF | G20: Investment-grade corporate bonds | H20: 1 | I20: =IF(data_old[[#This Row],[description_override]]="",data_old[[#This Row],[Description_GPT]],data_old[[#This Row],[description_override]]) -> iShares iBoxx $ Investment Grade Corporate Bond ETF | L20: IWM | M20: 2
A21: Credit | B21: USD | C21: HYG | D21: HY | F21: iShares iBoxx $ High Yield Corporate Bond ETF | G21: High-yield corporate bonds | H21: 1 | I21: =IF(data_old[[#This Row],[description_override]]="",data_old[[#This Row],[Description_GPT]],data_old[[#This Row],[description_override]]) -> iShares iBoxx $ High Yield Corporate Bond ETF | L21: QQQ | M21: 3
A22: Credit | B22: USD | C22: LQDH | I22: =IF(data_old[[#This Row],[description_override]]="",data_old[[#This Row],[Description_GPT]],data_old[[#This Row],[description_override]]) -> 0 | L22: DIA | M22: 4
A23: Credit | B23: USD | C23: HYGH | I23: =IF(data_old[[#This Row],[description_override]]="",data_old[[#This Row],[Description_GPT]],data_old[[#This Row],[description_override]]) -> 0 | L23: FEZ | M23: 20
A24: Rates | B24: USD | C24: SHY | D24: USD02 | F24: iShares 1-3 Year Treasury Bond ETF | G24: Short-term U.S. Treasury bonds (1-3 years) | H24: 1 | I24: =IF(data_old[[#This Row],[description_override]]="",data_old[[#This Row],[Description_GPT]],data_old[[#This Row],[description_override]]) -> iShares 1-3 Year Treasury Bond ETF | L24: SX7E | M24: 21
A25: Rates | B25: USD | C25: IEI | D25: USD05 | F25: iShares 3-7 Year Treasury Bond ETF | G25: Intermediate-term U.S. Treasury bonds (3-7 years) | H25: 1 | I25: =IF(data_old[[#This Row],[description_override]]="",data_old[[#This Row],[Description_GPT]],data_old[[#This Row],[description_override]]) -> iShares 3-7 Year Treasury Bond ETF | L25: EWU | M25: 22
A26: Rates | B26: USD | C26: IEF | D26: USD10 | F26: iShares 7-10 Year Treasury Bond ETF | G26: Intermediate-term U.S. Treasury bonds (7-10 years) | H26: 1 | I26: =IF(data_old[[#This Row],[description_override]]="",data_old[[#This Row],[Description_GPT]],data_old[[#This Row],[description_override]]) -> iShares 7-10 Year Treasury Bond ETF | L26: DAX | M26: 23
A27: Rates | B27: USD | C27: TLT | D27: USD30 | F27: iShares 20+ Year Treasury Bond ETF | G27: Long-term U.S. Treasury bonds (20+ years) | H27: 1 | I27: =IF(data_old[[#This Row],[description_override]]="",data_old[[#This Row],[Description_GPT]],data_old[[#This Row],[description_override]]) -> iShares 20+ Year Treasury Bond ETF | L27: EWC | M27: #N/A
A28: Rates | B28: USD | C28: TIP | D28: TIPS | F28: iShares TIPS Bond ETF | G28: U.S. Treasury Inflation-Protected Securities (TIPS) | H28: 1 | I28: =IF(data_old[[#This Row],[description_override]]="",data_old[[#This Row],[Description_GPT]],data_old[[#This Row],[description_override]]) -> iShares TIPS Bond ETF | L28: FTSEMIB.MI | M28: 24
A29: Rates | B29: USD | C29: VTIP | L29: CAC | M29: 25
A30: Rates | B30: USD | C30: MBB | F30: iShares MBS ETF | G30: U.S. mortgage-backed securities | H30: 0 | I30: =IF(data_old[[#This Row],[description_override]]="",data_old[[#This Row],[Description_GPT]],data_old[[#This Row],[description_override]]) -> iShares MBS ETF | L30: EWI | M30: 26
A31: Rates | B31: USD | C31: MBTA | F31: Simplify Mortgage Backed Securities ETF | G31: U.S. mortgage-backed securities (short duration) | H31: 0 | I31: =IF(data_old[[#This Row],[description_override]]="",data_old[[#This Row],[Description_GPT]],data_old[[#This Row],[description_override]]) -> Simplify Mortgage Backed Securities ETF | L31: ^IBEX | M31: 27
A32: Rates | B32: USD | C32: AGNC | F32: AGNC Investment Corp. | G32: Agency mortgage-backed securities | H32: 1 | I32: =IF(data_old[[#This Row],[description_override]]="",data_old[[#This Row],[Description_GPT]],data_old[[#This Row],[description_override]]) -> AGNC Investment Corp. | L32: EWP | M32: 28
A33: Rates | B33: USD | C33: VMBS | I33: =IF(data_old[[#This Row],[description_override]]="",data_old[[#This Row],[Description_GPT]],data_old[[#This Row],[description_override]]) -> 0 | L33: ^N225 | M33: 29
A34: Rates | B34: USD | C34: CMBS | D34: CMBS | I34: =IF(data_old[[#This Row],[description_override]]="",data_old[[#This Row],[Description_GPT]],data_old[[#This Row],[description_override]]) -> 0 | L34: TPX | M34: 30
A35: Rates | B35: EM | C35: EMB | F35: iShares J.P. Morgan USD Emerging Markets Bond ETF | G35: U.S. dollar-denominated bonds issued by emerging market governments | H35: 1 | I35: =IF(data_old[[#This Row],[description_override]]="",data_old[[#This Row],[Description_GPT]],data_old[[#This Row],[description_override]]) -> iShares J.P. Morgan USD Emerging Markets Bond ETF | L35: FXI | M35: 31
A36: Rates | B36: EM | C36: EMHY | I36: =IF(data_old[[#This Row],[description_override]]="",data_old[[#This Row],[Description_GPT]],data_old[[#This Row],[description_override]]) -> 0 | L36: ASHR | M36: 32
A37: Rates | B37: EM | C37: CEW | F37: WisdomTree Emerging Markets Local Debt Fund | G37: Local currency emerging market debt | H37: 0 | I37: =IF(data_old[[#This Row],[description_override]]="",data_old[[#This Row],[Description_GPT]],data_old[[#This Row],[description_override]]) -> WisdomTree Emerging Markets Local Debt Fund | L37: LQD | M37: 35
A38: Rates | B38: EM | C38: IGOV | F38: iShares International Government Bonds ETF | G38: Government bonds in developed markets | H38: 0 | I38: =IF(data_old[[#This Row],[description_override]]="",data_old[[#This Row],[Description_GPT]],data_old[[#This Row],[description_override]]) -> iShares International Government Bonds ETF | L38: HYG | M38: 37
A39: Commodities | B39: USD | C39: GLD | F39: SPDR Gold Shares | G39: Price of gold | H39: 1 | I39: =IF(data_old[[#This Row],[description_override]]="",data_old[[#This Row],[Description_GPT]],data_old[[#This Row],[description_override]]) -> SPDR Gold Shares | L39: LQDH | M39: 36
A40: Commodities | B40: USD | C40: SLV | F40: iShares Silver Trust | G40: Price of silver | H40: 1 | I40: =IF(data_old[[#This Row],[description_override]]="",data_old[[#This Row],[Description_GPT]],data_old[[#This Row],[description_override]]) -> iShares Silver Trust | L40: HYGH | M40: 38
A41: Commodities | B41: USD | C41: USO | F41: United States Oil Fund | G41: Price of West Texas Intermediate crude oil | H41: 1 | I41: =IF(data_old[[#This Row],[description_override]]="",data_old[[#This Row],[Description_GPT]],data_old[[#This Row],[description_override]]) -> United States Oil Fund | L41: SHY | M41: 42
A42: Commodities | B42: USD | C42: DBC | F42: Invesco DB Commodity Index Tracking Fund | G42: Broad commodity index | H42: 1 | I42: =IF(data_old[[#This Row],[description_override]]="",data_old[[#This Row],[Description_GPT]],data_old[[#This Row],[description_override]]) -> Invesco DB Commodity Index Tracking Fund | L42: IEI | M42: 43
A43: Currencies | B43: USD | C43: UUP | F43: Invesco DB US Dollar Index Bullish Fund | G43: U.S. Dollar Index | H43: 1 | I43: =IF(data_old[[#This Row],[description_override]]="",data_old[[#This Row],[Description_GPT]],data_old[[#This Row],[description_override]]) -> Invesco DB US Dollar Index Bullish Fund | L43: IEF | M43: 44
A44: Currencies | B44: EUR | C44: FXE | F44: Invesco CurrencyShares Euro Trust | G44: Euro against the U.S. dollar | H44: 1 | I44: =IF(data_old[[#This Row],[description_override]]="",data_old[[#This Row],[Description_GPT]],data_old[[#This Row],[description_override]]) -> Invesco CurrencyShares Euro Trust | L44: TLT | M44: 45
A45: Currencies | B45: JPY | C45: FXY | F45: Invesco CurrencyShares Japanese Yen Trust | G45: Japanese yen against the U.S. dollar | H45: 1 | I45: =IF(data_old[[#This Row],[description_override]]="",data_old[[#This Row],[Description_GPT]],data_old[[#This Row],[description_override]]) -> Invesco CurrencyShares Japanese Yen Trust | L45: TIP | M45: 40
L46: VTIP | M46: 41
C47: Emhy mdy vnq pff ashr kweb fxi aiq | L47: MBB | M47: 46
L48: MBTA | M48: 47
C49: tip | D49: {=_xlfn.XMATCH(C49:C57,data_old[factor_name])} -> 27 | F49: {=_xlfn.TEXTJOIN(", ",,_xlfn._xlws.FILTER(C49:C57,ISERROR(_xlfn.ANCHORARRAY(D49))))} -> #VALUE! | L49: AGNC | M49: 48
C50: vtip | D50: 28 | L50: VMBS | M50: 49
C51: cmbs | D51: 33 | L51: CMBS | M51: 50
C52: vmbs | D52: 32 | F52: XLK | L52: EMB | M52: 51
C53: gld | D53: 38 | F53: XLI | L53: EMHY | M53: 39
C54: lqd | D54: 19 | F54: XLF | L54: CEW | M54: 56
C55: lqdh | D55: 21 | F55: KRE | L55: IGOV | M55: 52
C56: hyg | D56: 20 | F56: XLC | L56: GLD | M56: 57
C57: hygh | D57: 22 | F57: XLE | J57: tip | L57: SLV | M57: 58
F58: XLY | J58: vtip | L58: USO | M58: 59
F59: XLB | J59: cmbs | L59: DBC | M59: 60
C60: {=_xlfn.TEXTSPLIT(C47,," ")} -> Emhy | D60: {=_xlfn.XMATCH(_xlfn.ANCHORARRAY(C60),data_old[factor_name])} -> 35 | F60: XLV | J60: vmbs | L60: UUP | M60: 53
C61: mdy | D61: #N/A | F61: XLU | J61: gld | L61: FXE | M61: 54
C62: vnq | D62: #N/A | F62: XLP | J62: lqd | L62: FXY | M62: 55
C63: pff | D63: #N/A | F63: IYR | J63: lqdh | L63: XLK | M63: 8
C64: ashr | D64: 18 | J64: hyg | L64: XLI | M64: 9
